Workbook

Sheet IVP amount sanctioned
A1: S.NO | B1: NAME | C1: Grant | D1: phone no. | E1: TEAM ID | F1: pitch deck file | G1: Linkedin | H1: colege linkedin
A2: 1 | B2: Aathavan valanarasu | C2: IVP Selected | D2: 9342049639 | E2: SC-rea6ge | F2: https://drive.google.com/file/d/1icj55HRkpEE6D2YhMiuNvMZMm4qS83lU/view?usp=sharing | G2: https://www.linkedin.com/in/aathavanvalan1/overlay/about-this-profile/?lipi=urn%3Ali%3Apage%3Ad_flagship3_profile_view_base%3BriTF2OrHS4OJ7A6z6xWIuQ%3D%3D | H2: https://www.linkedin.com/school/st.-joseph%27s-college-of-engineering/
A3: 2 | B3: DEEPIKA | C3: IVP Selected | D3: 7395956159 | E3: SC-qtithv | F3: https://drive.google.com/file/d/1OUSJwH2xDGJqMtzE109n35wkSSxf7pE8/view?usp=sharing | G3: https://www.linkedin.com/in/deepika-harigovindan-8974a7315/ | H3: https://www.linkedin.com/school/sri-sairam-homoeopathy-medical-college-inst.-code---209-chennai/about/
A4: 3 | B4: vijaykrishna | C4: IVP Selected | D4: 7305499740 | E4: SC-9e48xs | F4: https://docs.google.com/presentation/d/1RcoSCW7AzUCA6qeqWWS2U1sE5cu9pSk6/edit?usp=sharing&ouid=104277249549708518105&rtpof=true&sd=true | G4: https://www.linkedin.com/in/vijay-krishna-s/ | H4: https://www.linkedin.com/school/college-of-engineering-guindy/posts/?feedView=all
A5: 4 | B5: prempradeep S | C5: IVP Selected | D5: 7708365986 | E5: SC-b4jkfxa | F5: https://drive.google.com/file/d/1VorSWnUlyM-hZbEwKD3-ydU3amct_rNZ/view?usp=sharing | G5: https://www.linkedin.com/in/prem-pradeep-s | H5: https://www.linkedin.com/school/r.m.k-engineering-college/
A6: 5 | B6: S varshaa | C6: IVP Selected | D6: 9952048318 | E6: SC-ywojqq | F6: https://docs.google.com/presentation/d/1r_uJDDSgeSqdewnxUdc17ddlmhNFHjj7/edit?usp=sharing&ouid=104277249549708518105&rtpof=true&sd=true | G6: https://www.linkedin.com/in/varshaaselva/?utm_source=share&utm_campaign=share_via&utm_content=profile&utm_medium=ios_app | H6: https://www.linkedin.com/school/r.m.k-engineering-college/
A7: 6 | B7: purushothaman J | C7: IVP Selected | D7: 9176435615 | E7: SC-aodnso | F7: https://docs.google.com/presentation/d/1Jqm6_fP9FgL0YIqrGdUb-tYgGnQ5StAv/edit?usp=sharing&ouid=104277249549708518105&rtpof=true&sd=true | G7: https://www.linkedin.com/in/purushothaman-jayavel-19b121286?utm_source=share&utm_campaign=share_via&utm_content=profile&utm_medium=android_app | H7: https://www.linkedin.com/school/college-of-engineering-guindy/posts/?feedView=all
A8: 7 | B8: AKSHAY KARTHIKEYAN SK | C8: IVP Selected | D8: 9150452331 | E8: SC-2us6k | F8: https://drive.google.com/file/d/1iWc68HJJJgFSsLxllZe3TY45JOCKec0Z/view?usp=sharing | G8: https://www.linkedin.com/in/akshay--sk?utm_source=share&utm_campaign=share_via&utm_content=profile&utm_medium=ios_app | H8: https://www.linkedin.com/school/psg-college-of-technology/
A9: 8 | B9: suraj(8bix) | C9: IVP Selected | D9: 7397252915 | E9: PX-9cgwli | F9: https://docs.google.com/presentation/d/1zZYNJcw9kwJdoQmeNNB9xPR9xS-vA50l/edit?usp=sharing&ouid=104277249549708518105&rtpof=true&sd=true
A10: 9 | B10: selvakumar | C10: IVP Selected | D10: 9176529116 | E10: CEDAU-01 | F10: https://drive.google.com/file/d/1AFBWvei8iUFsbPvbpVzaLqXAFsFu4jvS/view
A11: 10 | B11: saravanan | C11: IVP Selected | D11: 9791005395 | E11: GP-003 | F11: https://docs.google.com/presentation/d/1b5MrpNXt1nMVPylbe9wylHSNXuDk8qDu/edit?usp=sharing&ouid=104277249549708518105&rtpof=true&sd=true | G11: https://www.linkedin.com/in/saravanan-krishnan-26373b5/
A12: 11 | B12: nikarika ramesh | C12: IVP Selected | D12: 9790004554 | E12: SS-xiv9fo | F12: https://docs.google.com/presentation/d/1UuvB8CG5hK21LYH5-VK1-ElnDGm_z_ck/edit?slide=id.p1#slide=id.p1 | G12: https://www.linkedin.com/in/nikarika-ramesh-242842198/
A13: 12 | B13: Jai Ganesh M | C13: IVP Selected | D13: 7358299188 | E13: cedau-03 | F13: https://drive.google.com/file/d/1f0KPgYZmecnbvsrtUrlSgDz0N6apAXyJ/view?usp=drive_link
A14: 13 | B14: Ranjith. K | C14: IVP Selected | D14: 8883035691 | E14: SC-591xv | F14: https://docs.google.com/presentation/d/1if-EUnplBW5VbKgR7L12TzrIzz_2XseW/edit?usp=sharing&ouid=104277249549708518105&rtpof=true&sd=true
A15: 14 | B15: Prathib Vamsi P (2024-25) | C15: IVP Selected | D15: 9003815145 | E15: cedau-06 | F15: https://docs.google.com/presentation/d/1R3kivspd_3Lf6F3BjWMmF6CfZnH8UGnm/edit?usp=drive_link&ouid=104277249549708518105&rtpof=true&sd=true | G15: https://www.linkedin.com/in/prathip-vamsi/
A16: 15 | B16: Satyendra | C16: IVP Selected | D16: 8092225251 | E16: IPO-ozm1k | F16: https://drive.google.com/file/d/18TKSjzu0XBMIfcvR-TzwQO4eOlv5TP4I/view?usp=sharing
A17: 16 | B17: Thanvi | C17: IVP Selected | D17: 9380184164 | E17: SC-ewhypl | F17: https://drive.google.com/file/d/1qUQVHPhnQ3qdrzuMrbhNc2rdmt8eokYp/view?usp=sharing
A18: 17 | B18: Jeremiah Japhet | C18: IVP Selected | D18: 8148091100 | E18: cedau-11 | F18: https://docs.google.com/presentation/d/1EV9T72VDcsImuuEu7YDiejbpGu0Mvy9q/edit?usp=sharing&ouid=104277249549708518105&rtpof=true&sd=true
A19: 18

Sheet  ivp
A1: Name | B1: EMAIL | C1: PASSWORD | E1: grant status | F1: COMPLETED | G1: schedule date | H1: phone no. | I1: team size | J1: Start up incubated | K1: Start up Registered | L1: women beneficiaries | M1: tier | N1: address | O1: gender | P1: caste | Q1: preinc ; whatsapp group | R1: prototyping ; whatsapp group | S1: TEAM ID | T1: pitch deck file | U1: Total amount
A2: sanjeev / ashwin jk | B2: misdautomation@gmail.com | D2: 25-26 | E2: IVP Selected | F2: COMPLETED | G2: 30.06.26 ( Old ) | H2: 9080861148 | I2: 2 founder | Q2: pre | S2: SC-n4aonf | T2: https://docs.google.com/presentation/d/11pbQZHDGUguVuSuwEOLjm3MfecqFhYTM/edit?usp=sharing&ouid=104277249549708518105&rtpof=true&sd=true
A3: Shakthi Prashanth G | D3: 25-26 | E3: not selected | F3: COMPLETED | G3: 14.11.25 | H3: 7358629515 | R3: yes | S3: cedau-02 | T3: https://drive.google.com/file/d/1nMe76mTFPVo5XOKaU2FZJ_icdnBYZdPt/view?usp=sharing
A4: Kota Nageshwar | B4: abikns@gmail.com | C4: Abikns@12 | D4: 25-26 | E4: IVP Selected | F4: COMPLETED | G4: 30.01.26 | H4: 9363300142 | I4: 1 Founder | K4: private | L4: 0 | M4: Tier 1 | N4: 6/31, G-2 raghas flats postal colony 2nd street, west mambalam, chennai -33 | O4: Male | P4: GENERAL | Q4: preinc | R4: yes | S4: CEDAU-07 | T4: https://drive.google.com/file/d/1n3xy0kOxO2Yp2Z-7V4fJMq_x4C118BzN/view?usp=sharing
A5: Reshma Ch | B5: binureshma110@gmail.com | C5: Binureshma@110 | D5: 25-26 | E5: not selected | F5: COMPLETED | G5: 12.01.26 | H5: 9940432697 | M5: Tier 1 | N5: 26 B Sivakami Nagar Korattur Chennai 600076 | O5: Female | P5: GENERAL | R5: yes | S5: CEDAU-04 | T5: https://docs.google.com/presentation/d/1Ntxw63M7DcsoxOIi704XmNM8A5r7ezz0/edit?usp=sharing&ouid=104277249549708518105&rtpof=true&sd=true
A6: Gokkul M | B6: mrgokkul@gmail.com | C6: Gokkul21341. | D6: 25-26 | E6: not selected | F6: COMPLETED | G6: 13.02.26 | H6: 9043405357 | M6: Tier 2 | N6: 2/93-2 Melachithram street, kattuparamakudi taluk, paramakudi, ramanathapuram 623707 | O6: Male | P6: OBC | R6: yes | S6: cedau-05 | T6: https://drive.google.com/file/d/1p4i1zajYvfSaNqnNbQ1cEiLOuEYvjDSJ/view?usp=sharing
A7: Praveen Kumar R | D7: 25-26 | E7: IVP Selected | F7: COMPLETED | G7: 30.01.26 | H7: 8148402208 | I7: 2 Founders + 10 employees | K7: Private | L7: 9 + 2515 other women benenficiaries | M7: Tier 3 | Q7: preinc | R7: yes | S7: cedau-19 | T7: https://docs.google.com/presentation/d/14q8HVWXmbsPywVvXUfo8vnvagpaozDFv/edit?usp=sharing&ouid=104277249549708518105&rtpof=true&sd=true
A8: Semmozhi Selvam S P | B8: semmozhiselvamsp@gmail.com | C8: selv@m2301 | D8: 25-26 | E8: IVP Selected | F8: COMPLETED | G8: 30.01.26 | H8: 6382396276 | I8: 1 Founder | K8: - | L8: 0 | M8: Tier 3 | N8: 121, Agraharam street, vembanoor, Moolangudi post, manjakkudi, KUDAVASAL, THIRUVARUR , 612610 | O8: Male | P8: OBC | Q8: preinc | R8: yes | S8: SC-8heikl | T8: https://docs.google.com/presentation/d/1L7eTzNmLVNQ7B7omSBjUOMv_Fo6yEUuj/edit?usp=sharing&ouid=104277249549708518105&rtpof=true&sd=true
A9: Vishnu Prasanna D | B9: vishnuprasanna.dl@gmail.com | C9: Vishnuprasanna@123 | D9: 25-26 | E9: not selected | F9: COMPLETED | G9: 30.01.26 | H9: 8608487249 | M9: Tier 3 | N9: 413, South Street, Bangalore main road, Thokkavadi, Thukkapet post, Chengam | O9: Male | P9: SC | R9: yes | S9: CEDAU-08 | T9: https://docs.google.com/presentation/d/16s3ed2pzozhPf-uAvWKXGMnci6USeI9O/edit?usp=sharing&ouid=104277249549708518105&rtpof=true&sd=true
A10: Sakthivel S | B10: iyyansoft@gmail.com | C10: Pw4IyyanSoft | D10: 25-26 | E10: not selected | F10: COMPLETED | G10: 21.07.26 | H10: 9944085762 | M10: Tier 1 | N10: Plot 30/2, 2nd St, Ramapuram, Officers Colony, Adambakkam, Chennai, Tamil Nadu 600088 | O10: Male | P10: SC | R10: yes | S10: CEDAU-09 | T10: https://docs.google.com/presentation/d/1PSNb4KAfoToZb3vJ3ZDzvwtjMzaZ7y4H/edit?usp=sharing&ouid=104277249549708518105&rtpof=true&sd=true
A11: Thiru Kumaran Nr | B11: kumaranthiru346@gmail.com | C11: Kumaranthiru@346 | D11: 25-26 | E11: not selected | F11: COMPLETED | G11: 10.03.26 | H11: 7305184227 | M11: Tier 1 | N11: 60, Queen Victoria Road, Ambal City, Poonamallee, 600056 | O11: Male | P11: OBC | R11: yes | S11: CEDAU-10 | T11: https://docs.google.com/presentation/d/1GpS3lq2AUHyhjevALarZz2JiP0aXoCf6/edit?usp=sharing&ouid=104277249549708518105&rtpof=true&sd=true
A12: Ms. M.Nirmaladevi Senthilkumar | B12: amuchitraditionalfoods@gmail.com | C12: Snsurya@1 | D12: 25-26 | E12: IVP Selected | F12: COMPLETED | G12: 29.07.26 | H12: 9688299333 | M12: Tier 2 | N12: No - 23, Sri Ram Nagar, Kooram Gate, Kancheepuram - 631552 | O12: Female | P12: GENERAL | Q12: pre | R12: yes | S12: CEDAU-29 | T12: https://drive.google.com/file/d/1sFC4pPdrt2TlqHFgBbsQ0UUPSKQ--6He/view?usp=sharing
A13: Dr N. Vasudevan | D13: 25-26 | E13: not selected | F13: COMPLETED | G13: 02.03.26 | H13: 9444910521 | R13: yes | S13: CEDAU-12 | T13: https://drive.google.com/file/d/1Em_cP1ecMnwQxTbmcsLeqcczsvVaZdln/view?usp=sharing
A14: Sriranjan | B14: arkfx@tuta.io | C14: Arkfx@12 | D14: 25-26 | E14: IVP Selected | F14: COMPLETED | G14: 29.07.26 | H14: 7358011726 | M14: Tier 1 | N14: 2nd main road , kalaimagal nagar , ekkattuthangal , chennai - | O14: Male | P14: OBC | Q14: preinc | R14: yes | S14: Sc-wx4f45 | T14: https://docs.google.com/presentation/d/1WTC753AOBmjf_nBHKMzSdm2saxshkMHi/edit?usp=sharing&ouid=104277249549708518105&rtpof=true&sd=true
A15: Subanesh | D15: 25-26 | E15: not selected | F15: COMPLETED | G15: 25.05.26 | H15: 7395903061 | S15: cedau-14
A16: P.N. Chendilnadan | F16: not done | S16: cedau-15
A17: Harish Kumar | F17: not done | H17: 8248375363 | S17: cedau-16
A18: Harihara Prabhu | D18: 25-26 | E18: not selected | F18: COMPLETED | H18: 6369492510 | R18: yes | S18: cedau-17 | T18: https://docs.google.com/presentation/d/1prMqTR-f9CdW-27PIrxhheLFhTq5VHGk/edit?usp=sharing&ouid=104277249549708518105&rtpof=true&sd=true
A19: Selvakumar | B19: - | D19: 25-26 | E19: IVP Selected | F19: COMPLETED | G19: 29.07.25 | H19: 9176529116 | I19: 2 Founder | K19: private | M19: Tier 1 | N19: Perungudi, Kancheepuram | O19: Male | P19: OBC | Q19: preinc | R19: yes | S19: CEDAU-01 | T19: https://drive.google.com/file/d/1AFBWvei8iUFsbPvbpVzaLqXAFsFu4jvS/view?usp=drive_link | U19: 3,00,000
A20: Suraj(8Bix) | B20: - | D20: 25-26 | E20: IVP Selected | F20: COMPLETED | G20: 29.07.25 | H20: 7397252915 | I20: 3 Founder | K20: private | L20: 0 | M20: Tier 1 | N20: N.No. 137, O. No.62, V.M. Street, Royapettah, Chennai, Chennai, Tamil Nadu, India, 600014. | Q20: preinc | R20: yes | S20: PX-9cgwli | T20: https://docs.google.com/presentation/d/1zZYNJcw9kwJdoQmeNNB9xPR9xS-vA50l/edit?usp=sharing&ouid=104277249549708518105&rtpof=true&sd=true | U20: 297000
A21: Aarjun Thiagarajan | F21: not done | H21: 8619792227 | S21: CEDAU-20 | T21: nil
A22: Dr.R.Senthilnathan | B22: drsenthil2460@gmail.com | C22: Drsenthil@2460 | D22: 25-26 | E22: absent | F22: COMPLETED | G22: 21.07.26 | H22: 9894119040 | M22: Tier 2 | N22: D10/77 -1b S.G.pudur Arasur Post, coimbatore-641407. Tamil Nadu. | O22: Male | P22: GENERAL | S22: cedau-22 | T22: https://docs.google.com/presentation/d/19KDfehkfiMjlVS4MmIh7c7SpujP0fHpK/edit?usp=sharing&ouid=104277249549708518105&rtpof=true&sd=true
A23: Aathavan Valanarasu | B23: aathavan.valanarasu5@gmail.com | C23: Aathavan@123 | D23: 25-26 | E23: IVP Selected | F23: COMPLETED | G23: 29.07.25 | H23: 9342049639 | I23: 4 Founders | L23: 2 | M23: Tier 1 | N23: Block C2, Toddhunter Nagar, PWD quarters,Saidapet, chennai-15 | O23: Male | P23: OBC | Q23: preinc | R23: yes | S23: SC-rea6ge | T23: https://drive.google.com/file/d/1icj55HRkpEE6D2YhMiuNvMZMm4qS83lU/view?usp=sharing | U23: 300000
A24: Nelson | B24: sathyanelson.m@gmail.com | C24: TrinityWorldReal!7 | D24: 25-26 | E24: not selected | F24: COMPLETED | G24: 05.06.26 | H24: 7358734289 | M24: Tier 1 | N24: SKCL Techsquare, Lazer Stret, South Phase, SIDCO Industrial Estate, Guindy, Chennai | O24: Male | P24: General | R24: yes | S24: cedau-25 | T24: https://docs.google.com/presentation/d/1svlsWidPE9Mo4IunAUtMRWoX6-3FELRG/edit?usp=sharing&ouid=104277249549708518105&rtpof=true&sd=true
A25: Prathib Vamsi P | D25: 25-26 | E25: IVP Selected | F25: COMPLETED | G25: 28.11.25 | H25: 9003815145 | I25: 2 founder +20 emp = 22 | K25: private | L25: 13 | M25: Tier 3 | Q25: preinc | S25: cedau-06 | T25: https://docs.google.com/presentation/d/1R3kivspd_3Lf6F3BjWMmF6CfZnH8UGnm/edit?usp=drive_link&ouid=104277249549708518105&rtpof=true&sd=true | U25: 200000
A26: Navinkrishna K | B26: krishnanavin03@gmail.com | C26: Navi@1 | D26: 25-26 | E26: absent | F26: COMPLETED | G26: 21.07.26 | H26: 8122980305 | M26: Tier 1 | N26: NO.106/1024, T.H ROAD, KALADIPET,THIRUVOTTIYUR | O26: Male | P26: GENERAL | R26: yes | S26: cedau-27 | T26: https://docs.google.com/presentation/d/1d8-jiX9yr-sMsCczAoqAxNddaCFgD9Lb/edit?usp=sharing&ouid=104277249549708518105&rtpof=true&sd=true
A27: G Rathi | B27: rathiraghuprakash@gmail.com | D27: 25-26 | E27: Yet to present | F27: COMPLETED | H27: 9952437272 | R27: yes | S27: CEDAU-28 | T27: https://docs.google.com/presentation/d/1FXIGWLrifrRMQscDpQMdcN-VyYJj8lRY/edit?usp=sharing&ouid=104277249549708518105&rtpof=true&sd=true
A28: Athithya Rayan R | D28: 25-26 | E28: IVP Selected | F28: COMPLETED | G28: 28.11.25 | H28: 6384712172 | I28: 2 founders | J28: kabif - preinc | K28: Private | L28: 0 | M28: Tier 3 | Q28: preinc | R28: yes | S28: cedau-24 | T28: https://drive.google.com/file/d/1TQHqyQdolrHhxhMYy4F0qSG_uUNK2Vpv/view?usp=sharing | U28: 300000
A29: S Varshaa | B29: varshaaselva@gmail.com | C29: Varshaaselva@06 | D29: 25-26 | E29: IVP Selected | F29: COMPLETED | G29: 28.11.25 | H29: 9952048318 | I29: 3 founders | K29: connect to yash | L29: 1 | M29: Tier 1 | N29: No.1,Babuji Nagar, Thiru VI Ka Nagar, Vinayakapuram, Lakshmipuram, Chennai, Tamil Nadu 600066 | O29: Female | P29: OBC | Q29: preinc | R29: yes | S29: SC-ywojqq | T29: https://docs.google.com/presentation/d/1r_uJDDSgeSqdewnxUdc17ddlmhNFHjj7/edit?usp=sharing&ouid=104277249549708518105&rtpof=true&sd=true | U29: 300000
A30: V Vijaya kumar | B30: roxercub@gmail.com | C30: Roxercub@123 | D30: 25-26 | E30: IVP Selected | F30: COMPLETED | G30: 21.07.26 | H30: 9884706822 | Q30: pre | R30: yes | S30: cedau-26 | T30: https://docs.google.com/presentation/d/1F6UprY1Bo46MyZFlV5jxGpMy8RoiGBv4/edit?usp=sharing&ouid=104277249549708518105&rtpof=true&sd=true
A31: Nagendra Dasari | B31: muralidora504@gmail.com | C31: Nagendra@2608 | D31: 25-26 | E31: NOt selected | F31: COMPLETED | G31: 12.08.26 | H31: 8555874504 | M31: Tier 1 | N31: Address of the Company1/37, MIG-II, Block1, TNHB-1500 Flat, SHOLLINGANALLUR, CHENNAI, TAMIL NADU | O31: Male | P31: GENERAL | R31: yes | S31: CEDAU-32 | T31: https://docs.google.com/presentation/d/1gXlydx6GGyjViK9BH2DExwsitvhYxcTC/edit?usp=sharing&ouid=104277249549708518105&rtpof=true&sd=true
A32: kalyani patra | B32: aswiga91@gmail.com | C32: Kalyani*1 | D32: 25-26 | E32: IVP Selected | F32: COMPLETED | G32: 21.07.26 | H32: 8608499779 | M32: Tier 1 | N32: No 1 chithra enclave, Aarthi nagar, East Tambaram | O32: Female | P32: OBC | S32: ipo-28zbru | T32: https://docs.google.com/presentation/d/1YFjs7wBOE-FwqPCIpm92exmo75IKjAZU/edit?usp=sharing&ouid=104277249549708518105&rtpof=true&sd=true
A33: Akash | B33: akashr.annauniv@gmail.com | C33: Akashr.annauniv@12 | D33: 25-26 | E33: NOt selected | F33: COMPLETED | G33: 12.08.26 | H33: 8754728402 | M33: Tier 1 | N33: 69/122, Vannier Street, Chooliamedu, Chennai - 600 094 | O33: Male | P33: SC | R33: yes | S33: CEDAU-34 | T33: https://docs.google.com/presentation/d/1vvNjk_1_mJJVLriLTt7MFXxwPhGuccHt/edit?usp=sharing&ouid=104277249549708518105&rtpof=true&sd=true
A34: Surendar K | B34: arcadeslevel@gmail.com | C34: SIH@aot6 | D34: 25-26 | E34: NOt selected | F34: COMPLETED | G34: 12.08.26 | H34: 93635 32027 | M34: Tier 3 | N34: 118/78,Nappalaya Street,Villupuram,Villupuram - 605602 | O34: Male | P34: OBC | R34: yes | S34: CEDAU-35 | T34: https://drive.google.com/file/d/1iMYV5dCGbdlUDh24yHlB6oced5JQ3Bc2/view?usp=sharing
A35: Hari Krishnan | B35: Tynkohari@123 | C35: harikrisrr@gmail.com | D35: 25-26 | E35: Yet to present | F35: COMPLETED | H35: 8939797268 | R35: yes | S35: CEDAU-36 | T35: https://drive.google.com/file/d/1Jpe5V4pSn5lJy2WIv8hH5IrXrD21Dcd2/view?usp=sharing
A36: Abinaya | B36: abinaya.auceg@gmail.com | C36: ATbian@2026 | D36: 25-26 | E36: Yet to present | F36: COMPLETED | H36: 9080721623 | M36: Tier 2 | N36: 54/3, bypass road, Melasanthapalayam, Musiri, Trichy -621211 | O36: Female | P36: OBC | R36: yes | S36: CEDAU-37 | T36: https://docs.google.com/presentation/d/1mFOPCn7ZHKzvNicJaWvacJD6nFsAMFeD/edit?usp=sharing&ouid=104277249549708518105&rtpof=true&sd=true
A37: Aparup Roy | B37: aparupdgp713217@gmail.com | C37: Gopalmath#713217 | D37: 25-26 | E37: Yet to present | F37: COMPLETED | H37: 9476478885 | M37: Tier 1 | N37: College of Engineering Guindy, Anna University, 12, Sardar Patel Road, Guindy, Chennai, Tamil Nadu, 600025 | O37: Male | P37: GENERAL | R37: yes | S37: cedau-38 | T37: https://drive.google.com/file/d/1ghr4wKJHaB9cM-p8gmva4wiN-FUH3Mmg/view?usp=sharing
A38: Anantha Kumar | B38: Contacts@ztorys.com | C38: Ztorys@2026! | D38: 25-26 | E38: Yet to present | F38: COMPLETED | H38: 7845471602 | M38: Tier 1 | N38: 8th floor, 85, Anna Salai, Guindy Institutional Area, SIDCO Industrial Estate, Guindy, Chennai, Tamil Nadu 600032 | O38: Male | R38: yes | S38: cedau-39 | T38: https://drive.google.com/file/d/1zwrG0J_pCo6yZG42LAl7d5Jx_zdp-LZ_/view?usp=sharing
A39: Kartheka Bojan | B39: karthekabojan@gmail.com | C39: Innovation2026 | D39: 26-27 | E39: Yet to present | F39: COMPLETED | H39: 8870169974 | R39: yes | S39: cedau-40 | T39: https://drive.google.com/file/d/1uDPKPYE5yjMZJlz_KH9e1FA4BpniXAqV/view?usp=sharing
A40: B Arumugapandian | D40: 26-27 | E40: Yet to present | F40: COMPLETED | H40: 9380523384 | S40: cedau-41 | T40: https://docs.google.com/presentation/d/17jQg9XR0LqRPj3eRC3a4YTSCC34bS2xC/edit?usp=sharing&ouid=104277249549708518105&rtpof=true&sd=true
A41: Sathishraj Selvaraj | B41: Sonucreativelabs@gmail.com | C41: Sonu09@edii | D41: 26-27 | E41: Yet to present | F41: COMPLETED | H41: 6379496755 | S41: cedau-42 | T41: https://docs.google.com/presentation/d/1oFUOmIKNt2GIY5MFtUsV5wWWwNS22Cvx/edit?usp=drive_link&ouid=104277249549708518105&rtpof=true&sd=true
A42: surya Prasad | D42: 26-27 | E42: yet to present | F42: COMPLETED | H42: 9952351453 | S42: cedau-43 | T42: https://docs.google.com/presentation/d/1q6DSpwV1hx2Rm-kzFBpcLePgyMdtoYN8/edit?usp=drive_link&ouid=104277249549708518105&rtpof=true&sd=true
A43: Vijay Samuel G | F43: PENDING | H43: 9952451033 | S43: cedau-45
A44: chandrika murali / arun | D44: 26-27 | E44: Yet to present | F44: COMPLETED | H44: 7708592890 | S44: cedau-46 | T44: https://drive.google.com/file/d/1DlTjyBNXXg7rvTQiMFflasG6_1AsoxPH/view?usp=drive_link
A45: Lakshmi kala narasimhan | B45: lakshmikala.n@choiice.in | C45: Kala5252***$$$ | D45: 26-27 | E45: Yet to present | F45: COMPLETED | H45: 9964800059 | R45: yes | S45: cedau-47 | T45: https://docs.google.com/presentation/d/12LN-QBBpvWc6tcuxKPHLibN5bA6aTuD1/edit?usp=sharing&ouid=104277249549708518105&rtpof=true&sd=true
A46: Pooja sai | B46: poojagokul79@gmail.com | C46: Nova@3eco | D46: 26-27 | E46: Yet to present | F46: COMPLETED | H46: 7012679913 | R46: yes | S46: cedau-48 | T46: https://docs.google.com/presentation/d/1a1-cslN2_rNuqqxhNwMaXR9GYvG_YwrY/edit?usp=sharing&ouid=104277249549708518105&rtpof=true&sd=true
A47: Suhasini B | B47: suhasini090604@gmail.com | C47: Startup@26 | D47: 26-27 | E47: Yet to present | F47: COMPLETED | H47: 7358088146 | S47: cedau-49 | T47: https://docs.google.com/presentation/d/1m8L6g7SZESpUVObADCFChgYbYZngLRPi/edit?usp=sharing&ouid=104277249549708518105&rtpof=true&sd=true
A48: Malar | B48: smtechsols@gmail.com | C48: Sreemahalakshmi23$ | D48: 26-27 | E48: Yet to present | F48: COMPLETED | H48: 9843545796 | R48: yes | S48: cedau-50 | T48: https://drive.google.com/file/d/16dmS9BkwYK-znvr3Rkj5DTs7hprWCF1E/view?usp=sharing
A49: Giritharan Janakiraman | D49: 26-27 | E49: Yet to present | F49: COMPLETED | H49: 8778373517 | S49: CEDAU-51 | T49: https://docs.google.com/presentation/d/1XuDjadqAkzk4-vE3pLzlhAgVZAATO4Mz/edit?usp=drive_link&ouid=104277249549708518105&rtpof=true&sd=true
A50: Uma Maheshwari | B50: send2vmdecor@gmail.com | C50: Velpari@3010 | F50: comPLETED | H50: 98409 94922 | S50: CEDAU-52 | T50: https://docs.google.com/presentation/d/1afpjyLh9-5tS8BVp6n7kGe_cPta3vbdj/edit?usp=drive_link&ouid=104277249549708518105&rtpof=true&sd=true
A51: Sushmitha Shree K | B51: krishyesh@gmail.com | C51: Voucher@2026 | F51: COMPLETED | H51: 91500 49921 | S51: CEDAU-53 | T51: https://docs.google.com/presentation/d/1OBy1oQxGUVgRaEYu_WITxGvuiEMEHJjK/edit?usp=drive_link&ouid=104277249549708518105&rtpof=true&sd=true
A52: keerthi kassan / jayalalitha | B52: jksemitech@gmail.com | C52: Keerthi24$ | D52: 26-27 | E52: Yet to present | F52: COMPLETED | H52: 9551075056 | S52: CEDAU-54 | T52: https://drive.google.com/file/d/1MZmmKsUva2j60JwGRRjdJHdHuwsOg9eV/view?usp=drive_link
A53: nithiyananthan M | D53: 26-27 | E53: Yet to present | F53: completed | H53: 9788546486 | R53: yes | S53: CEDAU-55
A54: Manikandan
A55: Dr. J. Manikandan
A56: Roshan Maharajan
A57: Nathiya
A58: Dr. G. Ananthi
A59: EVA virgin cocunut oil
A60: sivasubramanian | F60: PENDING | H60: 9940270031 | S60: CEDAU-56
A61: Jayachandran
A62: Sri govarasan
A63: Shanmuga bhuvaneswar | B63: bhuvan.ramalingam@hotmail.com | C63: Finfresh123$ | D63: 26-27 | E63: Yet to present | F63: completed | H63: 9943704677 | S63: cedau-57 | T63: https://drive.google.com/file/d/1UlrxM_AHdk68OEtgluBi7kH5FiObeWnn/view?usp=drive_link
A64: Lakshanaa A | D64: 26-27 | E64: Yet to present | F64: completed | H64: 98400 63038 | R64: yes | S64: cedau-58
A65: R V Aswiga | B65: aswiga.rv@vit.ac.in | C65: Aswiga*1 | D65: 25-26 | E65: IVP Selected | F65: COMPLETED | G65: 21.07.26 | H65: 9790341644 | M65: Tier 3 | N65: No-1 Aarthi Nagar, Chithra Enclave, Selaiyur | O65: Female | P65: OBC | Q65: preinc | R65: yes | S65: IPO-mf6d59 | T65: https://docs.google.com/presentation/d/1d_QPiSCNKK8qPBBvYe2cLPeJl46ZqELP/edit?usp=sharing&ouid=104277249549708518105&rtpof=true&sd=true
A66: AKASH RS | B66: satishkumar.veducate@gmail.com | C66: Satish@2025 | D66: 25-26 | E66: IVP Selected | F66: COMPLETED | G66: 21.07.26 | H66: 7305494413 | M66: Tier 1 | N66: 23/31, Appasamy St, Brindavan Extension, Kodambakkam, Chennai, Tamil Nadu 600024 | O66: Male | P66: GENERAL | Q66: pre | R66: yes | S66: SC-e4ss8o | T66: https://docs.google.com/presentation/d/1WbLTAapfRoC1Jw8AjPoUSNHbaO1Bni6Q/edit?usp=sharing&ouid=104277249549708518105&rtpof=true&sd=true
A67: P. Paneer Selvam | B67: pannerselvamece1368@gmail.com | C67: Panner@136 | D67: 25-26 | E67: IVP Selected | F67: COMPLETED | G67: 21.07.26 | H67: 8675058253 | M67: Tier 2 | N67: 2/212, Putheri STreet, Manampathy, Uthiramerur, Kancheepuram - 603403 | O67: Male | P67: OBC | Q67: preinc | R67: yes | S67: sc-s98rzx | T67: https://docs.google.com/presentation/d/1R62ldDA80PBjNGZCWUlo8ednBrIS-Aq_/edit?usp=sharing&ouid=104277249549708518105&rtpof=true&sd=true
A68: Jai Ganesh M | B68: intramobility@gmail.com | C68: Welcome@123 | D68: 25-26 | E68: IVP Selected | F68: COMPLETED | G68: 19.12.25 | H68: 7358299188 | I68: 3 founders | K68: Private | L68: 0 | M68: Tier 1 | N68: RMZ Millenia Park , Perungudi ,chennai | Q68: preinc | R68: yes | S68: cedau-03 | T68: https://drive.google.com/file/d/1f0KPgYZmecnbvsrtUrlSgDz0N6apAXyJ/view?usp=drive_link | U68: 300000
A69: akash siva teja | B69: skvinayagham@gmail.com | C69: Aakash*1 | D69: 25-26 | E69: not selected | F69: COMPLETED | G69: 21.07.26 | H69: 8121564541 / 7981973211 | M69: Tier 1 | N69: No 1 Aarthi Nagar Chithra Enclave | O69: Male | P69: OBC | S69: ipo-5av34m | T69: https://docs.google.com/presentation/d/15MGrNRcJXUSMXUaCjctPr49PzbioluZx/edit?usp=sharing&ouid=104277249549708518105&rtpof=true&sd=true
A70: SA siva sooryaa | B70: sasivasooryaa@gmail.com | C70: Sivasooryaasai@24 | D70: 25-26 | E70: not selected | F70: COMPLETED | G70: 02.03.26 | H70: 9488505516 | M70: Tier 1 | N70: No 9, thiruvengadam apartments, kongu nagar 1st street, mogappair, chennai-600037 | O70: Male | P70: OBC | R70: yes | S70: IPO-7i7nb | T70: https://drive.google.com/file/d/1P71FvYpItc1HA5flnMDZjHqgEnahKtvC/view?usp=sharing
A71: Sathya prakash | B71: sathyaprakash1029@gmail.com | C71: Sathya@#2003 | D71: 25-26 | E71: Yet to present | F71: COMPLETED | H71: 7401252411 | M71: Tier 1 | N71: 7/35 Ambethkar street mannivakkam | O71: Male | P71: SC | R71: yes | S71: ipo-axim | T71: https://docs.google.com/presentation/d/160cPo5CjhoTEcnbUqeoL4E6ufPBT0gxj/edit?usp=sharing&ouid=104277249549708518105&rtpof=true&sd=true
A72: S Thangavel | D72: 25-26 | E72: not selected | F72: COMPLETED | G72: 25.05.26 | H72: 9750366570 | S72: IPO-mf2rwi | T72: https://docs.google.com/presentation/d/1O-4Y-K-HaEKILeDFo5VeCQkQP8ahl1TS/edit?usp=sharing&ouid=104277249549708518105&rtpof=true&sd=true
A73: Akshay Karthikeyan Sk | B73: 23pc05@psgtech.ac.in | C73: Akshay@1906 | D73: 25-26 | E73: IVP Selected | F73: COMPLETED | G73: 19.12.25 | H73: 9150452331 | I73: 3 | Q73: preinc | R73: yes | S73: SC-2us6k | T73: https://drive.google.com/file/d/1iWc68HJJJgFSsLxllZe3TY45JOCKec0Z/view?usp=sharing | U73: 300000
A74: Purushothaman J | B74: purushj1996@gmail.com | C74: Purush@1996 | D74: 25-26 | E74: IVP Selected | F74: COMPLETED | G74: 19.12.25 | H74: 9176435615 | I74: 1 found + 3emp | L74: 1 | M74: Tier 1 | N74: NO 325, malligai poo nagar, adyar, chennai 600020 | O74: Male | P74: SC | Q74: preinc | R74: yes | S74: SC-aodnso | T74: https://docs.google.com/presentation/d/1Jqm6_fP9FgL0YIqrGdUb-tYgGnQ5StAv/edit?usp=sharing&ouid=104277249549708518105&rtpof=true&sd=true | U74: 300000
A75: Ranjith Karthikeyan | D75: 25-26 | E75: IVP Selected | F75: COMPLETED | G75: 17.04.25 | H75: 8883035691 | I75: 1 found | K75: Private | L75: 0 | M75: Tier 3 | N75: No 1/72 Near mathi rice mill Kovilur Pudukottai 622301 | O75: Male | P75: SC | Q75: preinc | R75: yes | S75: SC-591xv | T75: https://docs.google.com/presentation/d/1if-EUnplBW5VbKgR7L12TzrIzz_2XseW/edit?usp=sharing&ouid=104277249549708518105&rtpof=true&sd=true | U75: 200000
A76: E B Priyanka | D76: 25-26 | E76: not selected | F76: COMPLETED | G76: 25.05.26 | H76: 8098927503 | S76: IPO-slh17e | T76: https://docs.google.com/presentation/d/1MuQWS_G1HplPIFw5TjucIqjiErc1qDXv/edit?usp=sharing&ouid=104277249549708518105&rtpof=true&sd=true
A77: Ron Carter | B77: Did Not Disclose | C77: Did Not Disclose | F77: not done | H77: 9840663260 | M77: tier 2 | N77: Kelambakkam | O77: male | P77: BC | S77: IPO-v26g0f
A78: Aswath Vishnu.E | B78: aswathvishnu73@gmail.com | C78: Aswathvishnu@73 | D78: 25-26 | E78: not selected | F78: COMPLETED | G78: 11.07.25 | H78: 7845414195 | M78: Tier 3 | N78: E76 mathana gopal thilagam, agaram chinnamalanam patti, near surabi college, chinnamalanam patti, Dindigul, Tamil Nadu, Dindigul- 624709 | O78: Male | P78: OBC | R78: yes | S78: PX-3ki6nJ | T78: https://docs.google.com/presentation/d/17APXum_6v75puPYL7bfg9TQt7yJJxsxX/edit?usp=sharing&ouid=104277249549708518105&rtpof=true&sd=true
A79: Jeremiah Japhet | D79: 25-26 | E79: IVP Selected | F79: COMPLETED | G79: 15.10.25 | H79: 8148091100 | I79: 1 found + 35 emp | K79: - | L79: 5 | M79: Tier 3 | N79: No 7/2, 5th Street, Rajendra Nagar, Palayamkottai, Tirunelveli - 627002 | O79: Male | P79: OBC | Q79: preinc | R79: yes | S79: cedau-11 | T79: https://docs.google.com/presentation/d/1EV9T72VDcsImuuEu7YDiejbpGu0Mvy9q/edit?usp=drive_link&ouid=104277249549708518105&rtpof=true&sd=true | U79: 297000
A80: Vetriprasath | B80: vetriprasath59@gmail.com | C80: Vetriprasath@59 | D80: 25-26 | E80: not selected | F80: COMPLETED | G80: 31.10.26 | H80: 9600407657 | M80: Tier 2 | N80: 157,1st cross , Saravanapuram Allithurai, Tiruchirappalli, Tamil Nadu, 620102 | O80: Male | P80: OBC | R80: yes | S80: PX-875q6 | T80: https://drive.google.com/file/d/1tQYpjd0ys7bIEyfdKiGLxZMGevfiyhZ-/view?usp=sharing
A81: Vijaykrishna | B81: svijaykrishna12@gmail.com | C81: Svijaykrishna@12 | D81: 25-26 | E81: IVP Selected | F81: COMPLETED | G81: 15.10.25 | H81: 7305499740 | I81: 3found + 1emp | J81: - | K81: private | L81: 0 | M81: Tier 1 | N81: 3rd Main Road, Vijaya Nagar, Velachery, Chennai - 600042 | O81: Male | P81: GENERAL | Q81: preinc | R81: yes | S81: SC-9e48xs | T81: https://docs.google.com/presentation/d/1RcoSCW7AzUCA6qeqWWS2U1sE5cu9pSk6/edit?usp=sharing&ouid=104277249549708518105&rtpof=true&sd=true | U81: 300000
A82: Kotha Vamsi | B82: Vamsi8kotha123@gmail.com | C82: Vamsimadhu*charge1 | D82: 25-26 | E82: not selected | F82: COMPLETED | G82: 19.12.25 | H82: 6381784015 | M82: Tier 1 | N82: no 31 thirumalai nagar 2nd mainroad kolathur | O82: Male | P82: OBC | R82: no | S82: PX-cm2mr | T82: https://drive.google.com/file/d/1_oyvkYV9seEqEx0ZpV2wRqZi6JqcpK3a/view?usp=sharing
A83: S PRITHIV RAJ | B83: prithiviraj71173@gmail.com | C83: Ngz8GvV2pb2d4@6 | D83: 25-26 | E83: absent | F83: COMPLETED | G83: 12.08.26 | H83: 8220316694 | M83: Tier 2 | N83: Address of the Company1140 Hussain bhai thottam Thadagam road Gandhi park Coimbatore 641002 | O83: Male | P83: obc | R83: yes | S83: PX-iryrmq | T83: https://docs.google.com/presentation/d/16iZHJVd8g9Vuf773Dx3vQinjIncBZeZc/edit?usp=sharing&ouid=104277249549708518105&rtpof=true&sd=true
A84: Kavyashri K | B84: kavyashri.workspace@gmail.com | C84: Ka@210802 | D84: 25-26 | E84: Yet to present | F84: COMPLETED | H84: 6380541322 | M84: Tier 1 | N84: 7, Maruthi Avenue, Govarthanagiri, Avadi, Chennai - 600071 | O84: Female | P84: OBC | R84: yes | S84: PX-jq5l4j
A85: Sriram | B85: - | D85: 25-26 | E85: ABSENT | F85: COMPLETED | G85: 12.09.25 | H85: 6374960838 | R85: no | S85: PX-ptkk1
A86: Prempradeep S | B86: prempradeep038@gmail.com | C86: Prempradeep@038 | D86: 25-26 | E86: IVP Selected | F86: COMPLETED | G86: 14.11.25 | H86: 7708365986 | I86: 1found + 3 emp | J86: pre in c @ iitm | K86: - | L86: 1 | M86: Tier 1 | N86: No.10, Pon Vedha Apartments, Tamarai Nagar 2nd street, Cholambedu road, Ambattur, Chennai, Tamil Nadu - 600054 | O86: Male | P86: GENERAL | Q86: preinc | R86: yes | S86: SC-b4jkfxa | T86: https://drive.google.com/file/d/1VorSWnUlyM-hZbEwKD3-ydU3amct_rNZ/view?usp=sharing | U86: 300000
A87: Antanet Anusha G | B87: anuthiraviam@gmail.com | C87: Anuthiraviam@12 | D87: 25-26 | E87: absent | F87: COMPLETED | G87: 14.11.25 | H87: 9384233122 | M87: Tier 3 | N87: 2/3/59, Bharathiyar street, perumalmalai, Kodaikanal -624101 | O87: Female | P87: OBC | R87: yes | S87: Px-xocu6 | T87: https://docs.google.com/presentation/d/1GTUuQ193iH8aPr4qTGOjSh7oj8tF1aN7/edit?usp=sharing&ouid=104277249549708518105&rtpof=true&sd=true
A88: Tharaneeswharan | B88: tharaneeswharan5555@gmail.com | C88: Tharaneeswharan@55 | D88: 25-26 | E88: not selected | F88: COMPLETED | G88: 15.10.25 | H88: 9361054415 | M88: Tier 3 | N88: vakanathundu thottam bavathi nagar kanakampalayam. gobichettipalayam (tk), erode (dt) ..pin - 638505 | O88: Male | P88: GENERAL | R88: yes | S88: SC-07g6mo | T88: https://docs.google.com/presentation/d/1zH7oPcHBU2ypBkNZMJ-UzIHydcevpHCz/edit?usp=sharing&ouid=104277249549708518105&rtpof=true&sd=true
A89: Vishnu Priya V | B89: vishnu.act06@gmail.com | C89: @Vishnu21 | D89: 25-26 | E89: IVP Selected | F89: COMPLETED | G89: 14.11.25 | H89: 9789962388 | I89: 1 founder | K89: connect to yash | L89: 1 | M89: Tier 1 | N89: B3 mahalakshmi flats 2nd floor brahmin lane, saidapet, chennai-600015 | O89: Female | P89: OBC | Q89: preinc | R89: yes | S89: SS-e7fr19 | T89: https://docs.google.com/presentation/d/1g09SgWmRT8I0jsBBRlc4ZMBRmQxHlpzhdG2wl8bLoEM/edit?usp=sharing | U89: 300000
A90: MANI MOZHI VARMAN K | B90: skylerdanger2000@gmail.com | C90: Qloset@123 | D90: 25-26 | E90: Yet to present | F90: COMPLETED | H90: 9361455523 | M90: Tier 1 | N90: UNIHOMES PHASE 1 TOWER 1 NO 204,RATINAMANGALM CHENNAI-600127 | O90: Male | P90: obc | R90: yes | S90: Sc-3343hr | T90: https://drive.google.com/file/d/1JpesebGrTQRjlE59-oIm47tqykoWEbXQ/view?usp=sharing
A91: Sharvesh S | B91: sharvesh4705@gmail.com | C91: Sundaram1947 | D91: 25-26 | E91: IVP Selected | F91: COMPLETED | G91: 14.07.26 | H91: 6369766990 | M91: Tier 2 | N91: no.46, Balasubramania nagar, street no.2, ITI backside, GN Mills , Coimbatore -29 | O91: Male | Q91: pre | R91: yes | S91: PX-x22sud | T91: https://drive.google.com/file/d/1-yznzjE283jjx-b3vDiIbIwsga68hIlk/view?usp=sharing
A92: Anjhana | B92: anjhana.deiva@gmail.com | C92: Anjhana@12deiva | F92: not done | H92: 8903126530 | M92: Tier 1 | N92: 103 jaishree apartment, 2nd main road, r.a.puram, chennai -28 | O92: Female | P92: ST | S92: SC-3o0p3
A93: naveen kumar | B93: naviinkumar209@gmail.com | C93: AgriAi@2025 | D93: 25-26 | E93: absent | F93: COMPLETED | G93: 21.07.26 | H93: 8939724423 | M93: Tier 1 | N93: 156 Pentastech mullai st VGP shanthi nagar pallikaranai chennai 600100 TAMIL NADU CHENNAI | O93: Male | P93: GENERAL | R93: yes | S93: sc-3yn3y | T93: https://drive.google.com/file/d/1TD6Zr_t4dP2amdmHB97iyp7MVXGAWrPM/view?usp=sharing
A94: Sivasubramani C | B94: sivakbt21@gmail.com | C94: Siva@123 | D94: 25-26 | E94: IVP Selected | F94: COMPLETED | G94: 14.07.26 | H94: 6364057474 | M94: Tier 1 | N94: No 231, Big street, Kadambattur, CHENNAI , 631203 | O94: Male | P94: OBC | Q94: pre | R94: yes | S94: SC-ecrjpqw | T94: https://docs.google.com/presentation/d/17d-7F8ya_H6PxxxxcwOvvTarwPgPOlaN/edit?usp=sharing&ouid=104277249549708518105&rtpof=true&sd=true
A95: gopikakanagaraj | B95: gopikakanagaraj1111@gmail.com | C95: gopika17*KA | D95: 25-26 | E95: IVP Selected | F95: COMPLETED | G95: 14.07.26 | H95: 8610004262 | M95: Tier 3 | N95: 4/613 SP Nagar, Kullampalayam post, Gobichettipalayam, Erode dt | O95: Female | P95: OBC | Q95: pre | R95: yes | S95: SC-nx45i | T95: https://docs.google.com/presentation/d/100spzmnKXgcVCDW56dtZMhsgCfTyMSe0/edit?slide=id.p8#slide=id.p8
A96: maharaja pandian G | B96: pandianmaharajag@gmail.com | C96: @Gm@0345@ | D96: 25-26 | E96: IVP Selected | F96: COMPLETED | G96: 14.07.26 | H96: 8270345463 | M96: Tier 3 | N96: 80/8,kamaraj Nagar 1st Street, Sankarankovil, Tenkasi | O96: Male | P96: SC | Q96: pre | R96: yes | S96: sc-towsh | T96: https://docs.google.com/presentation/d/1qNVBk6gBUF6C_R1PZ17tOFm6axKc1L5C/edit?usp=sharing&ouid=104277249549708518105&rtpof=true&sd=true
A97: rahul g | B97: sterilysense@gmail.com | C97: Sterilysense@2024 | D97: 25-26 | E97: Yet to present | F97: COMPLETED | H97: 7305714848 | M97: Tier 1 | N97: Chennai | O97: male | P97: MBC | R97: yes | S97: SC-6y3eg | T97: https://drive.google.com/file/d/18ecch_ekv7-0S81KDJHkIjivGZFfbeRh/view?usp=sharing
A98: Shri Krishna | B98: - | F98: not done | H98: 7845210170 | S98: SC-76yta
A99: Mohammed Hussain Basith | B99: mohammedhussainbasithsa@gmail.com | C99: Mohammed@123 | D99: 25-26 | E99: not selected | F99: COMPLETED | G99: 12.01.26 | H99: 7200326094 | R99: yes | S99: SC-83s9eo | T99: https://docs.google.com/presentation/d/1XXOdoM72D_hhdWkD5i29TjW9-amrFpOE/edit?usp=sharing&ouid=104277249549708518105&rtpof=true&sd=true
A100: Kochadaimuthaiya | D100: 25-26 | E100: IVP Selected | F100: COMPLETED | G100: 13.02.26 | H100: 7092922565 | I100: 2 founders | K100: - | L100: 0 | Q100: preinc | R100: yes | S100: cedau-18 | T100: https://docs.google.com/presentation/d/1K0_8ixw9xLF8lSGKb6GeRqHY8DvkBBNV/edit?usp=sharing&ouid=104277249549708518105&rtpof=true&sd=true | U100: 300000
...

Sheet startify3.0
A1: ` | B1: College name | C1: Status Date | D1: Status | E1: Domain | F1: Grant | G1: ivp sno. | H1: PHNO. | I1: TEAMID | J1: pitch manual | K1: pitch sub form | L1: work | M1: in whatsapp group | N1: remarks
A2: 1 | B2: College of Engineering Guindy | C2: 45775 | D2: Selected for Finals | E2: Deep-Tech | F2: 5 | G2: {=_xlfn.XLOOKUP(I2,' ivp'!S:S,#REF!)} -> #N/A | H2: 8883035691 | I2: SC-591xv | J2: =_xlfn.XLOOKUP(I2, ivp!$K:$K, ivp!$M:$M) -> #REF! | K2: {=_xlfn.XLOOKUP(I2,Sheet2!$C$2:$C$56,Sheet2!$G$2:$G$56)} -> #N/A | M2: yes
A3: 2 | B3: St. Joseph's College of Engineering , OMR, Chennai. | C3: 45775 | D3: Selected for Finals | E3: Deep-Tech | F3: 1 | G3: {=_xlfn.XLOOKUP(I3,' ivp'!S:S,#REF!)} -> #N/A | H3: 7812876724 | I3: SC-1ewg7k | J3: =_xlfn.XLOOKUP(I3, ivp!$K:$K, ivp!$M:$M) -> #REF! | K3: {=_xlfn.XLOOKUP(I3,Sheet2!$C$2:$C$56,Sheet2!$G$2:$G$56)} -> #N/A | L3: called | M3: yes | N3: exams
A4: 3 | B4: St. Joseph's College of Engineering , OMR, Chennai. | C4: 45775 | D4: Selected for Finals | E4: Ed-Tech | F4: 5 | G4: {=_xlfn.XLOOKUP(I4,' ivp'!S:S,#REF!)} -> #N/A | H4: 9342049639 | I4: SC-rea6ge | J4: =_xlfn.XLOOKUP(I4, ivp!$K:$K, ivp!$M:$M) -> #REF! | K4: {=_xlfn.XLOOKUP(I4,Sheet2!$C$2:$C$56,Sheet2!$G$2:$G$56)} -> #N/A | M4: no
A5: 4 | B5: University College of Engineering, Thirukkuvalai | C5: 45775 | D5: Selected for Finals | E5: Space-Tech | F5: 6 | G5: {=_xlfn.XLOOKUP(I5,' ivp'!S:S,#REF!)} -> #N/A | H5: 7094149367 | I5: SC-ss0phb | J5: =_xlfn.XLOOKUP(I5, ivp!$K:$K, ivp!$M:$M) -> #REF! | K5: {=_xlfn.XLOOKUP(I5,Sheet2!$C$2:$C$56,Sheet2!$G$2:$G$56)} -> https://drive.google.com/open?id=1DrL3w6tkh8WgbEy3HjkfwRQ93uZiQ4Wz | M5: yes
A6: 5 | B6: St. Joseph's College of Engineering , OMR, Chennai. | C6: 45775 | D6: Selected for Finals | E6: Deep-Tech | F6: 3 | G6: {=_xlfn.XLOOKUP(I6,' ivp'!S:S,#REF!)} -> #N/A | H6: 7200939492 | I6: SC-8s2knl | J6: =_xlfn.XLOOKUP(I6, ivp!$K:$K, ivp!$M:$M) -> #REF! | K6: {=_xlfn.XLOOKUP(I6,Sheet2!$C$2:$C$56,Sheet2!$G$2:$G$56)} -> https://drive.google.com/open?id=1Rbchip-rj68Va3SjmYraQyLPBDxUK_cI | M6: yes
A7: 6 | B7: Mepco Schlenk Engineering College | C7: 45775 | D7: Selected for Finals | E7: AYUSH | F7: 1 | G7: {=_xlfn.XLOOKUP(I7,' ivp'!S:S,#REF!)} -> #N/A | H7: 9342177824 | I7: SC-g2rv7h | J7: =_xlfn.XLOOKUP(I7, ivp!$K:$K, ivp!$M:$M) -> #REF! | K7: {=_xlfn.XLOOKUP(I7,Sheet2!$C$2:$C$56,Sheet2!$G$2:$G$56)} -> #N/A | L7: called | M7: yes | N7: last checks
A8: 7 | B8: Chettinad College of Engineering & Technology | C8: 45776 | D8: Selected to Pre-finals | E8: SaaS | F8: 1 | G8: {=_xlfn.XLOOKUP(I8,' ivp'!S:S,#REF!)} -> #N/A | H8: 7868945597 | I8: SC-mjkoin | J8: =_xlfn.XLOOKUP(I8, ivp!$K:$K, ivp!$M:$M) -> #REF! | K8: {=_xlfn.XLOOKUP(I8,Sheet2!$C$2:$C$56,Sheet2!$G$2:$G$56)} -> #N/A | M8: yes | O8: Startify Status - 1 Yet to Apply Grant, 2 Processed from CED, 3 Grant Application Submitted to Govt., 4 Grant Steering Committee Interview Scheduled, 5 Granted 6 Investor Pitching Requested
A9: 8 | B9: College of Engineering Guindy, Anna University | C9: 45776 | D9: Selected for Finals | E9: MAaaS | F9: 1 | G9: {=_xlfn.XLOOKUP(I9,' ivp'!S:S,#REF!)} -> #N/A | H9: 9123551408 | I9: SC-ebcgyq | J9: =_xlfn.XLOOKUP(I9, ivp!$K:$K, ivp!$M:$M) -> #REF! | K9: {=_xlfn.XLOOKUP(I9,Sheet2!$C$2:$C$56,Sheet2!$G$2:$G$56)} -> #N/A | L9: called | M9: yes
A10: 9 | B10: Mepco Schlenk Engineering College, Sivakasi | C10: 45776 | D10: Selected for Finals | E10: AYUSH | F10: 1 | G10: {=_xlfn.XLOOKUP(I10,' ivp'!S:S,#REF!)} -> #N/A | H10: ​6379986903 | I10: SC-1l7eqi | J10: =_xlfn.XLOOKUP(I10, ivp!$K:$K, ivp!$M:$M) -> #REF! | K10: {=_xlfn.XLOOKUP(I10,Sheet2!$C$2:$C$56,Sheet2!$G$2:$G$56)} -> #N/A | L10: called | M10: yes | N10: he
A11: 10 | B11: Chettinad College of Engineering and Technology | C11: 45776 | D11: Selected to Pre-finals | E11: Agri-Tech | F11: 1 | G11: {=_xlfn.XLOOKUP(I11,' ivp'!S:S,#REF!)} -> #N/A | H11: 8438784753 | I11: SC-l7i27h | J11: =_xlfn.XLOOKUP(I11, ivp!$K:$K, ivp!$M:$M) -> #REF! | K11: {=_xlfn.XLOOKUP(I11,Sheet2!$C$2:$C$56,Sheet2!$G$2:$G$56)} -> #N/A | L11: send pref g invite link | M11: no
A12: 11 | B12: Velammal institute of Technology | C12: 45776 | D12: Selected to Pre-finals | E12: Deep-Tech | F12: 1 | G12: {=_xlfn.XLOOKUP(I12,' ivp'!S:S,#REF!)} -> #N/A | H12: 9600430853 | I12: SC-fg08d | J12: =_xlfn.XLOOKUP(I12, ivp!$K:$K, ivp!$M:$M) -> #REF! | K12: {=_xlfn.XLOOKUP(I12,Sheet2!$C$2:$C$56,Sheet2!$G$2:$G$56)} -> #N/A | M12: yes
A13: 12 | B13: St. Joseph's College of Engineering , OMR, Chennai. | C13: 45776 | D13: Selected for Finals | E13: DaaS | F13: 3 | G13: {=_xlfn.XLOOKUP(I13,' ivp'!S:S,#REF!)} -> #N/A | H13: 8639764726 | I13: SC-wv04l9 | J13: =_xlfn.XLOOKUP(I13, ivp!$K:$K, ivp!$M:$M) -> #REF! | K13: {=_xlfn.XLOOKUP(I13,Sheet2!$C$2:$C$56,Sheet2!$G$2:$G$56)} -> #N/A | M13: yes
A14: 13 | B14: KGiSL Institute of Technology | C14: 45776 | D14: Selected to Pre-finals | E14: SaaS | F14: 1 | G14: {=_xlfn.XLOOKUP(I14,' ivp'!S:S,#REF!)} -> #N/A | H14: 7339614900 | I14: SC-d3cp | J14: =_xlfn.XLOOKUP(I14, ivp!$K:$K, ivp!$M:$M) -> #REF! | K14: {=_xlfn.XLOOKUP(I14,Sheet2!$C$2:$C$56,Sheet2!$G$2:$G$56)} -> #N/A | M14: yes
A15: 14 | B15: R.M.D. Engineering College | C15: 45841 | D15: Selected for Finals | E15: MAaaS | F15: 6 | G15: {=_xlfn.XLOOKUP(I15,' ivp'!S:S,#REF!)} -> #N/A | H15: 8148522265 | I15: SC-oajf6r | J15: =_xlfn.XLOOKUP(I15, ivp!$K:$K, ivp!$M:$M) -> #REF! | K15: {=_xlfn.XLOOKUP(I15,Sheet2!$C$2:$C$56,Sheet2!$G$2:$G$56)} -> https://drive.google.com/open?id=1VWhrxq4im2ROTVEhW3mI93TDMyUbpKfn | M15: yes
A16: 15 | B16: Erode Sengunthar Engineering College | C16: 45776 | D16: Selected to Pre-finals | E16: MAaaS | F16: 1 | G16: {=_xlfn.XLOOKUP(I16,' ivp'!S:S,#REF!)} -> #N/A | H16: 7695916662 | I16: SC-4moum | J16: =_xlfn.XLOOKUP(I16, ivp!$K:$K, ivp!$M:$M) -> #REF! | K16: {=_xlfn.XLOOKUP(I16,Sheet2!$C$2:$C$56,Sheet2!$G$2:$G$56)} -> #N/A | M16: yes
A17: 16 | B17: Meenakshi Sundararajan Engineering College | C17: 45777 | D17: Selected for Finals | E17: Health-Tech | F17: 5 | G17: {=_xlfn.XLOOKUP(I17,' ivp'!S:S,#REF!)} -> #N/A | H17: 7305567239 | I17: PX-9cgwli | J17: =_xlfn.XLOOKUP(I17, ivp!$K:$K, ivp!$M:$M) -> #REF! | K17: {=_xlfn.XLOOKUP(I17,Sheet2!$C$2:$C$56,Sheet2!$G$2:$G$56)} -> https://drive.google.com/open?id=1zZYNJcw9kwJdoQmeNNB9xPR9xS-vA50l | M17: no
A18: 17 | B18: Saveetha Engineering College | C18: 45777 | D18: Selected for Finals | E18: EV Services | F18: 3 | G18: {=_xlfn.XLOOKUP(I18,' ivp'!S:S,#REF!)} -> #N/A | H18: 6381784015 | I18: PX-cm2mr | J18: =_xlfn.XLOOKUP(I18, ivp!$K:$K, ivp!$M:$M) -> #REF! | K18: {=_xlfn.XLOOKUP(I18,Sheet2!$C$2:$C$56,Sheet2!$G$2:$G$56)} -> #N/A | M18: yes
A19: 18 | B19: Sri Sairam Institute of Technology | C19: 45777 | D19: Selected to Pre-finals | E19: MAaaS | F19: 1 | G19: {=_xlfn.XLOOKUP(I19,' ivp'!S:S,#REF!)} -> #N/A | H19: 9003181180 | I19: SC-2t6aon | J19: =_xlfn.XLOOKUP(I19, ivp!$K:$K, ivp!$M:$M) -> #REF! | K19: {=_xlfn.XLOOKUP(I19,Sheet2!$C$2:$C$56,Sheet2!$G$2:$G$56)} -> #N/A | M19: no
A20: 19 | B20: KCG College of Technology | C20: 45777 | D20: Selected for Finals | E20: Climate-Tech | F20: 1 | G20: {=_xlfn.XLOOKUP(I20,' ivp'!S:S,#REF!)} -> #N/A | H20: 7395964806 | I20: SC-qdryod | J20: =_xlfn.XLOOKUP(I20, ivp!$K:$K, ivp!$M:$M) -> #REF! | K20: {=_xlfn.XLOOKUP(I20,Sheet2!$C$2:$C$56,Sheet2!$G$2:$G$56)} -> #N/A | L20: called | M20: yes
A21: 20 | B21: Saveetha Engineering College | C21: 45777 | D21: Selected for Finals | E21: MAaaS | F21: 1 | G21: {=_xlfn.XLOOKUP(I21,' ivp'!S:S,#REF!)} -> #N/A | H21: 8015375750 | I21: SC-en6n7o | J21: =_xlfn.XLOOKUP(I21, ivp!$K:$K, ivp!$M:$M) -> #REF! | K21: {=_xlfn.XLOOKUP(I21,Sheet2!$C$2:$C$56,Sheet2!$G$2:$G$56)} -> https://drive.google.com/open?id=1NXq1MT1nOZOwoEwzjtHP8wfEw4HrFKUH | L21: need to apply ivp | M21: yes
A22: 21 | B22: R.M.K. Engineering College | C22: 45778 | D22: Selected for Finals | E22: MAaaS | F22: 1 | G22: {=_xlfn.XLOOKUP(I22,' ivp'!S:S,#REF!)} -> #N/A | H22: 9677277149 | I22: SC-paxd4f | J22: =_xlfn.XLOOKUP(I22, ivp!$K:$K, ivp!$M:$M) -> #REF! | K22: {=_xlfn.XLOOKUP(I22,Sheet2!$C$2:$C$56,Sheet2!$G$2:$G$56)} -> #N/A | L22: called | M22: yes
A23: 22 | B23: SRM IST TRICHY | C23: 45778 | D23: Selected for Finals | E23: Enviro-Tech | F23: 3 | G23: {=_xlfn.XLOOKUP(I23,' ivp'!S:S,#REF!)} -> #N/A | H23: 7845414195 | I23: PX-3ki6nj | J23: =_xlfn.XLOOKUP(I23, ivp!$K:$K, ivp!$M:$M) -> #REF! | K23: {=_xlfn.XLOOKUP(I23,Sheet2!$C$2:$C$56,Sheet2!$G$2:$G$56)} -> #N/A | M23: no
A24: 23 | B24: Velalar College of Engineering and Technology | C24: 45778 | D24: Selected for Finals | E24: Agri-Tech | F24: 3 | G24: {=_xlfn.XLOOKUP(I24,' ivp'!S:S,#REF!)} -> #N/A | H24: 9361054415 | I24: SC-07g6mo | J24: =_xlfn.XLOOKUP(I24, ivp!$K:$K, ivp!$M:$M) -> #REF! | K24: {=_xlfn.XLOOKUP(I24,Sheet2!$C$2:$C$56,Sheet2!$G$2:$G$56)} -> https://drive.google.com/open?id=1zH7oPcHBU2ypBkNZMJ-UzIHydcevpHCz | M24: no
A25: 24 | B25: R.M.K. Engineering College | C25: 45779 | D25: Selected to Pre-finals | E25: MAaaS | F25: 1 | G25: {=_xlfn.XLOOKUP(I25,' ivp'!S:S,#REF!)} -> #N/A | H25: 8610937637 | I25: SC-4dv97 | J25: =_xlfn.XLOOKUP(I25, ivp!$K:$K, ivp!$M:$M) -> #REF! | K25: {=_xlfn.XLOOKUP(I25,Sheet2!$C$2:$C$56,Sheet2!$G$2:$G$56)} -> #N/A | M25: yes
A26: 25 | B26: R.M.D. Engineering College | C26: 45779 | D26: Selected to Pre-finals | E26: MAaaS | F26: 1 | G26: {=_xlfn.XLOOKUP(I26,' ivp'!S:S,#REF!)} -> #N/A | H26: 7418496591 | I26: SC-u1zyff | J26: =_xlfn.XLOOKUP(I26, ivp!$K:$K, ivp!$M:$M) -> #REF! | K26: {=_xlfn.XLOOKUP(I26,Sheet2!$C$2:$C$56,Sheet2!$G$2:$G$56)} -> #N/A | L26: send pref g invite link | M26: no
A27: 26 | B27: R.M.K. Engineering College | C27: 45779 | D27: Selected to Pre-finals | E27: MAaaS | F27: 1 | G27: {=_xlfn.XLOOKUP(I27,' ivp'!S:S,#REF!)} -> #N/A | H27: 8838118951 | I27: SC-4lbm5d | J27: =_xlfn.XLOOKUP(I27, ivp!$K:$K, ivp!$M:$M) -> #REF! | K27: {=_xlfn.XLOOKUP(I27,Sheet2!$C$2:$C$56,Sheet2!$G$2:$G$56)} -> #N/A | M27: no
A28: 27 | B28: AAA College of Engineering and Technology | C28: 45779 | D28: Selected for Finals | E28: MAaaS | F28: 1 | G28: {=_xlfn.XLOOKUP(I28,' ivp'!S:S,#REF!)} -> #N/A | H28: 7695851661 | I28: SC-ft2xkq | J28: =_xlfn.XLOOKUP(I28, ivp!$K:$K, ivp!$M:$M) -> #REF! | K28: {=_xlfn.XLOOKUP(I28,Sheet2!$C$2:$C$56,Sheet2!$G$2:$G$56)} -> #N/A | L28: called | M28: yes
A29: 28 | B29: Madras Institute of Technology, Chromepet | C29: 45779 | D29: Selected for Finals | E29: Health-Tech | F29: 1 | G29: {=_xlfn.XLOOKUP(I29,' ivp'!S:S,#REF!)} -> #N/A | H29: 8610254655 | I29: SC-yd0hxd | J29: =_xlfn.XLOOKUP(I29, ivp!$K:$K, ivp!$M:$M) -> #REF! | K29: {=_xlfn.XLOOKUP(I29,Sheet2!$C$2:$C$56,Sheet2!$G$2:$G$56)} -> #N/A | L29: called | M29: no
A30: 29 | B30: Adhiyamaan College of Agriculture and Research | C30: 45779 | D30: Selected for Finals | E30: Agri-Tech | F30: 6 | G30: {=_xlfn.XLOOKUP(I30,' ivp'!S:S,#REF!)} -> #N/A | H30: 6385256271 | I30: SC-oyp2ts | J30: =_xlfn.XLOOKUP(I30, ivp!$K:$K, ivp!$M:$M) -> #REF! | K30: {=_xlfn.XLOOKUP(I30,Sheet2!$C$2:$C$56,Sheet2!$G$2:$G$56)} -> https://drive.google.com/open?id=12RsdTu1tH7jx2uQYyNA2C3v1dFMkZU0H | L30: send f g invite link | M30: no
A31: 30 | B31: R.M.K. Engineering College | C31: 45779 | D31: Selected for Finals | E31: Ed-Tech | F31: 3 | G31: {=_xlfn.XLOOKUP(I31,' ivp'!S:S,#REF!)} -> #N/A | H31: 9952048318 | I31: SC-ywojqq | J31: =_xlfn.XLOOKUP(I31, ivp!$K:$K, ivp!$M:$M) -> #REF! | K31: {=_xlfn.XLOOKUP(I31,Sheet2!$C$2:$C$56,Sheet2!$G$2:$G$56)} -> https://docs.google.com/presentation/d/1r_uJDDSgeSqdewnxUdc17ddlmhNFHjj7/edit?usp=sharing&ouid=104277249549708518105&rtpof=true&sd=true | M31: yes
A32: 31 | B32: R.M.K. Engineering College | C32: 45779 | D32: Selected for Finals | E32: MAaaS | F32: 1 | G32: {=_xlfn.XLOOKUP(I32,' ivp'!S:S,#REF!)} -> #N/A | H32: 9788606171 | I32: SC-1k48n8 | J32: =_xlfn.XLOOKUP(I32, ivp!$K:$K, ivp!$M:$M) -> #REF! | K32: {=_xlfn.XLOOKUP(I32,Sheet2!$C$2:$C$56,Sheet2!$G$2:$G$56)} -> #N/A | L32: called | M32: yes | N32: last checks
A33: 32 | B33: R.M.K. Engineering College | C33: 45779 | D33: Selected for Finals | E33: MAaaS | F33: 1 | G33: {=_xlfn.XLOOKUP(I33,' ivp'!S:S,#REF!)} -> #N/A | H33: 8825400260 | I33: SC-wl7dmv | J33: =_xlfn.XLOOKUP(I33, ivp!$K:$K, ivp!$M:$M) -> #REF! | K33: {=_xlfn.XLOOKUP(I33,Sheet2!$C$2:$C$56,Sheet2!$G$2:$G$56)} -> #N/A | L33: called | M33: yes | N33: get back
A34: 33 | B34: Sathyabama Institute of Science and Technology | C34: 45779 | D34: Selected to Pre-finals | E34: Deep-Tech | F34: 1 | G34: {=_xlfn.XLOOKUP(I34,' ivp'!S:S,#REF!)} -> #N/A | H34: 9025456450 | I34: SC-jxifzd | J34: =_xlfn.XLOOKUP(I34, ivp!$K:$K, ivp!$M:$M) -> #REF! | K34: {=_xlfn.XLOOKUP(I34,Sheet2!$C$2:$C$56,Sheet2!$G$2:$G$56)} -> #N/A | M34: yes
A35: 34 | B35: Panimalar Engineering College | C35: 45960 | D35: Selected for Finals | E35: blank | F35: 3 | G35: {=_xlfn.XLOOKUP(I35,' ivp'!S:S,#REF!)} -> #N/A | H35: 6374990762 | I35: SC-pcw53a | J35: =_xlfn.XLOOKUP(I35, ivp!$K:$K, ivp!$M:$M) -> #REF! | K35: {=_xlfn.XLOOKUP(I35,Sheet2!$C$2:$C$56,Sheet2!$G$2:$G$56)} -> #N/A | L35: called | M35: yes | N35: company incorporation
A36: 35 | B36: Rajalakshmi Engineering College | C36: 45780 | D36: Selected to Pre-finals | E36: blank | F36: 1 | G36: {=_xlfn.XLOOKUP(I36,' ivp'!S:S,#REF!)} -> #N/A | H36: 9360341516 | I36: SC-l8l0si | J36: =_xlfn.XLOOKUP(I36, ivp!$K:$K, ivp!$M:$M) -> #REF! | K36: {=_xlfn.XLOOKUP(I36,Sheet2!$C$2:$C$56,Sheet2!$G$2:$G$56)} -> #N/A | L36: send pref g invite link | M36: no
A37: 36 | B37: R.M.K College of Engineering and Technology, Tiruvallur | C37: 45780 | D37: Selected for Finals | E37: Automobile | F37: 1 | G37: {=_xlfn.XLOOKUP(I37,' ivp'!S:S,#REF!)} -> #N/A | H37: 8940116891 | I37: SC-4yp9l | J37: =_xlfn.XLOOKUP(I37, ivp!$K:$K, ivp!$M:$M) -> #REF! | K37: {=_xlfn.XLOOKUP(I37,Sheet2!$C$2:$C$56,Sheet2!$G$2:$G$56)} -> #N/A | L37: called | M37: no | N37: exams
A38: 37 | B38: Jansons Institute of Technology | C38: 45780 | D38: Selected for Finals | E38: Industrial IoT /Smart City | F38: 1 | G38: {=_xlfn.XLOOKUP(I38,' ivp'!S:S,#REF!)} -> #N/A | H38: 8148232205 | I38: SC-mnnn9n | J38: =_xlfn.XLOOKUP(I38, ivp!$K:$K, ivp!$M:$M) -> #REF! | K38: {=_xlfn.XLOOKUP(I38,Sheet2!$C$2:$C$56,Sheet2!$G$2:$G$56)} -> https://drive.google.com/open?id=1Kkw_iTDBFZV0hwN1-vITM_lwyEMhi6Dw | L38: called | M38: no
A39: 38 | B39: Erode Sengunthar Engineering College | C39: 45782 | D39: Selected to Pre-finals | E39: Deep-Tech | F39: 1 | G39: {=_xlfn.XLOOKUP(I39,' ivp'!S:S,#REF!)} -> #N/A | H39: 9360119932 | I39: SC-y43euj | J39: =_xlfn.XLOOKUP(I39, ivp!$K:$K, ivp!$M:$M) -> #REF! | K39: {=_xlfn.XLOOKUP(I39,Sheet2!$C$2:$C$56,Sheet2!$G$2:$G$56)} -> https://drive.google.com/open?id=1nOtcqzNxnN1cVZZNgYC7O4pMceJ1vuq4 | M39: yes
A40: 39 | B40: R.M.K. Engineering College | C40: 45782 | D40: Selected for Finals | E40: Deep-Tech | F40: 3 | G40: {=_xlfn.XLOOKUP(I40,' ivp'!S:S,#REF!)} -> #N/A | H40: 7708365986 | I40: SC-b4jkfxa | J40: =_xlfn.XLOOKUP(I40, ivp!$K:$K, ivp!$M:$M) -> #REF! | K40: {=_xlfn.XLOOKUP(I40,Sheet2!$C$2:$C$56,Sheet2!$G$2:$G$56)} -> https://drive.google.com/open?id=1VorSWnUlyM-hZbEwKD3-ydU3amct_rNZ | M40: yes
A41: 40 | B41: Adithya Institute of Technology | C41: 45782 | D41: Selected for Finals | E41: MAaaS | F41: 1 | G41: {=_xlfn.XLOOKUP(I41,' ivp'!S:S,#REF!)} -> #N/A | H41: 9383475378 | I41: SC-pye3oi | J41: =_xlfn.XLOOKUP(I41, ivp!$K:$K, ivp!$M:$M) -> #REF! | K41: {=_xlfn.XLOOKUP(I41,Sheet2!$C$2:$C$56,Sheet2!$G$2:$G$56)} -> https://drive.google.com/open?id=1X3kRolb3adDdEW7REfueac7cptP6jieD | L41: called | M41: yes
A42: 41 | B42: KCG College of Technology | C42: 45783 | D42: Selected for Finals | E42: Enviro-Tech | F42: 1 | G42: {=_xlfn.XLOOKUP(I42,' ivp'!S:S,#REF!)} -> #N/A | H42: 8754864334 | I42: SC-y4ea0v | J42: =_xlfn.XLOOKUP(I42, ivp!$K:$K, ivp!$M:$M) -> #REF! | K42: {=_xlfn.XLOOKUP(I42,Sheet2!$C$2:$C$56,Sheet2!$G$2:$G$56)} -> #N/A | L42: need to apply ivp | M42: yes
A43: 42 | B43: Madras Institute of Technology, Chromepet | C43: 45783 | D43: Selected for Finals | E43: Renewable Energy | F43: 1 | G43: {=_xlfn.XLOOKUP(I43,' ivp'!S:S,#REF!)} -> #N/A | H43: 9345856926 | I43: SC-83s9eo | J43: =_xlfn.XLOOKUP(I43, ivp!$K:$K, ivp!$M:$M) -> #REF! | K43: {=_xlfn.XLOOKUP(I43,Sheet2!$C$2:$C$56,Sheet2!$G$2:$G$56)} -> #N/A | L43: called | M43: yes
A44: 43 | B44: RVS Educational Trust's Group of Institutions | C44: 45784 | D44: Selected for Finals | E44: MAaaS | F44: 1 | G44: {=_xlfn.XLOOKUP(I44,' ivp'!S:S,#REF!)} -> #N/A | H44: 7010637848 | I44: SC-tktqp | J44: =_xlfn.XLOOKUP(I44, ivp!$K:$K, ivp!$M:$M) -> #REF! | K44: {=_xlfn.XLOOKUP(I44,Sheet2!$C$2:$C$56,Sheet2!$G$2:$G$56)} -> #N/A | L44: called
A45: 44 | B45: RVS Educational Trust's Group of Institutions | C45: 45784 | D45: Selected for Finals | E45: MAaaS | F45: 6 | G45: {=_xlfn.XLOOKUP(I45,' ivp'!S:S,#REF!)} -> #N/A | H45: 9042871766 | I45: SC-9a9rgd | J45: =_xlfn.XLOOKUP(I45, ivp!$K:$K, ivp!$M:$M) -> #REF! | K45: {=_xlfn.XLOOKUP(I45,Sheet2!$C$2:$C$56,Sheet2!$G$2:$G$56)} -> https://drive.google.com/open?id=149HppxiF5fWSdC5NDButuJX_m6yEKHIP | M45: no
A46: 45 | B46: Bannari Amman Institute of Technology, Sathy | C46: 45784 | D46: Selected to Pre-finals | E46: Aqua-Culture | F46: 1 | G46: {=_xlfn.XLOOKUP(I46,' ivp'!S:S,#REF!)} -> #N/A | H46: 9025377096 | I46: SC-m0m97 | J46: =_xlfn.XLOOKUP(I46, ivp!$K:$K, ivp!$M:$M) -> #REF! | K46: {=_xlfn.XLOOKUP(I46,Sheet2!$C$2:$C$56,Sheet2!$G$2:$G$56)} -> #N/A | M46: yes
A47: 46 | B47: College of Engineering Guindy | C47: 45959 | D47: Selected for Finals | E47: Enviro-Tech | F47: 5 | G47: {=_xlfn.XLOOKUP(I47,' ivp'!S:S,#REF!)} -> #N/A | H47: 9841454141 | I47: PX-5lg1jf | J47: =_xlfn.XLOOKUP(I47, ivp!$K:$K, ivp!$M:$M) -> #REF! | K47: {=_xlfn.XLOOKUP(I47,Sheet2!$C$2:$C$56,Sheet2!$G$2:$G$56)} -> #N/A | L47: called | M47: yes
A48: 47 | B48: University College of Engineering, Tindivanam | C48: 45784 | D48: Selected to Pre-finals | E48: Deep-Tech | F48: 1 | G48: {=_xlfn.XLOOKUP(I48,' ivp'!S:S,#REF!)} -> #N/A | H48: 9361077566 | I48: SC-tretx | J48: =_xlfn.XLOOKUP(I48, ivp!$K:$K, ivp!$M:$M) -> #REF! | K48: {=_xlfn.XLOOKUP(I48,Sheet2!$C$2:$C$56,Sheet2!$G$2:$G$56)} -> #N/A | L48: send pref g invite link | M48: no
A49: 48 | B49: A.V.C. College of Engineering | C49: 45787 | D49: Selected to Pre-finals | E49: MAaaS | F49: 1 | G49: {=_xlfn.XLOOKUP(I49,' ivp'!S:S,#REF!)} -> #N/A | H49: 6383142129 | I49: SC-d034dd | J49: =_xlfn.XLOOKUP(I49, ivp!$K:$K, ivp!$M:$M) -> #REF! | K49: {=_xlfn.XLOOKUP(I49,Sheet2!$C$2:$C$56,Sheet2!$G$2:$G$56)} -> #N/A | L49: send pref g invite link | M49: no
A50: 49 | B50: KGiSL Institute of Technology | C50: 45787 | D50: Selected for Finals | E50: SaaS | F50: 1 | G50: {=_xlfn.XLOOKUP(I50,' ivp'!S:S,#REF!)} -> #N/A | H50: 9360124106 | I50: SC-aal3wa | J50: =_xlfn.XLOOKUP(I50, ivp!$K:$K, ivp!$M:$M) -> #REF! | K50: {=_xlfn.XLOOKUP(I50,Sheet2!$C$2:$C$56,Sheet2!$G$2:$G$56)} -> #N/A | M50: yes
A51: 50 | B51: Panimalar Engineering College | C51: 45789 | D51: Selected for Finals | E51: Deep-Tech | F51: 6 | G51: {=_xlfn.XLOOKUP(I51,' ivp'!S:S,#REF!)} -> #N/A | H51: 9025314278 | I51: SC-dyjltj | J51: =_xlfn.XLOOKUP(I51, ivp!$K:$K, ivp!$M:$M) -> #REF! | K51: {=_xlfn.XLOOKUP(I51,Sheet2!$C$2:$C$56,Sheet2!$G$2:$G$56)} -> #N/A | M51: no
A52: 51 | B52: St. Joseph's College of Engineering , OMR, Chennai. | C52: 45789 | D52: Selected for Finals | E52: Deep-Tech | F52: 1 | G52: {=_xlfn.XLOOKUP(I52,' ivp'!S:S,#REF!)} -> #N/A | H52: 8667282961 | I52: SC-g8mwsh | J52: =_xlfn.XLOOKUP(I52, ivp!$K:$K, ivp!$M:$M) -> #REF! | K52: {=_xlfn.XLOOKUP(I52,Sheet2!$C$2:$C$56,Sheet2!$G$2:$G$56)} -> #N/A | L52: called | M52: yes
A53: 52 | B53: St. Joseph's College of Engineering , OMR, Chennai. | C53: 45789 | D53: Selected for Finals | E53: SaaS | F53: 1 | G53: {=_xlfn.XLOOKUP(I53,' ivp'!S:S,#REF!)} -> #N/A | H53: 9790339415 | I53: SC-9au7v | J53: =_xlfn.XLOOKUP(I53, ivp!$K:$K, ivp!$M:$M) -> #REF! | K53: {=_xlfn.XLOOKUP(I53,Sheet2!$C$2:$C$56,Sheet2!$G$2:$G$56)} -> #N/A | L53: need to apply ivp | M53: yes
A54: 53 | B54: Jeppiaar Engineering College | C54: 45789 | D54: Selected for Finals | E54: Health-Care | F54: 0 | G54: {=_xlfn.XLOOKUP(I54,' ivp'!S:S,#REF!)} -> #N/A | H54: - | I54: SC-42107 | J54: =_xlfn.XLOOKUP(I54, ivp!$K:$K, ivp!$M:$M) -> #REF! | K54: {=_xlfn.XLOOKUP(I54,Sheet2!$C$2:$C$56,Sheet2!$G$2:$G$56)} -> #N/A
A55: 54 | B55: KGiSL Institute of Technology | C55: 45796 | D55: Selected to Pre-finals | E55: Ed-Tech | F55: 1 | G55: {=_xlfn.XLOOKUP(I55,' ivp'!S:S,#REF!)} -> #N/A | H55: 9361584129 | I55: SC-nxbt9d | J55: =_xlfn.XLOOKUP(I55, ivp!$K:$K, ivp!$M:$M) -> #REF! | K55: {=_xlfn.XLOOKUP(I55,Sheet2!$C$2:$C$56,Sheet2!$G$2:$G$56)} -> #N/A | L55: send pref g invite link | M55: no
A56: 55 | B56: St. Joseph's College of Engineering , OMR, Chennai. | C56: 45796 | D56: Selected to Pre-finals | E56: Deep-Tech | F56: 1 | G56: {=_xlfn.XLOOKUP(I56,' ivp'!S:S,#REF!)} -> #N/A | H56: 9363402924 | I56: SC-e0llzf | J56: =_xlfn.XLOOKUP(I56, ivp!$K:$K, ivp!$M:$M) -> #REF! | K56: {=_xlfn.XLOOKUP(I56,Sheet2!$C$2:$C$56,Sheet2!$G$2:$G$56)} -> #N/A | L56: send pref g invite link | M56: no
A57: 56 | B57: College of Engineering Guindy, Anna University | C57: 45796 | D57: Selected for Finals | E57: Deep-Tech | F57: 2 | G57: {=_xlfn.XLOOKUP(I57,' ivp'!S:S,#REF!)} -> #N/A | H57: 6382725434 | I57: SC-xu2qlg | J57: =_xlfn.XLOOKUP(I57, ivp!$K:$K, ivp!$M:$M) -> #REF! | K57: {=_xlfn.XLOOKUP(I57,Sheet2!$C$2:$C$56,Sheet2!$G$2:$G$56)} -> https://drive.google.com/open?id=1b4go98skQmw_jcdiLt8kXyKtdRkgpWCV | L57: need to apply ivp | M57: yes | N57: got the consent form , has to apply
A58: 57 | B58: Velammal Institute of Technology | C58: 45796 | D58: Selected for Finals | E58: Deep-Tech | F58: 1 | G58: {=_xlfn.XLOOKUP(I58,' ivp'!S:S,#REF!)} -> #N/A | H58: 6364057474 | I58: SC-ecrjpqw | J58: =_xlfn.XLOOKUP(I58, ivp!$K:$K, ivp!$M:$M) -> #REF! | K58: {=_xlfn.XLOOKUP(I58,Sheet2!$C$2:$C$56,Sheet2!$G$2:$G$56)} -> #N/A | L58: need to apply ivp | M58: no
A59: 58 | B59: Prince Shri Venkateshwara Padmavathy Engineering college | C59: 45797 | D59: Selected for Finals | E59: IoT | F59: 1 | G59: {=_xlfn.XLOOKUP(I59,' ivp'!S:S,#REF!)} -> #N/A | H59: 9176775477 | I59: SC-lvrbhd | J59: =_xlfn.XLOOKUP(I59, ivp!$K:$K, ivp!$M:$M) -> #REF! | K59: {=_xlfn.XLOOKUP(I59,Sheet2!$C$2:$C$56,Sheet2!$G$2:$G$56)} -> #N/A | M59: yes
A60: 59 | B60: Kalaignar Karunanidhi Institute of Technology | C60: 45797 | D60: Selected to Pre-finals | E60: Agri-Tech | F60: 1 | G60: {=_xlfn.XLOOKUP(I60,' ivp'!S:S,#REF!)} -> #N/A | H60: 9994614891 | I60: SC-5gvo9n | J60: =_xlfn.XLOOKUP(I60, ivp!$K:$K, ivp!$M:$M) -> #REF! | K60: {=_xlfn.XLOOKUP(I60,Sheet2!$C$2:$C$56,Sheet2!$G$2:$G$56)} -> #N/A | L60: send pref g invite link | M60: no
A61: 61 | B61: KGiSL Institute of Technology | C61: 45797 | D61: Selected to Pre-finals | E61: Ed-Tech | F61: 1 | G61: {=_xlfn.XLOOKUP(I61,' ivp'!S:S,#REF!)} -> #N/A | H61: 9042059598 | I61: SC-u96aa4 | J61: =_xlfn.XLOOKUP(I61, ivp!$K:$K, ivp!$M:$M) -> #REF! | K61: {=_xlfn.XLOOKUP(I61,Sheet2!$C$2:$C$56,Sheet2!$G$2:$G$56)} -> #N/A | M61: yes
A62: 62 | B62: R.M.K. Engineering College | C62: 45797 | D62: Selected for Finals | E62: Health-Tech | F62: 1 | G62: {=_xlfn.XLOOKUP(I62,' ivp'!S:S,#REF!)} -> #N/A | H62: 9150624440 | I62: SC-slpbfe | J62: =_xlfn.XLOOKUP(I62, ivp!$K:$K, ivp!$M:$M) -> #REF! | K62: {=_xlfn.XLOOKUP(I62,Sheet2!$C$2:$C$56,Sheet2!$G$2:$G$56)} -> #N/A | L62: called | M62: yes | N62: exams
A63: 63 | B63: Hindusthan College of Engineering and Technology | C63: 45799 | D63: Selected to Pre-finals | E63: IoT | F63: 1 | G63: {=_xlfn.XLOOKUP(I63,' ivp'!S:S,#REF!)} -> #N/A | H63: 9094949411 | I63: SC-081wb | J63: =_xlfn.XLOOKUP(I63, ivp!$K:$K, ivp!$M:$M) -> #REF! | K63: {=_xlfn.XLOOKUP(I63,Sheet2!$C$2:$C$56,Sheet2!$G$2:$G$56)} -> #N/A | M63: yes
A64: 64 | B64: KGiSL Institute of Technology | C64: 45799 | D64: Selected to Pre-finals | E64: MAaaS | F64: 1 | G64: {=_xlfn.XLOOKUP(I64,' ivp'!S:S,#REF!)} -> #N/A | H64: 9629862664 | I64: SC-nznrrh | J64: =_xlfn.XLOOKUP(I64, ivp!$K:$K, ivp!$M:$M) -> #REF! | K64: {=_xlfn.XLOOKUP(I64,Sheet2!$C$2:$C$56,Sheet2!$G$2:$G$56)} -> #N/A | L64: send pref g invite link | M64: no
A65: 65 | B65: Dhanalakshmi Srinivasan University | C65: 45799 | D65: Selected to Pre-finals | E65: SaaS | F65: 1 | G65: {=_xlfn.XLOOKUP(I65,' ivp'!S:S,#REF!)} -> #N/A | H65: 6369969575 | I65: SC-xrz94 | J65: =_xlfn.XLOOKUP(I65, ivp!$K:$K, ivp!$M:$M) -> #REF! | K65: {=_xlfn.XLOOKUP(I65,Sheet2!$C$2:$C$56,Sheet2!$G$2:$G$56)} -> #N/A | M65: yes
A66: 66 | B66: Easwari Engineering College | C66: 45801 | D66: Selected for Finals | E66: Health-Tech | F66: 1 | G66: {=_xlfn.XLOOKUP(I66,' ivp'!S:S,#REF!)} -> #N/A | H66: 9361579843 | I66: SC-v80p8o | J66: =_xlfn.XLOOKUP(I66, ivp!$K:$K, ivp!$M:$M) -> #REF! | K66: {=_xlfn.XLOOKUP(I66,Sheet2!$C$2:$C$56,Sheet2!$G$2:$G$56)} -> #N/A | M66: yes
A67: 67 | B67: St. Joseph's College of Engineering , OMR, Chennai. | C67: 45801 | D67: Selected for Finals | E67: Health-Tech | F67: 1 | G67: {=_xlfn.XLOOKUP(I67,' ivp'!S:S,#REF!)} -> #N/A | H67: 8438646623 | I67: SC-9y6edj | J67: =_xlfn.XLOOKUP(I67, ivp!$K:$K, ivp!$M:$M) -> #REF! | K67: {=_xlfn.XLOOKUP(I67,Sheet2!$C$2:$C$56,Sheet2!$G$2:$G$56)} -> https://drive.google.com/open?id=1yhwdGyqyQaxxCpTdhazJmfT0qeGAy4je | L67: called | M67: yes | N67: last checks
A68: 68 | B68: Kings College of Engineering | C68: 45801 | D68: Selected for Finals | E68: MAaaS | F68: 1 | G68: {=_xlfn.XLOOKUP(I68,' ivp'!S:S,#REF!)} -> #N/A | H68: 6369115585 | I68: SC-6eh558 | J68: =_xlfn.XLOOKUP(I68, ivp!$K:$K, ivp!$M:$M) -> #REF! | K68: {=_xlfn.XLOOKUP(I68,Sheet2!$C$2:$C$56,Sheet2!$G$2:$G$56)} -> #N/A | L68: called | M68: yes
A69: 69 | B69: Rajalakshmi Engineering College | C69: 45801 | D69: Selected to Pre-finals | E69: Fashion & Retail | F69: 1 | G69: {=_xlfn.XLOOKUP(I69,' ivp'!S:S,#REF!)} -> #N/A | H69: 9176591451 | I69: SC-i822op | J69: =_xlfn.XLOOKUP(I69, ivp!$K:$K, ivp!$M:$M) -> #REF! | K69: {=_xlfn.XLOOKUP(I69,Sheet2!$C$2:$C$56,Sheet2!$G$2:$G$56)} -> #N/A | M69: yes
A70: 70 | B70: Sri Sairam Homoeopathy Medical College and Research Centre | C70: 45803 | D70: Selected for Finals | E70: Health-Tech, MAaaS | F70: 6 | G70: {=_xlfn.XLOOKUP(I70,' ivp'!S:S,#REF!)} -> #N/A | H70: 7395956159 | I70: SC-qtithv | J70: =_xlfn.XLOOKUP(I70, ivp!$K:$K, ivp!$M:$M) -> #REF! | K70: {=_xlfn.XLOOKUP(I70,Sheet2!$C$2:$C$56,Sheet2!$G$2:$G$56)} -> #N/A | M70: yes
A71: 71 | B71: Sri Venkateswara College of Engineering | C71: 45803 | D71: Selected for Finals | E71: Bio-Tech | F71: 3 | G71: {=_xlfn.XLOOKUP(I71,' ivp'!S:S,#REF!)} -> #N/A | H71: 8825987128 | I71: SC-ox0pjd | J71: =_xlfn.XLOOKUP(I71, ivp!$K:$K, ivp!$M:$M) -> #REF! | K71: {=_xlfn.XLOOKUP(I71,Sheet2!$C$2:$C$56,Sheet2!$G$2:$G$56)} -> https://drive.google.com/open?id=1nHZJs4i8lSAPFeGmnNbmIfUuscVuCEPM | L71: called | M71: yes
A72: 72 | B72: Sethu Institute of Technology | C72: 45803 | D72: Selected for Finals | E72: SaaS | F72: 1 | G72: {=_xlfn.XLOOKUP(I72,' ivp'!S:S,#REF!)} -> #N/A | H72: 8438532004 | I72: SC-dg0km | J72: =_xlfn.XLOOKUP(I72, ivp!$K:$K, ivp!$M:$M) -> #REF! | K72: {=_xlfn.XLOOKUP(I72,Sheet2!$C$2:$C$56,Sheet2!$G$2:$G$56)} -> #N/A | L72: need to apply ivp | M72: yes
A73: 73 | B73: Rajalakshmi Engineering College | C73: 45803 | D73: Selected for Finals | E73: MAaaS | F73: 1 | G73: {=_xlfn.XLOOKUP(I73,' ivp'!S:S,#REF!)} -> #N/A | H73: 9894411860 | I73: SC-8j8zog | J73: =_xlfn.XLOOKUP(I73, ivp!$K:$K, ivp!$M:$M) -> #REF! | K73: {=_xlfn.XLOOKUP(I73,Sheet2!$C$2:$C$56,Sheet2!$G$2:$G$56)} -> #N/A | L73: need to apply ivp | M73: yes
A74: 74 | B74: Mepco Schlenk Engineering College, Sivakasi | C74: 45803 | D74: Selected for Finals | E74: Agri-Tech | F74: 1 | G74: {=_xlfn.XLOOKUP(I74,' ivp'!S:S,#REF!)} -> #N/A | H74: 6383245425 | I74: SC-352sbi | J74: =_xlfn.XLOOKUP(I74, ivp!$K:$K, ivp!$M:$M) -> #REF! | K74: {=_xlfn.XLOOKUP(I74,Sheet2!$C$2:$C$56,Sheet2!$G$2:$G$56)} -> #N/A | L74: called | M74: yes
A75: 75 | B75: Alagappa College of Technology, Anna University | C75: 45803 | D75: Selected for Finals | E75: Bio-Tech | F75: 1 | G75: {=_xlfn.XLOOKUP(I75,' ivp'!S:S,#REF!)} -> #N/A | H75: 8072959463 | I75: SC(BT)-3yqjDH | J75: =_xlfn.XLOOKUP(I75, ivp!$K:$K, ivp!$M:$M) -> #REF! | K75: {=_xlfn.XLOOKUP(I75,Sheet2!$C$2:$C$56,Sheet2!$G$2:$G$56)} -> #N/A | L75: called | M75: yes | N75: exams
A76: 76 | B76: Mohamed Sathak A J College of engineering | C76: 45806 | D76: Selected to Pre-finals | E76: blank | F76: 1 | G76: {=_xlfn.XLOOKUP(I76,' ivp'!S:S,#REF!)} -> #N/A | H76: 6383284218 | I76: SC-lpwpfz | J76: =_xlfn.XLOOKUP(I76, ivp!$K:$K, ivp!$M:$M) -> #REF! | K76: {=_xlfn.XLOOKUP(I76,Sheet2!$C$2:$C$56,Sheet2!$G$2:$G$56)} -> #N/A | L76: send pref g invite link | M76: no
A77: 77 | B77: Government College of Engineering Srirangam Trichy | C77: 45806 | D77: Selected for Finals | E77: blank | F77: 1 | G77: {=_xlfn.XLOOKUP(I77,' ivp'!S:S,#REF!)} -> #N/A | H77: 9360169224 | I77: SC-a9ruvt | J77: =_xlfn.XLOOKUP(I77, ivp!$K:$K, ivp!$M:$M) -> #REF! | K77: {=_xlfn.XLOOKUP(I77,Sheet2!$C$2:$C$56,Sheet2!$G$2:$G$56)} -> #N/A | L77: called | M77: yes
A78: 78 | B78: KGiSL Institute of Technology | C78: 45806 | D78: Selected for Finals | E78: blank | F78: 1 | G78: {=_xlfn.XLOOKUP(I78,' ivp'!S:S,#REF!)} -> #N/A | H78: 9342579223 | I78: SC-aeude | J78: =_xlfn.XLOOKUP(I78, ivp!$K:$K, ivp!$M:$M) -> #REF! | K78: {=_xlfn.XLOOKUP(I78,Sheet2!$C$2:$C$56,Sheet2!$G$2:$G$56)} -> https://drive.google.com/open?id=1eSK4TMygEDUwydtw3Bz8FhlF3MQxJlQy | L78: need to apply ivp | M78: yes
A79: 79 | B79: Mepco Schlenk Engineering College, Sivakasi | C79: 45806 | D79: Selected for Finals | E79: blank | F79: 1 | G79: {=_xlfn.XLOOKUP(I79,' ivp'!S:S,#REF!)} -> #N/A | H79: 9597870425 | I79: SC-rawi2j | J79: =_xlfn.XLOOKUP(I79, ivp!$K:$K, ivp!$M:$M) -> #REF! | K79: {=_xlfn.XLOOKUP(I79,Sheet2!$C$2:$C$56,Sheet2!$G$2:$G$56)} -> #N/A | L79: called | M79: yes | N79: no idea
A80: 80 | B80: Kongu Engineering College | C80: 45808 | D80: Selected for Finals | E80: Agri-Tech | F80: 1 | G80: {=_xlfn.XLOOKUP(I80,' ivp'!S:S,#REF!)} -> #N/A | H80: 8610961896 | I80: SC-h83z6f | J80: =_xlfn.XLOOKUP(I80, ivp!$K:$K, ivp!$M:$M) -> #REF! | K80: {=_xlfn.XLOOKUP(I80,Sheet2!$C$2:$C$56,Sheet2!$G$2:$G$56)} -> #N/A | L80: called | M80: yes | N80: last checks
A81: 81 | B81: Mepco Schlenk Engineering College, Sivakasi | C81: 45808 | D81: finals - not interested | E81: blank | F81: 0 | G81: {=_xlfn.XLOOKUP(I81,' ivp'!S:S,#REF!)} -> #N/A | H81: 4562235104 | I81: SC-fs1xt | J81: =_xlfn.XLOOKUP(I81, ivp!$K:$K, ivp!$M:$M) -> #REF! | K81: {=_xlfn.XLOOKUP(I81,Sheet2!$C$2:$C$56,Sheet2!$G$2:$G$56)} -> #N/A
A82: 82 | B82: Sathyabama Institute of Science and Technology | C82: 45808 | D82: Selected for Finals | E82: Renewable Energy / Smart City | F82: 1 | G82: {=_xlfn.XLOOKUP(I82,' ivp'!S:S,#REF!)} -> #N/A | H82: 8807506879 | I82: SC-fp1ter | J82: =_xlfn.XLOOKUP(I82, ivp!$K:$K, ivp!$M:$M) -> #REF! | K82: {=_xlfn.XLOOKUP(I82,Sheet2!$C$2:$C$56,Sheet2!$G$2:$G$56)} -> https://drive.google.com/open?id=1OLvPZ68ByXNy7YfpMPQm7yBxDzWSn8pt | L82: need to apply ivp | M82: yes
A83: 83 | B83: College of Engineering, Guindy | C83: 45819 | D83: Selected to Pre-finals | E83: Health-Tech | F83: 1 | G83: {=_xlfn.XLOOKUP(I83,' ivp'!S:S,#REF!)} -> #N/A | H83: 9345520711 | I83: SS-q04a2 | J83: =_xlfn.XLOOKUP(I83, ivp!$K:$K, ivp!$M:$M) -> #REF! | K83: {=_xlfn.XLOOKUP(I83,Sheet2!$C$2:$C$56,Sheet2!$G$2:$G$56)} -> #N/A | M83: yes
A84: 84 | B84: Srinivasa Subbaraya Polytechnic College | C84: 45819 | D84: Selected to Pre-finals | E84: Food tech | F84: 1 | G84: {=_xlfn.XLOOKUP(I84,' ivp'!S:S,#REF!)} -> #N/A | H84: 9176232880 | I84: SC-qi0vx | J84: =_xlfn.XLOOKUP(I84, ivp!$K:$K, ivp!$M:$M) -> #REF! | K84: {=_xlfn.XLOOKUP(I84,Sheet2!$C$2:$C$56,Sheet2!$G$2:$G$56)} -> #N/A | M84: yes
A85: 85 | B85: Karunya Institute of Technology | C85: 45819 | D85: Selected for Finals | E85: Agri-Tech | F85: 1 | G85: {=_xlfn.XLOOKUP(I85,' ivp'!S:S,#REF!)} -> #N/A | H85: 8637449620 | I85: SC-j3pgz | J85: =_xlfn.XLOOKUP(I85, ivp!$K:$K, ivp!$M:$M) -> #REF! | K85: {=_xlfn.XLOOKUP(I85,Sheet2!$C$2:$C$56,Sheet2!$G$2:$G$56)} -> #N/A | L85: called | M85: yes
A86: 86 | B86: Sathyabama Institute of Science and Technology | C86: 45820 | D86: Selected for Finals | E86: EnviroTech | F86: 1 | G86: {=_xlfn.XLOOKUP(I86,' ivp'!S:S,#REF!)} -> #N/A | H86: ​6385161700 | I86: SC-tbel1l | J86: =_xlfn.XLOOKUP(I86, ivp!$K:$K, ivp!$M:$M) -> #REF! | K86: {=_xlfn.XLOOKUP(I86,Sheet2!$C$2:$C$56,Sheet2!$G$2:$G$56)} -> #N/A | L86: called | M86: yes
A87: 87 | B87: Tirunelveli Medical College | C87: 45820 | D87: Selected for Finals | E87: Health-Tech | F87: 1 | G87: {=_xlfn.XLOOKUP(I87,' ivp'!S:S,#REF!)} -> #N/A | H87: 9821350641 | I87: SC-rk3elg | J87: =_xlfn.XLOOKUP(I87, ivp!$K:$K, ivp!$M:$M) -> #REF! | K87: {=_xlfn.XLOOKUP(I87,Sheet2!$C$2:$C$56,Sheet2!$G$2:$G$56)} -> https://drive.google.com/open?id=1-9Wakw9eAXg6Our-F86qHsC68NeKtp7A | L87: called | M87: yes | N87: map problem - udayam/ last checks / need to apply
A88: 88 | B88: St. Joseph's College of Engineering , OMR, Chennai. | C88: 45821 | D88: Selected for Finals | E88: FinTech | F88: 1 | G88: {=_xlfn.XLOOKUP(I88,' ivp'!S:S,#REF!)} -> #N/A | H88: 9750821151 | I88: SC-ns7yu | J88: =_xlfn.XLOOKUP(I88, ivp!$K:$K, ivp!$M:$M) -> #REF! | K88: {=_xlfn.XLOOKUP(I88,Sheet2!$C$2:$C$56,Sheet2!$G$2:$G$56)} -> #N/A | L88: called | M88: yes | N88: exams
A89: 89 | B89: St. Joseph's Institute of Technology | C89: 45821 | D89: Selected for Finals | E89: Health-Tech | F89: 1 | G89: {=_xlfn.XLOOKUP(I89,' ivp'!S:S,#REF!)} -> #N/A | H89: 7358998645 | I89: SC-l8fdc | J89: =_xlfn.XLOOKUP(I89, ivp!$K:$K, ivp!$M:$M) -> #REF! | K89: {=_xlfn.XLOOKUP(I89,Sheet2!$C$2:$C$56,Sheet2!$G$2:$G$56)} -> #N/A | M89: yes
A90: 90 | B90: Sathyabama Institute of Science and Technology | C90: 45821 | D90: Selected for Finals | E90: blank | F90: 1 | G90: {=_xlfn.XLOOKUP(I90,' ivp'!S:S,#REF!)} -> #N/A | H90: 8807821116 | I90: SC-xbei4 | J90: =_xlfn.XLOOKUP(I90, ivp!$K:$K, ivp!$M:$M) -> #REF! | K90: {=_xlfn.XLOOKUP(I90,Sheet2!$C$2:$C$56,Sheet2!$G$2:$G$56)} -> https://drive.google.com/open?id=1tWJh1aNqjYXJaB4xffewaxs0cTIYca-r | L90: called | M90: yes
A91: 91 | B91: R.M.K. Engineering College | C91: 45821 | D91: Selected for Finals | E91: MAaaS | F91: 1 | G91: {=_xlfn.XLOOKUP(I91,' ivp'!S:S,#REF!)} -> #N/A | H91: 9150479903 | I91: SC-e2mmc2 | J91: =_xlfn.XLOOKUP(I91, ivp!$K:$K, ivp!$M:$M) -> #REF! | K91: {=_xlfn.XLOOKUP(I91,Sheet2!$C$2:$C$56,Sheet2!$G$2:$G$56)} -> #N/A | L91: need to call | M91: yes
A92: 92 | B92: Sathyabama Institute of Science and Technology | C92: 45822 | D92: Selected to Pre-finals | E92: blank | F92: 1 | G92: {=_xlfn.XLOOKUP(I92,' ivp'!S:S,#REF!)} -> #N/A | H92: 8838863843 | I92: SC-rw2it | J92: =_xlfn.XLOOKUP(I92, ivp!$K:$K, ivp!$M:$M) -> #REF! | K92: {=_xlfn.XLOOKUP(I92,Sheet2!$C$2:$C$56,Sheet2!$G$2:$G$56)} -> #N/A | M92: no
A93: 93 | B93: Sri Sairam Institute of Technology | C93: 45822 | D93: Selected for Finals | E93: SaaS | F93: 3 | G93: {=_xlfn.XLOOKUP(I93,' ivp'!S:S,#REF!)} -> #N/A | H93: 7539960504 | I93: SC-ireg2m | J93: =_xlfn.XLOOKUP(I93, ivp!$K:$K, ivp!$M:$M) -> #REF! | K93: {=_xlfn.XLOOKUP(I93,Sheet2!$C$2:$C$56,Sheet2!$G$2:$G$56)} -> https://drive.google.com/open?id=1oVGXQB851bH8GxkM8Q2Ul1WD3_NojREl | M93: yes
A94: 94 | B94: SSN College of Engineering | C94: 45822 | D94: Selected to Pre-finals | E94: Health-Tech | F94: 1 | G94: {=_xlfn.XLOOKUP(I94,' ivp'!S:S,#REF!)} -> #N/A | H94: 9498451242 | I94: SC-r5gvfa | J94: =_xlfn.XLOOKUP(I94, ivp!$K:$K, ivp!$M:$M) -> #REF! | K94: {=_xlfn.XLOOKUP(I94,Sheet2!$C$2:$C$56,Sheet2!$G$2:$G$56)} -> #N/A | M94: yes
A95: 95 | B95: Alagappa College of Technology | C95: 45822 | D95: Selected to Pre-finals | E95: Bio-Tech | F95: 1 | G95: {=_xlfn.XLOOKUP(I95,' ivp'!S:S,#REF!)} -> #N/A | H95: 8778446189 | I95: SC(BT)-pQ0NO | J95: =_xlfn.XLOOKUP(I95, ivp!$K:$K, ivp!$M:$M) -> #REF! | K95: {=_xlfn.XLOOKUP(I95,Sheet2!$C$2:$C$56,Sheet2!$G$2:$G$56)} -> #N/A | L95: send pref g invite link | M95: no
A96: 96 | B96: Rajalakshmi Engineering College | C96: 45825 | D96: Selected for Finals | E96: Agri-Tech | F96: 1 | G96: {=_xlfn.XLOOKUP(I96,' ivp'!S:S,#REF!)} -> #N/A | H96: 9384899474 | I96: SC-gyh4lg | J96: =_xlfn.XLOOKUP(I96, ivp!$K:$K, ivp!$M:$M) -> #REF! | K96: {=_xlfn.XLOOKUP(I96,Sheet2!$C$2:$C$56,Sheet2!$G$2:$G$56)} -> #N/A | L96: need to apply ivp | M96: yes
A97: 97 | B97: KCG College of Technology | C97: 45825 | D97: Selected for Finals | E97: blank | F97: 1 | G97: {=_xlfn.XLOOKUP(I97,' ivp'!S:S,#REF!)} -> #N/A | H97: 7305714848 | I97: SC-6y3eg | J97: =_xlfn.XLOOKUP(I97, ivp!$K:$K, ivp!$M:$M) -> #REF! | K97: {=_xlfn.XLOOKUP(I97,Sheet2!$C$2:$C$56,Sheet2!$G$2:$G$56)} -> #N/A | L97: called | M97: yes | N97: last checks
A98: 98 | B98: Sri Venkateswara College of Engineering | C98: 45826 | D98: Selected for Finals | E98: EV Services | F98: 1 | G98: {=_xlfn.XLOOKUP(I98,' ivp'!S:S,#REF!)} -> #N/A | H98: 8056096632 | I98: SC-fav05 | J98: =_xlfn.XLOOKUP(I98, ivp!$K:$K, ivp!$M:$M) -> #REF! | K98: {=_xlfn.XLOOKUP(I98,Sheet2!$C$2:$C$56,Sheet2!$G$2:$G$56)} -> #N/A | L98: called | M98: yes
A99: 99 | B99: St. Peter's College of Engineering and Technology | C99: 45826 | D99: Selected for Finals | E99: blank | F99: 1 | G99: {=_xlfn.XLOOKUP(I99,' ivp'!S:S,#REF!)} -> #N/A | H99: 8925481638 | I99: SC-zqwfns | J99: =_xlfn.XLOOKUP(I99, ivp!$K:$K, ivp!$M:$M) -> #REF! | K99: {=_xlfn.XLOOKUP(I99,Sheet2!$C$2:$C$56,Sheet2!$G$2:$G$56)} -> #N/A | L99: called | M99: no | N99: delusional
A100: 100 | B100: Alagappa College of Technology | C100: 45826 | D100: Selected for Finals | E100: Med-Tech | F100: 6 | G100: {=_xlfn.XLOOKUP(I100,' ivp'!S:S,#REF!)} -> #N/A | H100: 8122302503 | I100: SC(BT)-36X8Y | J100: =_xlfn.XLOOKUP(I100, ivp!$K:$K, ivp!$M:$M) -> #REF! | K100: {=_xlfn.XLOOKUP(I100,Sheet2!$C$2:$C$56,Sheet2!$G$2:$G$56)} -> #N/A | M100: yes
...

Sheet Sheet2
A1: Column 8 | B1: cross verfy start sno. | C1: Team ID | D1: Primary Contact Name | E1: Primary contact no. | F1: Primary Email. | G1: Please upload your Pitch presentation
B2: {=_xlfn.XLOOKUP(C2,Table1_2[TEAMID],Table1_2[`])} -> #N/A | C2: CEDAU-04 | D2: RESHMA C H | E2: 9940432697 | F2: binureshma110@gmail.com | G2: https://drive.google.com/open?id=1Ntxw63M7DcsoxOIi704XmNM8A5r7ezz0
B3: {=_xlfn.XLOOKUP(C3,Table1_2[TEAMID],Table1_2[`])} -> #N/A | C3: CEDAU-08 | D3: VISHNU PRASANNA DEVARAJAN | E3: 8608487249 | F3: vishnuprasanna.dl@gmail.com | G3: https://drive.google.com/open?id=16s3ed2pzozhPf-uAvWKXGMnci6USeI9O
B4: {=_xlfn.XLOOKUP(C4,Table1_2[TEAMID],Table1_2[`])} -> 144 | C4: GP-1bjcbo | D4: Saravanan K | E4: 9791005395 | F4: saravanankrish@annauniv.edu | G4: https://drive.google.com/open?id=1b5MrpNXt1nMVPylbe9wylHSNXuDk8qDu
B5: {=_xlfn.XLOOKUP(C5,Table1_2[TEAMID],Table1_2[`])} -> 145 | C5: GP-zvvwzi | D5: Dr.P.Ganesh Kumar | E5: 9791638370 | F5: drganesh30@gmail.com | G5: https://drive.google.com/open?id=1RaSKcvZtyuFxCyemLEnoqYmV2Y58scdO
B6: {=_xlfn.XLOOKUP(C6,Table1_2[TEAMID],Table1_2[`])} -> 114 | C6: PX-875q6 | D6: vetriprasath V | E6: 9600407657 | F6: vetriprasath59@gmail.com | G6: https://drive.google.com/open?id=1kkTkDVzx7IcjWyCseEaZRkQ-xYIfc6PJ
B7: {=_xlfn.XLOOKUP(C7,Table1_2[TEAMID],Table1_2[`])} -> 16 | C7: PX-9cgwli | D7: Suraj | E7: 7397252915 | F7: 8bix2024@gmail.com | G7: https://drive.google.com/open?id=1zZYNJcw9kwJdoQmeNNB9xPR9xS-vA50l
B8: {=_xlfn.XLOOKUP(C8,Table1_2[TEAMID],Table1_2[`])} -> 136 | C8: PX-xocu6 | D8: Antanet Anusha G | E8: 9384233122 | F8: anuthiraviam@gmail.com | G8: https://drive.google.com/open?id=1GTUuQ193iH8aPr4qTGOjSh7oj8tF1aN7
B9: {=_xlfn.XLOOKUP(C9,Table1_2[TEAMID],Table1_2[`])} -> 23 | C9: SC-07G6MO | D9: Tharaneeshwaran A | E9: 9361054415 | F9: tharaneeshwaran5555@gmail.com | G9: https://drive.google.com/open?id=1zH7oPcHBU2ypBkNZMJ-UzIHydcevpHCz
B10: {=_xlfn.XLOOKUP(C10,Table1_2[TEAMID],Table1_2[`])} -> 104 | C10: SC-1uzde | D10: Thilagaraaj .J | E10: 7845127728 | F10: 24it177@stjosephs.ac.in | G10: https://drive.google.com/open?id=1h9tBZeIaTYj8Em_ZR4Zz4Hh5uaf9SDvU
B11: {=_xlfn.XLOOKUP(C11,Table1_2[TEAMID],Table1_2[`])} -> #N/A | C11: SC-2aiz3p | D11: Mukeshkumar M | E11: 6380568055 | F11: mukeshkumar.cse24@gmail.com | G11: https://drive.google.com/open?id=1UJbWZgyLzAlkh7J9SHcaH0BMVLJ5RJMx
B12: {=_xlfn.XLOOKUP(C12,Table1_2[TEAMID],Table1_2[`])} -> #N/A | C12: SC-321ex | D12: Jayashree M | E12: 9344599054 | F12: jayashreemad0505@gmail.com | G12: https://drive.google.com/open?id=1MfHI_NNqr7AkbgYK9KOLmgUp_0weURL_
B13: {=_xlfn.XLOOKUP(C13,Table1_2[TEAMID],Table1_2[`])} -> 200 | C13: SC-3gcyak | D13: Muni Chandrasekar Reddy K | E13: 9962764646 | F13: kmcr2005@gmail.com | G13: https://drive.google.com/open?id=1uK1jvNK5uZzUPeWETKPYgSroJ5mXheZM
... B56: {=_xlfn.XLOOKUP(C56,Table1_2[TEAMID],Table1_2[`])} -> #N/A | C56: VEN-ZEPH-2773 | D56: Nevan.L | E56: 9445633545 | F56: nevan.28ee@licet.ac.in | G56: https://drive.google.com/open?id=1GgAzrhaWcpBPQsW6zHRD2g3L7XVQbRBh

Sheet review schedule
A1: letter no. : | C1: Name | D1: COMPLETED | E1: Contact | F1: TEAM ID | G1: startup name | H1: Domain | I1: Session no. | J1: College name
A2: blank | C2: Prathib Vamsi P | D2: COMPLETED | E2: 9003815145 | F2: cedau-06 | G2: MotorX Mobility Private Limited | H2: Consumables | I2: S6 | J2: EDII-TN
A3: 26 | C3: Aswath Vishnu.E | D3: COMPLETED | E3: 7845414195 | F3: PX-3ki6nJ | G3: ChrysoLux | H3: Enviro-Tech | I3: S5 | J3: SRM IST TRICHY
A4: 27 | B4: 1 | C4: Anjanarangarajan | D4: COMPLETED | E4: 9790339415 | F4: SC-9au7v | G4: Nova AI | H4: ai | I4: S1 | J4: St. Joseph's College of Engineering , OMR, Chennai.
A5: 31 | B5: 2 | C5: Armaan Patnaik | D5: COMPLETED | E5: 8939077434 | F5: SC-eanbmk | G5: FIOXYY-NEURAGENT | H5: ai | I5: S1 | J5: Madras Institute of Technology, Chromepet
A6: 25 | B6: 3 | C6: Arun Nivethan | D6: COMPLETED | E6: 7539960504 | F6: SC-ireg2m | G6: SPACE CRAFT AI | H6: ai | I6: S1 | J6: Sri Sairam Institute of Technology
A7: 30 | B7: 4 | C7: Aadhavan Valanarasu | D7: COMPLETED | E7: 9342049639 | F7: SC-rea6ge | G7: Niya Therapy Hub | H7: Ed-Tech | I7: S8 | J7: St. Joseph's College of Engineering , OMR, Chennai.
A8: 28 | C8: Sadhana | D8: COMPLETED | E8: 6385256271 | F8: SC-oyp2ts | G8: GeneGlow | H8: Agri-Tech | I8: S4 | J8: Adhiyamaan College of Agriculture and Research
A9: 33 | B9: 5 | C9: Shirish | D9: COMPLETED | E9: 8939747045 | F9: SC-hetzhm | G9: PickMyseat.ai | H9: ai | I9: S1 | J9: College of Engineering, Guindy
A10: 41 | B10: 6 | C10: Faheera Umu Salma | D10: COMPLETED | E10: 8681879364 | F10: SC(BT)-fFRV5 | G10: Diagnobee | H10: Med-Tech | I10: S7 | J10: Alagappa College of Technology
A11: 43 | C11: Deepika | D11: COMPLETED | E11: 7395956159 | F11: SC-qtithv | G11: Diatech | H11: Health-Tech | I11: S7 | J11: Sri Sairam Homoeopathy Medical College and Research Centre
A12: 42 | B12: 7 | C12: Saravanan | D12: COMPLETED | E12: 9791005395 | F12: GP-003 | G12: Animal Tradex | H12: ai | I12: S1 | J12: Faculty, CEG
A13: 45 | C13: Tharaneeswharan | D13: COMPLETED | E13: 9361054415 | F13: SC-07g6mo | G13: UZHAVAN | H13: Enviro-Tech | I13: S4 | J13: Velalar College of Engineering and Technology
A14: 44 | B14: 8 | C14: Shanmuga Pradeepan R | D14: COMPLETED | E14: 8438532004 | F14: SC-dg0km | G14: Edufyte | H14: ai | I14: S1 | J14: Sethu Institute of Technology
A15: blank | B15: 9 | C15: Vijay Krishnan | D15: COMPLETED | E15: 7305499740 | F15: SC-9e48xs | G15: Vision Solve | H15: Ed-Tech | I15: S8 | J15: College of Engineering, Guindy
A16: blank | B16: 10 | C16: Priya Roshni A | D16: COMPLETED | E16: 9363197584 | F16: SC-vnqnnm | G16: Orion AI | H16: ai | I16: S1 | J16: Vels University
A17: 52 | C17: Vetriprasath | D17: COMPLETED | E17: 9600407657 | F17: PX-875q6 | G17: DizziGuard | H17: Health-Tech | I17: S7 | J17: SRM IST TRICHY
A18: 48 | C18: Shakthi Prashanth G | D18: COMPLETED | E18: 7358629515 | F18: cedau-02 | G18: Gig AI Labs | H18: ai | I18: S1 | J18: EDII-TN
A19: 50 | C19: Ruthresh A | D19: COMPLETED | E19: 9003530044 | F19: CEDAU-33 | G19: Vitron | H19: ai | I19: S1 | J19: startup Walk in
A20: 49 | C20: Antanet Anusha G | D20: COMPLETED | E20: 9384233122 | F20: Px-xocu6 | G20: Millet-Based Electrolyte Beverages | H20: Food tech | I20: S4 | J20: Alagappa College of Technology
A21: 51 | C21: Sandiep Lakshman | D21: COMPLETED | E21: 9944039984 | F21: SC-vm5wp7 | G21: EternalEnergy | H21: Renewable Energy | I21: S5 | J21: College of Engineering, Guindy
A22: 52 | B22: 11 | C22: S Varshaa | D22: COMPLETED | E22: 9952048318 | F22: SC-ywojqq | G22: Learnsphere | H22: Ed-Tech | I22: S8 | J22: R.M.K. Engineering College
A23: 39 | C23: Purushothaman J | D23: COMPLETED | E23: 9176435615 | F23: SC-aodnso | G23: Grainforge3D Printer | H23: Industry 4.0 | I23: S3 | J23: College of Engineering, Guindy
A24: 55 | C24: Santhoshkumar P | D24: COMPLETED | E24: 9843930292 | F24: SC-Votrgd | G24: FITNGRO | H24: Health-Tech | I24: S7 | J24: P.A. College of Engineering and Technology
A25: 56 | C25: Mohammed Hussain Basith | D25: COMPLETED | E25: 7200326094 | F25: SC-83s9eo | G25: OCEAN WAVE ENERGY CONVERTER | H25: Renewable Energy | I25: S5 | J25: Madras Institute of Technology, Chromepet
C26: Mukesh Kumar R | D26: COMPLETED | E26: 8122687750 | F26: SC-fmdki | G26: RMK Aerospace and Sustainable Technology Private Limited | H26: Enviro-Tech | I26: S5 | J26: KCG College of Technology
A27: blank | C27: Vishnu Priya V | D27: COMPLETED | E27: 9789962388 | F27: SS-e7fr19 | G27: indyarn Clean Tech | H27: Agri-Tech | I27: S4 | J27: Alagappa College of Technology
A28: 61 | C28: Akshey Karthikeyan SK | D28: COMPLETED | E28: 9150452331 | F28: SC-2us6k | G28: Curio | H28: Fashion | I28: S6 | J28: PSG College of Technology, Coimbatore
A29: 60 | C29: Kotha Vamsi | D29: COMPLETED | E29: 6381784015 | F29: PX-cm2mr | G29: CHARGE ONE | H29: Auto ; EV | I29: S5 | J29: Saveetha Engineering College
A30: blank | B30: 12 | C30: Harini Premkumar | D30: COMPLETED | E30: 6381337230 | F30: SC-j51bjj | G30: Spar Shield+ | H30: Med-Tech | I30: S7 | J30: R.M.K. Engineering College
A31: blank | C31: Anantha Kumar | D31: COMPLETED | E31: 7845471602 | F31: cedau-39 | G31: Ztorys | H31: ai | I31: S1 | J31: startup Walk in
B32: 13 | C32: S Jeevesh | D32: COMPLETED | E32: 9025314278 | F32: SC-dyjltj | G32: Navogenix Technologies | H32: ai | I32: S1 | J32: Panimalar Engineering College
A33: blank | C33: Reshma Ch | D33: COMPLETED | E33: 9940432697 | F33: CEDAU-04 | G33: SanBio 360 | H33: Bio-Tech | I33: S7 | J33: College of Engineering, Guindy
A34: blank | B34: 14 | C34: Shabeera S | D34: COMPLETED | E34: 9042934637 | F34: SC-i8ijt | G34: SPEAK KARO | H34: Ed-Tech | I34: S8 | J34: Anand Institute of Higher Technology
A35: 57 | B35: 15 | C35: Ganesh Kumar P | D35: COMPLETED | E35: 9791638370 | F35: GP-zvvwzi | G35: UPI.Direct | H35: FinTech | I35: S8 | J35: College of Engineering, Guindy
A36: blank | B36: 16 | C36: Thanvi M | D36: COMPLETED | E36: 9380184164 | F36: SC-ewhypl | G36: SafeStride Tech | H36: ai | I36: S1 | J36: R.M.K. Engineering College
A37: blank | C37: Semmozhi Selvam S P | D37: COMPLETED | E37: 6382396276 | F37: SC-8heikl | G37: Quick Glow | H37: Consumables | I37: S6 | J37: College of Engineering, Guindy
A38: blank | C38: Kota Nageshwar | D38: COMPLETED | E38: 9363300142 | F38: CEDAU-07 | G38: Swatch Water Filters | H38: Consumables | I38: S6 | J38: Startup Walk in
A39: 29 | B39: 17 | C39: Satyendra / Lakshmi Priya | D39: COMPLETED | E39: 8092225251 | F39: IPO-ozm1k | G39: Scout Edge | H39: ai | I39: S1 | J39: IIT Madras
A40: 35 | B40: 18 | C40: Keerthana | D40: COMPLETED | E40: 8122302503 | F40: SC(BT)-36X8Y | G40: EcoShieldSPF | H40: Med-Tech | I40: S7 | J40: Alagappa College of Technology
C41: Suraj | D41: COMPLETED | E41: 7397252915 | F41: PX-9cgwli | G41: 8Bix | H41: Health-Tech | I41: S7 | J41: Meenakshi Sundararajan Engineering College
A42: 46 | C42: Sathishraj Selvaraj | D42: COMPLETED | E42: 6379496755 | F42: cedau-42 | G42: Bails | H42: ai | I42: S1 | J42: startup Walk in
B43: 19 | C43: Jeziel Praise Son | D43: COMPLETED | E43: 9042871766 | F43: SC-9a9rgd | G43: TrustIT | H43: deep-Tech | I43: S3 | J43: RVS Educational Trust's Group of Institutions
A44: 36 | B44: 20 | C44: Howard Nikhil | D44: COMPLETED | E44: 7094149367 | F44: SC-ss0phb | G44: Astro Access | H44: deep-Tech | I44: S3 | J44: University College of Engineering, Thirukkuvalai
A45: blank | C45: Vishnu Prasanna D | D45: COMPLETED | E45: 8608487249 | F45: CEDAU-08 | G45: DE la Greenspark | H45: Enviro-Tech | I45: S5 | J45: EDII-TN
B46: 21 | C46: Vignesh S | D46: COMPLETED | E46: 7358254947 | F46: SC-wv04l9 | G46: APIDS | H46: deep-Tech | I46: S3 | J46: St. Joseph's College of Engineering , OMR, Chennai.
A47: blank | B47: 22 | C47: Prempradeep S | D47: COMPLETED | E47: 7708365986 | F47: SC-b4jkfxa | G47: Aquaholics | H47: Deep-Tech | I47: S3 | J47: R.M.K. Engineering College
A48: blank | C48: AruldhaRaja Aiswarya | D48: COMPLETED | E48: 9791896178 | F48: SC-596dld | G48: Nova Bottles | H48: Consumables | I48: S6 | J48: College of Engineering, Guindy
C49: Gokkul M | D49: COMPLETED | E49: 9043405357 | F49: cedau-05 | G49: Aero rover | H49: Deep-Tech | I49: S3 | J49: Startup Walk in
A50: blank | C50: Santhoshjeferson | D50: COMPLETED | E50: 8903672237 | F50: SS-gxk3kp | G50: Jefey Composites | H50: Enviro-Tech | I50: S5 | J50: College of Engineering, Guindy
A51: blank | B51: 23 | C51: Tharani P S | D51: COMPLETED | E51: 7200939492 | F51: SC-8s2knl | G51: Auronox Private Limited | H51: Deep-Tech | I51: S3 | J51: St. Joseph's College of Engineering , OMR, Chennai.
A52: blank | B52: 24 | C52: Nikarika Ramesh | D52: COMPLETED | E52: 9790004554 | F52: SS-xiv9fo | G52: Vitasafe | H52: Deep-Tech | I52: S3 | J52: Alagappa College of Technology
A53: blank | C53: Salonica D | D53: COMPLETED | E53: 8825987128 | F53: SC-ox0pjd | G53: PlumeXB | H53: Bio-Tech | I53: S7 | J53: Sri Venkateswara College of Engineering
C54: Jeremiah Japheth | D54: COMPLETED | E54: 8148091100 | F54: cedau-11 | G54: CEG Motors | H54: Auto ; EV | I54: S5 | J54: College of Engineering, Guindy
C55: Parthsarathi | D55: COMPLETED | E55: 8610254655 | F55: SC-yd0hxd | G55: #N/A | H55: Health-Tech | I55: S7 | J55: Madras Institute of Technology, Chromepet
C56: Ranjith Karthikeyan | D56: COMPLETED | E56: 8883035691 | F56: SC-591xv | G56: Automaki | H56: Consumables | I56: S6 | J56: College of Engineering Guindy
A57: 70 | B57: 25 | C57: Vigneshwaran E | D57: COMPLETED | E57: 6382725434 | F57: SC-xu2qlg | G57: Blue Core Innovations | H57: Deep-Tech | I57: S3 | J57: College of Engineering Guindy, Anna University
A58: 74 | C58: Alex | D58: COMPLETED | E58: 9500194696 | F58: IPO-ojc1rs | G58: Geosonic | H58: Industry 4.0 | I58: S3 | J58: Startup Walk in
A59: 75 | B59: 26 | C59: Naveen Kanna | D59: COMPLETED | E59: 6374990762 | F59: SC-pcw53a | G59: Asynchonix | H59: Deep-Tech | I59: S3 | J59: Panimalar Engineering College
A60: 80 | B60: 27 | C60: Tejashree | D60: COMPLETED | E60: 8106872520 | F60: SC-v4m8f | G60: Little Hands | H60: Deep-Tech | I60: S3 | J60: Sathyabama Institute of Science and Technology
A61: 79 | B61: 28 | C61: Vendan U | D61: COMPLETED | E61: 8667282961 | F61: Sc-g8mwsh | G61: Tactical Bee | H61: Deep-Tech | I61: S3 | J61: St. Joseph's College of Engineering , OMR, Chennai.
A62: 78 | C62: Liya Therese A J | D62: COMPLETED | E62: 9626316318 | F62: SS-6h7rb | G62: Eclolin Ventures | H62: Agri-Tech | I62: S4 | J62: PSG College of Arts and Science
A63: 76 | B63: 29 | C63: Siva Subramaniyan | D63: COMPLETED | E63: 9342242802 | F63: SC-ug8ozm | G63: Trustable | H63: FinTech | I63: S8 | J63: PSG Institute of Technology and Applied Research
A64: 77 | B64: 30 | C64: Anil Kumar | D64: COMPLETED | E64: 9705933771 | F64: SC-os5t2w | G64: Runverve | H64: Med-Tech | I64: S7 | J64: IIT Madras
A65: blank | B65: 31 | C65: Sharvesh S | D65: COMPLETED | E65: 6369766990 | F65: PX-x22sud | G65: Sun-dram Technologies | H65: Deep-Tech | I65: S3 | J65: PSG Institute of Technology and Applied Research
A66: 53 | B66: 32 | C66: naveen kumar | D66: COMPLETED | E66: 8939724423 | F66: sc-3yn3y | G66: Pentastech | H66: Deep-Tech | I66: S3 | J66: St. Joseph's College of Engineering , OMR, Chennai.
A67: blank | C67: Dhanesh Km | D67: COMPLETED | E67: 9578124419 / 7200806009 | F67: SC-dbkdjs | G67: Agrogen | H67: Agri-Tech | I67: S4 | J67: Jeppiaar Institute of Technology
A68: blank | B68: 33 | C68: kalyani patra | D68: COMPLETED | E68: 8608499779 | F68: ipo-28zbru | G68: Smart Hundi | H68: Deep-Tech | I68: S3 | J68: Vellore Institute of Technology, Chennai
A69: blank | C69: Sivasubramani C | D69: COMPLETED | E69: 6364057474 | F69: SC-ecrjpqw | G69: ColdHot | H69: Consumables | I69: S6 | J69: Velammal Institute of Technology
A70: 38 | C70: Kavyashri K | D70: COMPLETED | E70: 6380541322 | F70: PX-jq5l4j | G70: Lignozyme | H70: Bio-Tech | I70: S7 | J70: College of Engineering, Guindy
A71: 52 | C71: Naveen P | D71: COMPLETED | E71: 9566834018 | F71: sc-zvs89 | G71: Sugarless Wonders | H71: Food tech | I71: S4 | J71: College of Engineering, Guindy
A72: 62 | C72: Jai Ganesh M | D72: COMPLETED | E72: 7358299188 | F72: cedau-03 | G72: Intra Mobility and Precision System Pvt Ltd | H72: Consumables | I72: S6 | J72: EDII-TN
A73: blank | C73: Sasikala Natarajamani | D73: COMPLETED | E73: 9884065356 | F73: CEDAU-13 | G73: Crea AI | H73: Health-Tech | I73: S7 | J73: College of Engineering, Guindy
A74: blank | C74: Subanesh | D74: COMPLETED | E74: 7395903061 | F74: cedau-14 | G74: Loopverse | H74: Deep-Tech | I74: S3 | J74: EDII-TN
A75: blank | C75: P.N. Chendilnadan | D75: not interested | E75: - | F75: cedau-15 | G75: #N/A | H75: #N/A | J75: EDII-TN
A76: blnk | B76: 34 | C76: sanjeev misd | D76: COMPLETED | E76: 9080861148 | F76: SC-n4aonf | G76: misd automation | H76: Deep-Tech | I76: S3 | J76: Erode Sengunthar Engineering College
A77: blank | B77: 35 | C77: W Karunakaran | D77: COMPLETED | E77: 9840620303 | F77: CEDAU-31 | G77: Pro EduVate | H77: Ed-Tech | I77: S8 | J77: Agni College of Technology
A78: blank | C78: Harish Kumar | D78: not interested | E78: 8248375363 | F78: cedau-16 | G78: #N/A | H78: #N/A | J78: EDII-TN
A79: 81 | C79: Athithya Rayan | D79: COMPLETED | E79: 6384712172 | F79: cedau-24 | G79: Hybrid Biofertilizer (Magasool) | H79: Agri-Tech | I79: S4 | J79: EDII-TN
A80: blank | B80: 36 | C80: Dr N. Vasudevan | D80: COMPLETED | E80: 9444910521 | F80: CEDAU-12 | G80: Rapikit | H80: Med-Tech | I80: S7 | J80: College of Engineering, Guindy
A81: blank | C81: Praveen Kumar R | D81: COMPLETED | E81: 8148402208 | F81: cedau-19 | G81: Namma Vivasayi | H81: Agri-Tech | I81: S4 | J81: EDII-TN
B82: 37 | C82: Mohammed Azgar | D82: COMPLETED | E82: 8148522265 | F82: SC-oajf6r | G82: SPREZOX | H82: SaaS | I82: S2 | J82: R.M.D. Engineering College
C83: P. Paneer Selvam | D83: COMPLETED | E83: 8675058253 | F83: sc-s98rzx | G83: Leogar Renewables | H83: Renewable Energy | I83: S5 | J83: Karpaga Vinayaga College of Engineering and Technology
C84: rithuparan p s | D84: COMPLETED | E84: 9150624440 | F84: SC-slpbfe | G84: Alertcare | H84: Health-Tech | I84: S7 | J84: R.M.K. Engineering College
C85: barath raj | D85: COMPLETED | E85: 8148232205 | F85: sc-mnnn9n | G85: Fluxora | H85: Industry 4.0 | I85: S3 | J85: Jansons Institute of Technology
B86: 38 | C86: maharaja pandian G | D86: COMPLETED | E86: 8270345463 | F86: sc-towsh | G86: Biomediac Solution X | H86: Med-Tech | I86: S7 | J86: Holycross Engineering College, Tuticorin
C87: rahul g | D87: COMPLETED | E87: 7305714848 | F87: SC-6y3eg | G87: Lensora AI | H87: blank | J87: KCG College of Technology
B88: 39 | C88: Selvakumar | D88: COMPLETED | E88: 9176529116 | F88: CEDAU-01 | G88: Ennamopenuphro Compute Technologies Pvt Ltd | H88: SaaS | I88: S2 | J88: Alumini, CEG
B89: 40 | C89: Sakthivel S | D89: COMPLETED | E89: 9944085762 | F89: CEDAU-09 | G89: Iyyansoft Technologies | H89: SaaS | I89: S2 | J89: College of Engineering, Guindy
C90: Vedhavarshan S | D90: COMPLETED | E90: 9361579843 | F90: sc-v80p8o | G90: SSGhealthcare pvt ltd | H90: Health-Tech | I90: S7 | J90: Easwari Engineering College
B91: 41 | C91: gopikakanagaraj | D91: COMPLETED | E91: 8610004262 | F91: SC-nx45i | G91: Haptic Verse | H91: Med-Tech | I91: S7 | J91: Ragas Dental College and Hospital
C92: R V Aswiga | D92: COMPLETED | E92: 9790341644 | F92: IPO-mf6d59 | G92: Simma Enterprise | H92: Health-Tech | I92: S7 | J92: Vellore Institute of Technology
B93: 42 | C93: Dharshini C | D93: COMPLETED | E93: 6382785930 | F93: SC-qdmhpb | G93: Harvo | H93: Med-Tech | I93: S7 | J93: VIVEKANANDHA COLLEGE OF ENGINNERING FOR WOMEN
C94: Mohammed Roshan Ibrahim | D94: COMPLETED | E94: 8754864334 | F94: SC-y4ea0v | G94: Hyrowah | H94: Enviro-Tech | I94: S5 | J94: KCG College of Technology
B95: 43 | C95: Saigovind V / Sadhana | D95: COMPLETED | E95: 9789095971 | F95: SC-bgbq2f | G95: SyncField | H95: SaaS | I95: S2 | J95: College of Engineering, Guindy
B96: 44 | C96: Muni Chandrasekar Reddy K | D96: COMPLETED | E96: 9962764646 | F96: SC-3gcyak | G96: APEX | H96: SaaS | I96: S2 | J96: College of Engineering, Guindy
C97: Navinkrishna K | D97: COMPLETED | E97: 8122980305 | F97: cedau-27 | G97: Gas Tech | H97: IoT | I97: S3 | J97: EDII-TN
B98: 45 | C98: AKASH RS | D98: COMPLETED | E98: 7305494413 | F98: SC-e4ss8o | G98: Veducate Skills and Technologies | H98: Ed-Tech | I98: S8 | J98: St.Joseph's college of engineering , OMR, Chennai.
C99: Thiru Kumaran Nr | D99: COMPLETED | E99: 7305184227 | F99: CEDAU-10 | G99: School Campus | H99: Ed-Tech | I99: S8 | J99: EDII-TN
C100: Nelson | D100: COMPLETED | E100: 7358734289 | F100: cedau-25 | G100: ResourceIndia.co | H100: Ed-Tech | I100: S8 | J100: EDII-TN
...

Sheet all funds -1926
A1: S.NO | B1: NAME | C1: COMPANY / PRODUCT NAME | D1: THRUST AREA | E1: Funding Scheme | F1: AMOUNT
A2: 1 | B2: Aadhavan Valanarasu | C2: Niya Therapy Hub | D2: AR/VR | E2: IVP | F2: ₹ 3,00,000
A3: 2 | B3: AKASH RS | C3: Veducate Skills and Technologies | D3: EduTech | E3: IVP | F3: ₹ 3,00,000
A4: 3 | B4: Akshey Karthikeyan SK | C4: Curio | D4: Fashion Tech | E4: IVP | F4: ₹ 3,00,000
A5: 4 | B5: Alex | C5: Geosonic | D5: Automobile | E5: IVP | F5: ₹ 3,00,000
A6: 5 | B6: Alex Bruno | C6: George Multitech System | D6: Industry 4.0 | E6: IVP | F6: ₹ 7,00,000
A7: 6 | B7: Aruldha Raja Aiswarya CA | C7: Nova Bottles | D7: Marine Tech | E7: Balakamalam | F7: ₹ 50,000
A8: 7 | B8: Aruldha Raja Aiswarya CA | C8: NOVA Ecotech | D8: Marine Tech | E8: IVP | F8: ₹ 2,93,000
A9: 8 | B9: Athithya Rayan | C9: Hybrid Biofertilizer (Magasool) | D9: Agri | E9: IVP | F9: ₹ 3,00,000
A10: 9 | B10: Ayush Upadhyay | C10: Crisp Roots | D10: Agri Tech | E10: Balakamalam | F10: ₹ 50,000
A11: 10 | B11: Chandrika Murali | C11: Fusillade Innotech Ventures | D11: IOT | E11: SISFS | F11: ₹ 10,00,000
A12: 11 | B12: Deepika | C12: Diatech | D12: MedTech | E12: IVP | F12: ₹ 3,00,000
A13: 12 | B13: Ezhilarasan M | C13: CARBONERGY CONSULTANCY | D13: IOT | E13: IVP | F13: ₹ 2,00,000
... A17: 16 | B17: Jai Ganesh M | C17: Intra Mobility and Precision System Pvt Ltd | D17: Electronic Consumables | E17: IVP | F17: ₹ 3,00,000
A18: 17 | B18: Janani Selvaganesh | C18: Verdent Vision | E18: IVP | F18: ₹ 2,60,000
A19: 18 | B19: Jeremiah Japheth | C19: CEG Motors | D19: Automobile | E19: IVP | F19: ₹ 2,97,000
A20: 19 | B20: Jeremiah Japheth | C20: CEG Motors | D20: Automobile | E20: EDII-TN | F20: ₹ 2,34,000
A21: 20 | B21: kalyani patra | C21: Vetri | D21: Deep Tech | E21: IVP | F21: ₹ 3,00,000
A22: 21 | B22: Karunakaran | C22: Pro Eduvate | E22: IVP | F22: ₹ 3,00,000
A23: 22 | B23: Kaviya Kannan | C23: Cold Storage | D23: Agri Tech | E23: Balakamalam | F23: ₹ 30,000
A24: 23 | B24: Kochadai M | C24: Ziggers | D24: SAAS | E24: IVP | F24: ₹ 3,00,000
A25: 24 | B25: Kota Nageshwar | C25: Swatch Water Filters | D25: IOT | E25: IVP | F25: ₹ 3,00,000
A26: 25 | B26: Lakshmi Priya | C26: Scout Edge | D26: Sports Tech | E26: IVP | F26: ₹ 3,00,000
A27: 26 | B27: Liya Therese A J | C27: PlantIn | D27: Agri | E27: Balakamalam | F27: ₹ 50,000
A28: 27 | B28: maharaja pandian G | C28: Biomediac Solution X | D28: BioTech | E28: IVP | F28: ₹ 3,00,000
A29: 28 | B29: Mohammed Roshan Ibrahim | C29: Hyrowah | D29: Water Tech | E29: Balakamalam | F29: ₹ 50,000
A30: 29 | B30: Mohammed Roshan Ibrahim | C30: Hyrowah | D30: Renewables | E30: IVP | F30: ₹ 3,00,000
A31: 30 | B31: Ms. M.Nirmaladevi Senthilkumar | C31: Namma ammuchi tradition foods | D31: Food Tech | E31: IVP | F31: ₹ 3,00,000
A32: 31 | B32: Mukesh Kumar R | C32: RMK | D32: Waste to Wealth | E32: GTP | F32: ₹ 1,00,000
A33: 32 | B33: Muruganantham R | C33: Global Technologies | E33: IVP | F33: ₹ 3,00,000
A34: 33 | B34: Muni Chandrasekar Reddy | C34: Apex | D34: SAAS | E34: IVP | F34: ₹ 2,97,000
A35: 34 | B35: Nikarika Ramesh | C35: Vitasafe | D35: MedTech | E35: IVP | F35: ₹ 3,00,000
A36: 35 | B36: P. Paneer Selvam / Krishna kumar | C36: Leogar Renewables | D36: Renewables | E36: IVP | F36: ₹ 3,00,000
A37: 36 | B37: Prathib Vamsi P | C37: MotorX Mobility Private Limited | D37: Automobile | E37: IVP | F37: ₹ 9,00,000
A38: 37 | B38: Prathib Vamsi P | C38: MotorX Mobility Private Limited | D38: Automobile | E38: TANSEED | F38: ₹ 10,00,000
A39: 38 | B39: Praveen B B | C39: PraIOT | D39: IOT | E39: GTP | F39: ₹ 1,00,000
A40: 39 | B40: Praveen B B | C40: PraIOT | D40: IOT | E40: IVP | F40: ₹ 2,88,000
A41: 40 | B41: Praveen Kumar R | C41: Namma Vivasayi | D41: Agri Tech | E41: IVP | F41: ₹ 3,00,000
A42: 41 | B42: Prempradeep S | C42: Aquaholics | D42: Industry 4.0 | E42: IVP | F42: ₹ 3,00,000
A43: 42 | B43: Prempradeep S | C43: Aquaholics | D43: Industry 4.0 | E43: Internal Hackhathon | F43: ₹ 1,000
A44: 43 | B44: Purushothaman J | C44: Grainforge3D Printer | D44: Industry 4.0 | E44: IVP | F44: ₹ 3,00,000
A45: 44 | B45: R V Aswiga | C45: Simma Enterprise | D45: Health Tech | E45: IVP | F45: ₹ 7,00,000
A46: 45 | B46: Ranjith Karthikeyan | C46: Automaki | D46: Automobile | E46: IVP | F46: ₹ 2,00,000
A47: 46 | B47: Ruthresh | C47: Vitron | E47: IVP | F47: ₹ 3,00,000
A48: 47 | B48: S Varshaa | C48: Learnsphere | D48: SAAS | E48: IVP | F48: ₹ 3,00,000
A49: 48 | B49: Salonika D | C49: Plume Xbio Pvt Ltd | D49: Waste to Wealth | E49: IVP | F49: ₹ 3,00,000
A50: 49 | B50: Sanjeev M | C50: MISD Automation | D50: IOT | E50: IVP | F50: ₹ 3,00,000
A51: 50 | B51: Sanjeev M | C51: MISD Automation | D51: IOT | E51: GTP | F51: ₹ 1,00,000
A52: 51 | B52: Saravanan | C52: Animal Tradex | D52: SAAS | E52: IVP | F52: ₹ 3,00,000
A53: 52 | B53: Sasikala Natarajamani | C53: Andro Crea Innovations Pvt ltd | D53: Bio Tech | E53: IVP | F53: ₹ 3,00,000
A54: 53 | B54: Selvakumar | C54: Ennamopenuphro Compute Technologies Pvt Ltd | D54: SAAS | E54: IVP | F54: ₹ 3,00,000
A55: 54 | B55: Semmozhi Selvam S P | C55: Quick Glow | D55: IOT | E55: IVP | F55: ₹ 3,00,000
A56: 55 | B56: Sharvesh S | C56: Sun-dram Technologies | D56: Deep Tech | E56: IVP | F56: ₹ 3,00,000
A57: 56 | B57: Sivasubramani C | C57: ColdHot (HydroX) | D57: Electronic Consumables | E57: IVP | F57: ₹ 3,00,000
A58: 57 | B58: Sriranjan | C58: Sentivest | D58: SAAS | E58: IVP | F58: ₹ 3,00,000
A59: 58 | B59: Suraj | C59: 8Bix | D59: MedTech | E59: IVP | F59: ₹ 2,97,000
... A68: 67 | B68: Vishnu Priya V | C68: Fashion to Farm | D68: Agri Tech | E68: IVP | F68: ₹ 3,00,000
B70: TOTAL | F70: ₹ 1,94,47,000

Sheet ivp - problem statement
A1: Si.no | B1: NAME | C1: IVP - STATUS | D1: submission date | E1: phone no. | F1: cross verify sno. | G1: preinc ; whatsapp group | H1: prototyping ; whatsapp group | I1: TEAM ID | J1: Domain Tags | K1: pitch deck file | L1: problem statement
A2: 1 | B2: Ruthresh A | C2: COMPLETED | E2: 9003530044 | F2: {=_xlfn.XLOOKUP(I2,startify3.0!I:I,startify3.0!A:A)} -> #N/A | H2: yes | I2: CEDAU-33 | J2: AI / ML, Fashion , App Development / Software | K2: https://drive.google.com/file/d/1fzGMOVP8oCSnj7eaLmstMJs_p2Kp5jbl/view?usp=sharing | L2: Fashion retail faces high return rates from customers' uncertainty about online clothing fit, appearance, and styling, plus challenges trying multiple outfits in physical stores, causing financial losses for retailers and inconvenience for buyers. Vitron addresses this widespread issue with an AI-powered virtual try-on platform that realistically shows garments on users and provides personalized outfit recommendations based on body type and preferences, deployable as software for both online and offline retail without expensive hardware
A3: 2 | B3: Aathavan Valanarasu | C3: COMPLETED | D3: 19/07/25 | E3: 9342049639 | F3: {=_xlfn.XLOOKUP(I3,startify3.0!I:I,startify3.0!A:A)} -> 3 | G3: preinc | H3: yes | I3: SC-rea6ge | J3: AI / ML, SaaS, EdTech, Bio Tech | K3: https://drive.google.com/file/d/1icj55HRkpEE6D2YhMiuNvMZMm4qS83lU/view?usp=sharing | L3: Autism Spectrum Disorder (ASD) affects 1 in 100 children globally (WHO 2023), impacting over 70 million people worldwide and 10 million in India, with limited therapy access in rural areas due to high costs and scarce trained therapists, burdening individuals with ASD, caregivers, families, therapy centers, and schools. Niya Therapy Hub solves this through a VR-based AI-driven platform on Meta Quest headsets, featuring immersive therapy environments, an AI virtual guide for personalized support, real-time progress tracking, and skill-building modules that blend therapy, education, and engagement—making it portable, scalable, and collaborative unlike costly traditional sessions or non-immersive apps, targeting a $2 billion+ global therapy market.
A4: 3 | B4: Abinaya | C4: COMPLETED | E4: 9080721623 | F4: {=_xlfn.XLOOKUP(I4,startify3.0!I:I,startify3.0!A:A)} -> #N/A | I4: CEDAU-37 | J4: EdTech, Enviro Tech | K4: https://docs.google.com/presentation/d/1mFOPCn7ZHKzvNicJaWvacJD6nFsAMFeD/edit?usp=sharing&ouid=104277249549708518105&rtpof=true&sd=true | L4: SenseUs addresses a major gap in workplace training, where traditional LMS-based programs create awareness but fail to drive lasting behavioral change. Organizations struggle with recurring communication issues, low engagement, and ineffective culture-building because employees rarely get opportunities to practice real workplace situations. SenseUs solves this through a simulation-based training platform that places employees in interactive, decision-driven workplace scenarios with real-time responses, progressive difficulty, and behavior-focused gamification. By enabling continuous practice, reinforcement, and measurable learning outcomes, SenseUs helps embed empathy, respect, and responsible workplace behavior into organizational culture, creating safer, more inclusive, and productive work environments.
A5: 4 | B5: abishek A | C5: COMPLETED | E5: 8610961896 | F5: {=_xlfn.XLOOKUP(I5,startify3.0!I:I,startify3.0!A:A)} -> 80 | I5: sc-h83z6f | J5: AgriTech, CleanTech , IoT / Hardware, food Tech | K5: https://drive.google.com/file/d/15VC3YOTSvBp5zx_f2_UnedEDj7sMRjGc/view?usp=sharing | L5: Hydros addresses the global need for sustainable, local food in water-scarce, urban and peri-urban regions, where families and small farmers lack space, depend on chemical-intensive soil farming, and face rising demand for healthy produce without affordable, efficient technology. Hydros proposes a solar-powered, IoT-driven aquaponics system that combines fish and plants in a closed-loop unit using sensors, automated pumps, and aeration to maintain water and nutrient balance, reducing water use by up to 90%, eliminating chemical inputs, and enabling compact, scalable, low-maintenance farming for households, small farmers, and institutions
A6: 5 | B6: Akash | C6: COMPLETED | E6: 8754728402 | F6: {=_xlfn.XLOOKUP(I6,startify3.0!I:I,startify3.0!A:A)} -> #N/A | H6: yes | I6: CEDAU-34 | J6: Bio Tech , Enviro Tech | K6: https://docs.google.com/presentation/d/1vvNjk_1_mJJVLriLTt7MFXxwPhGuccHt/edit?usp=sharing&ouid=104277249549708518105&rtpof=true&sd=true | L6: India's 77+ million diabetes patients rely on painful finger-prick tests or expensive, bulky Continuous Glucose Monitors (CGMs) that are inaccessible to rural users, rigid, short-lived, and battery-dependent. The solution is a flexible, skin-conformal wearable patch using microporous carbon electrodes from upcycled PET waste, sesame stalks, and sewage sludge, enabling non-invasive sweat-based glucose sensing via enzyme layers and PVA hydrogel, with smartphone Bluetooth connectivity for real-time monitoring at 10x lower cost.
A7: 6 | B7: AKASH RS | C7: COMPLETED | E7: 7305494413 | F7: {=_xlfn.XLOOKUP(I7,startify3.0!I:I,startify3.0!A:A)} -> 227 | H7: yes | I7: SC-e4ss8o | J7: AI / ML, EdTech , Saas | K7: https://docs.google.com/presentation/d/1WbLTAapfRoC1Jw8AjPoUSNHbaO1Bni6Q/edit?usp=sharing&ouid=104277249549708518105&rtpof=true&sd=true | L7: ZapSkill by Veducate Skills & Technologies tackles engineering students' lack of hands-on practical learning despite industry demands for job-ready skills, with existing platforms being theoretical, non-interactive, and lacking real-time AI guidance or progress tracking. Colleges struggle with outdated labs and monitoring, hindering scalable industry-ready talent development. The solution delivers browser-based interactive missions with cloud-powered real-time practice environments an adaptive AI mentor for instant personalized feedback/hints, and AI-driven skill progression analytics to identify gaps, recommend micro-tasks, and certify internship readiness
A8: 7 | B8: Akshay Karthikeyan Sk | C8: COMPLETED | D8: 19/12/25 | E8: 9150452331 | F8: {=_xlfn.XLOOKUP(I8,startify3.0!I:I,startify3.0!A:A)} -> 182 | H8: yes | I8: SC-2us6k | J8: Fashion / Lifestyle, Enviro Tech | K8: https://drive.google.com/file/d/1iWc68HJJJgFSsLxllZe3TY45JOCKec0Z/view?usp=sharing | L8: Active individuals, professionals, and people in hot/humid/active environments experience discomfort and self-consciousness from body odor and fading clothing freshness throughout the day, as current apparel lacks lasting fragrance or odor control. Curio solves this through microencapsulation technology embedding fragrance microcapsules into fabric fibers during textile finishing for smart release via friction/heat/movement, delivering long-lasting freshness surviving 30-40 washes using eco-friendly non-toxic materials, offered as stylish affordable D2C apparel targeting Gen Z/millennials/active lifestyle adopters within India's $8.89B functional apparel market and $160.2M→$857.9M smart textiles niche (20.5% CAGR).
A9: 8 | B9: Alex | C9: COMPLETED | E9: 9500194696 | F9: {=_xlfn.XLOOKUP(I9,startify3.0!I:I,startify3.0!A:A)} -> 221 | H9: yes | I9: IPO-ojc1rs | J9: IoT / Hardware | K9: https://drive.google.com/file/d/1Ut3XYaHh13bLRoFmhbJoREBB6yk05q2M/view?usp=sharing | L9: Geosonic explores unsafe interactions between overhead and floor cranes in heavy equipment factories, where existing light-based anti-collision sensors are unreliable due to dust, lighting variations, maintenance difficulty, and blind spots, creating significant risk of collisions and accidents across dynamic crane operations. The solution is a scalable, low-cost ultrasonic sensor–based anti-collision system using custom microcontroller PCBs, a PLC-controlled sensing setup, MODBUS communication, and a handheld interface to ensure accurate distance detection, coordinated crane interlocking, and easier deployment across multiple crane systems
A10: 9 | B10: Anantha Kumar | C10: COMPLETED | D10: #N/A | E10: 7845471602 | I10: cedau-39 | J10: Fin Tech , App Development / Software | K10: https://drive.google.com/file/d/1zwrG0J_pCo6yZG42LAl7d5Jx_zdp-LZ_/view?usp=sharing | L10: Ztorys is a multi-language digital publishing platform that empowers writers to earn directly from their content without technical barriers or upfront costs. Addressing declining search traffic, high website setup expenses, and unstable monetization, Ztorys enables creators to publish in 340+ languages and earn through 55% ad revenue sharing, sponsored content, promotions, and affiliate commissions. With 110+ active writers, 250+ articles, and growing monthly engagement, the platform combines long-form articles and short “Notes” for virality and discovery. Targeting India’s 15 million writers and global creators, Ztorys aims to build a scalable, YouTube-like monetization ecosystem for written content
A11: 10 | B11: Anil Kumar | C11: COMPLETED | E11: 9705933771 | F11: {=_xlfn.XLOOKUP(I11,startify3.0!I:I,startify3.0!A:A)} -> 191 | H11: yes | I11: SC-os5t2w | J11: Consumables , Bio Tech, Sports Tech | K11: https://docs.google.com/presentation/d/1qyALgLmfBGwRQZVtXpNxFVOCOLST_2BK/edit?usp=sharing&ouid=104277249549708518105&rtpof=true&sd=true | L11: The problem is widespread chronic pain and muscle fatigue—affecting 1.5 billion people globally, 13% of adults in India, and 79% of people with joint pain—while current solutions like massage guns, heating pads, and TENS devices are bulky, stationary, or inconvenient, requiring active use or sticky pads. This under-served need exists within a rapidly growing global pain-management and sports recovery market worth tens of billions of dollars. The solution, SMARTHEAL, is a lightweight, wearable, washable massager combining heat, vibration, and TENS/EMS electrotherapy, delivering continuous, hands-free, app-controlled pain relief during daily activities.
A12: 11 | B12: Anjanarangarajan | C12: COMPLETED | D12: 45968 | E12: 9790339415 | F12: {=_xlfn.XLOOKUP(I12,startify3.0!I:I,startify3.0!A:A)} -> 52 | H12: yes | I12: SC-9au7v | J12: AI / ML, IoT / Hardware | K12: https://drive.google.com/file/d/1YWnN75jWtxNAdKR8L3b7q3YvrpJshX1-/view?usp=sharing | L12: NOVA AI addresses industrial hazards in chemical manufacturing MSMEs like those in Sivakasi, where manual monitoring fails to detect early gas leaks, thermal hotspots, and machine stress, leading to frequent fires, toxic exposures, and equipment failures. India reports 48,000+ factory accidents and 6,500+ fatalities (2017-2021), with Tamil Nadu among the top states and Sivakasi fireworks seeing 500+ fires, 300+ deaths over 10 years; 80% of factories lack real-time safety systems costing ₹50,000+ per node. The solution is an edge AI-powered multi-sensor system (thermal, gas, vibration, vision on Jetson Nano) for real-time hazard detection, automated shutdowns/ventilation, predictive maintenance, PPE compliance, and reports—all offline at ₹18-25k per modular node, 30-50% cheaper via local processing without cloud fees.
A13: 12 | B13: Antanet Anusha G | C13: COMPLETED | D13: 14/11/25 | E13: 9384233122 | F13: {=_xlfn.XLOOKUP(I13,startify3.0!I:I,startify3.0!A:A)} -> 136 | H13: yes | I13: Px-xocu6 | J13: Bio Tech, Food Tech | K13: https://docs.google.com/presentation/d/1GTUuQ193iH8aPr4qTGOjSh7oj8tF1aN7/edit?usp=sharing&ouid=104277249549708518105&rtpof=true&sd=true | L13: Commercial electrolyte drinks suffer from high sugar content (20–35g per serving), costly premium options 40–60% more expensive, single-use PET plastic packaging, and high water/carbon footprints in a USD 42.6B global market (2024) projected to USD 74.2B by 2034, driving obesity, diabetes, and metabolic risks especially among athletes, children, diabetics, and low-income consumers. The millet-based electrolyte beverage solution uses controlled germination of millets (finger/proso) to activate phytase for 2–3× higher natural mineral absorption (Ca²⁺, Mg²⁺, Fe²⁺, Zn²⁺), delivers low-glycemic hydration with prebiotic oligosaccharides, antioxidants, gut health support, and 70% less water usage in a sustainable, clean-label formulation safe for diabetics/children.
A14: 13 | B14: Aparup Roy | C14: COMPLETED | E14: 9476478885 | I14: cedau-38 | J14: AI / ML, SaaS | K14: https://drive.google.com/file/d/1ghr4wKJHaB9cM-p8gmva4wiN-FUH3Mmg/view?usp=sharing | L14: SENSChat is a zero-trace anonymous consensus platform addressing three gaps: identity fear on profile-linked social media that suppresses honest sharing of relationship/work/mental health dilemmas, skewed feedback in identity-tracked corporate surveys, and endless argument loops on Reddit/Quora with no conclusive outcome. The solution is an LLM-moderated (Grok API/Llama 4 Scout) sanctuary that purges IP/email data, gates voting behind a 200+ reputation threshold, and ends every thread with a locked crowd verdict. Hybrid model: B2C rewards (₹5–15 per streak/vote/comment) drives logic-quality contributors; B2B sells un-sanitized sentiment reports (₹499 standard, ₹999 premium) at 35–40% margin, targeting the $80B market research industry.
A15: 14 | B15: Armaan Patnaik | C15: COMPLETED | D15: 31/10/25 | E15: 8939077434 | F15: {=_xlfn.XLOOKUP(I15,startify3.0!I:I,startify3.0!A:A)} -> 149 | H15: yes | I15: SC-eanbmk | J15: AI / ML, SaaS | K15: https://docs.google.com/presentation/d/1J48yzTB4_Zx3WazHZzagoKl9RPujXHf-/edit?usp=sharing&ouid=104277249549708518105&rtpof=true&sd=true | L15: Employees spend 2+ hours daily searching for right documents and information within them, with 60% affected and legal, healthcare, manufacturing sectors facing critical knowledge retrieval issues due to disorganized enterprise data and scattered information sources leading to ineffective search performance and unreliable content retrieval. Neuragent is a cloud-native SaaS platform combining neural semantic search and RAG-LLM pipelines with multi-tenant vector database management using FAISS for similarity search, transformer-based embeddings for semantic understanding, RESTful APIs for enterprise integration, and real-time document indexing. The solution delivers 5x higher accuracy than legacy keyword-based systems with context-aware, generative AI responses, 99.9% uptime enterprise-grade security, and ROI within 6 months targeting 10,000+ enterprises across legal, healthcare, manufacturing sectors.
A16: 15 | B16: Aruldha Raja Aiswarya Ca | C16: COMPLETED | E16: 9791896178 | F16: {=_xlfn.XLOOKUP(I16,startify3.0!I:I,startify3.0!A:A)} -> 198 | H16: yes | I16: SC-596dld | J16: Bio Tech, Enviro Tech | K16: https://drive.google.com/file/d/16L1EekCBLUWcJ2222051da0cnQvXCEjA/view?usp=sharing | L16: NOVA Ecotech develops 100% biodegradable water bottles from a novel biopolymer blend that decomposes in 4 years (marine)/2 years (land) vs PET's centuries-long persistence (500B bottles/year produced, only 9-12% recycled, projected to outnumber ocean fish in 30 years, leaching phthalates/BPA). Non-toxic/BPA-free with PET-like strength/barrier properties at lower carbon footprint (₹27 bulk B2B/₹30 retail), it outperforms Cove/Hilly (less biodegradable) and Tetra Pak/Aquafina (non-marine safe), targeting airports/resorts/corporates/hospitals (B2B) + eco-urban consumers (B2C) via partners/expos. Stage 1 (biopolymer selection) complete, Stage 2 (lab validation) ongoing;
A17: 16 | B17: Arun Nivethan | C17: COMPLETED | D17: 19/12/25 | E17: 7539960504 | F17: {=_xlfn.XLOOKUP(I17,startify3.0!I:I,startify3.0!A:A)} -> 93 | H17: yes | I17: SC-ireg2m | J17: AI / ML, FinTech, , Deep Tech | K17: https://docs.google.com/presentation/d/1cBdWM-yx1Et9L-TzJYMXq4fBO_v_P6uC/edit?usp=sharing&ouid=104277249549708518105&rtpof=true&sd=true | L17: Homeowners and designers in India face fragmented home renovation processes with visualization difficulties, cost uncertainty from opaque local pricing, unreliable suppliers/contractors, and complex project management lacking transparency and control. Space Craft AI solves this via an AI-powered platform offering real-time culturally relevant design visualization (Stable Diffusion + ControlNet reducing design time 70%/costs 50%), instant location-specific cost estimates, smart matching with verified RERA-compliant contractors/suppliers via uploaded material lists with competitive quotes, AI-driven project scheduling/milestone tracking/escrow payments, AR/VR previews, targeting India's ₹5,070B home services TAM (₹42B online SAM) fueled by urbanization and 60%+ digital-first urban consumers through 15-20% commissions, premium listings, subscriptions, and ads.​
A18: 17 | B18: Aswath Vishnu.E | C18: COMPLETED | D18: 45968 | E18: 7845414195 | F18: {=_xlfn.XLOOKUP(I18,startify3.0!I:I,startify3.0!A:A)} -> 22 | H18: yes | I18: PX-3ki6nJ | J18: AgriTech, Fashion / Lifestyle, Enviro Tech | K18: https://docs.google.com/presentation/d/17APXum_6v75puPYL7bfg9TQt7yJJxsxX/edit?usp=sharing&ouid=104277249549708518105&rtpof=true&sd=true | L18: The leather industry relies on animal leather (causing deforestation, methane emissions, and toxic tanning) and PU/PVC vegan leather (petroleum-derived, non-biodegradable, causing microplastic pollution). The global leather goods market is valued at $498.57 billion (2024), growing to $855.36 billion (2032), while the vegan leather market is $82.19 billion (2024), projected to reach $198.17 billion (2034). Chrysolux addresses this by developing mycelium-based leather combined with Black Soldier Fly chitin coating, creating a 100% biodegradable, plastic-free, chemical-free material with water resistance and antimicrobial properties
A19: 18 | B19: Athithya Rayan R | C19: COMPLETED | D19: 28/11/25 | E19: 6384712172 | F19: {=_xlfn.XLOOKUP(I19,startify3.0!I:I,startify3.0!A:A)} -> #N/A | H19: yes | I19: cedau-24 | J19: AgriTech | K19: https://drive.google.com/file/d/1TQHqyQdolrHhxhMYy4F0qSG_uUNK2Vpv/view?usp=sharing | L19: Magasool Agri Tech addresses the twin crisis faced by inorganic and organic farmers: chemical fertilizers deliver fast yields but degrade soil, pollute water, and are costly, while traditional organic methods are slow, inconsistent, and labor-intensive, creating an urgent gap for fast yet sustainable solutions. Magasool Agri Tech proposes a hybrid biofertilizer derived from seaweed and NPK-fixing microbes that delivers quick yield improvements, restores soil health and microbial life, supplies balanced macro- and micronutrients, and is easy to apply across diverse crops and soils, enabling farmers to transition toward sustainable agriculture without sacrificing productivity
A20: 19 | B20: B. Dhinesh (2020-21) | C20: completed - prev startify | I20: CEDAU1-02
A21: 20 | B21: barath raj | C21: COMPLETED | E21: 8148232205 | F21: {=_xlfn.XLOOKUP(I21,startify3.0!I:I,startify3.0!A:A)} -> 37 | H21: yes | I21: sc-mnnn9n | J21: IoT / Hardware , App Development / Software | K21: https://drive.google.com/file/d/1Ah--a7bYtRmDx9Kk1r_kXVKF3d9aC0Po/view?usp=sharing | L21: Fluxora addresses costly, inefficient street lighting in Indian cities, where lights run at full brightness without need, failures go undetected, and lack of automation leads to energy waste, higher emissions, and safety risks. The scale of the problem involves city-wide networks that lose crores of rupees annually and create dark zones when lamps fail. The solution, Fluxora SmartLight, is an IoT-enabled system using sensor fusion, LoRa communication, and AI-based analytics to adapt brightness to movement and weather, detect faults in real time, cut electricity use by 60–70%, extend lamp life, and enable centralized monitoring for large deployments.
A22: 21 | B22: bhuvana | C22: COMPLETED | E22: 8807800947 | F22: {=_xlfn.XLOOKUP(I22,startify3.0!I:I,startify3.0!A:A)} -> 21 | H22: yes | I22: SC-paxd4f | J22: AI / ML , App Development / Software | K22: https://drive.google.com/file/d/1xq7J9KAZck44UQZR2L1-9K3gje5SnQ5O/view?usp=sharing | L22: There is widespread problem of harmful screen use and digital fatigue, where over 63% of parents and 72% of teens report negative impacts like addiction, weak family bonds, and reduced emotional connection, especially in urban and semi-urban families heavily reliant on devices. This affects millions of parents, children, teens, educators, and mental health professionals globally. The solution is KinSync, an AI-powered mobile platform that combines shared planning, screen-time visualization, memory sharing, and age-based bonding and wellness activities into a single family app, aiming to reduce screen time and strengthen relationships through personalized, togetherness-focused experiences.
A23: 22 | B23: Chandrika Murali | C23: COMPLETED | E23: 7708592890 | I23: cedau-46 | J23: E-commerce , App Development / Software | K23: https://drive.google.com/file/d/1DlTjyBNXXg7rvTQiMFflasG6_1AsoxPH/view?usp=drive_link | L23: DECHTA (Fusillade Innotech Ventures LLP, Chennai) is a one-stop digital construction commerce and workforce platform tackling India's fragmented ecosystem, where 50%+ of the 36–70M construction workforce is informal, materials aren't reliably available, pricing is opaque, and Tamil Nadu's 25 lakh+ workers stay disconnected from demand. It unifies material procurement (multi-vendor), skilled worker hiring (masons, plumbers, electricians, carpenters), delivery coordination, and project monitoring on a single app — features scattered across HomeRun, Urban Company, Apna, WorkIndia, IndiaMart. Revenue via commissions on materials, worker bookings, deliveries, interiors, and ads. Currently at MVP stage, seeking ₹7.75L (₹7L from EDII-TN Innovation Voucher), targeting 200+ vendors, 300+ workers, 150+ business customers, and ₹50L+ GTV in 12 months. Claimed impact: 60% faster procurement, 10–20% cost savings.
A24: 23 | B24: Deepika | C24: COMPLETED | D24: 46000 | E24: 7395956159 | F24: {=_xlfn.XLOOKUP(I24,startify3.0!I:I,startify3.0!A:A)} -> 70 | G24: preinc | I24: SC-qtithv | J24: Bio Tech, IoT / Hardware, App Development / Software | K24: https://drive.google.com/file/d/1OUSJwH2xDGJqMtzE109n35wkSSxf7pE8/view?usp=sharing | L24: Peripheral neuropathy silently affects 50%+ of India's 100M+ diabetics, particularly in rural (50M+) and semi-urban areas where every 1 in 2 diabetics is at risk, with no early warning symptoms (numbness, burning pain, foot ulcers) until it's too late, and existing tools like expensive VibraSense, NeuroTouch, digital/analog biothesiometers are costly, non-portable, and inaccessible even in cities. Neurotronix's Diatec-D is a portable, affordable, app-guided smart diagnostic device for early non-invasive neuropathy detection, featuring a compact prototype (81x38mm) with motor, sensors, and mobile app integration for patient data entry (name, age, diabetes duration, ulcer history), outperforming expensive/non-portable alternatives through its accessible design targeting government PHCs, diabetic NGOs, hospitals, and clinics amid a global diabetic population of 537M where half develop neuropathy.​
A25: 24 | B25: Dhanesh Km | C25: COMPLETED | E25: 9578124419 / 7200806009 | F25: {=_xlfn.XLOOKUP(I25,startify3.0!I:I,startify3.0!A:A)} -> 156 | I25: SC-dbkdjs | J25: AI / ML, AgriTech, E-Commerce, IoT / Hardware, App Development / Software | K25: https://drive.google.com/open?id=1AKxv-vEykgim5SRlL5e67fYOaca71-EL | L25: AgroGen is an AI-powered smart farming assistant and marketplace designed for small and marginal Indian farmers. It tackles fragmented landholdings, climate volatility, pests, lack of real-time soil/crop insights, exploitative middlemen, low digital literacy, and poor access to schemes and finance, all of which keep yields low and incomes unstable. The solution combines AI-driven soil and crop analysis, weather-based advisory, real-time market intelligence, a multi-language + SMS chatbot, a transparent vendor marketplace with APMC-approved suppliers, and on-demand shared services (drones, machinery, skilled labour) in one simple, affordable platform that’s scalable for individual farmers, cooperatives, NGOs and government programs, with strong social and environmental impact.
A26: 25 | B26: Dharshini C | C26: COMPLETED | E26: 6382785930 | F26: {=_xlfn.XLOOKUP(I26,startify3.0!I:I,startify3.0!A:A)} -> #N/A | H26: yes | I26: SC-qdmhpb | J26: AgriTech, Enviro Tech | K26: https://docs.google.com/presentation/d/1wggAGBMSMlgdD-zX_qRXkmL0vKLyx013/edit?usp=sharing&ouid=104277249549708518105&rtpof=true&sd=true | L26: The problem addressed is the need for effective tomato preservation without reliance on refrigeration. The scale of the problem is significant, as it targets post-harvest losses and preservation challenges in contexts where cold storage is limited or unavailable. The developed solution focuses on a smart, non-refrigerated tomato preservation approach. The project proposes a technically driven method with defined competitive and technical advantages, aimed at extending usability and reducing wastage. The solution is designed to deliver social and environmental benefits while remaining cost-effective, supported through a grant model covering a major portion of the project cost
A27: 26 | B27: Dr N. Vasudevan | C27: COMPLETED | E27: 9444910521 | F27: {=_xlfn.XLOOKUP(I27,startify3.0!I:I,startify3.0!A:A)} -> #N/A | H27: yes | I27: CEDAU-12 | J27: SaaS, Bio Tech | K27: https://drive.google.com/file/d/1Em_cP1ecMnwQxTbmcsLeqcczsvVaZdln/view?usp=sharing | L27: Rapikit Hp by Pocgen Technologies LLP is a rapid, visual molecular diagnostic kit for detecting Helicobacter pylori using a malachite green-based Loop-Mediated Isothermal Amplification (MG-LAMP) assay. Addressing limitations of Rapid Urease Tests and non-portable PCR methods, the kit offers high sensitivity and specificity with a simple color change visible to the naked eye. Operable at a constant 65°C using basic equipment like a water bath, it eliminates complex DNA extraction and reduces false positives. Designed for point-of-care and low-resource settings, Rapikit Hp enables faster, reliable bedside diagnosis, supporting early treatment of gastritis, peptic ulcers, and gastric cancer while improving healthcare accessibility and affordability
A28: 27 | B28: Dr.R.Senthilnathan | C28: COMPLETED | E28: 9894119040 | F28: {=_xlfn.XLOOKUP(I28,startify3.0!I:I,startify3.0!A:A)} -> #N/A | I28: cedau-22 | J28: AI / ML, SaaS, Bio Tech, IoT / Hardware | K28: https://docs.google.com/presentation/d/19KDfehkfiMjlVS4MmIh7c7SpujP0fHpK/edit?usp=sharing&ouid=104277249549708518105&rtpof=true&sd=true | L28: Ventilators in critical care lack continuous IoT monitoring, leaving biomedical teams without breakdown visibility, increasing patient risks from delayed detection, burdening clinicians with manual tracking, and causing missed failure alerts, which heighten mortality in ICUs/NICUs/PICUs. The solution is an end-to-end ecosystem with non-invasive smart sensors tracking vibration, pressure, airflow, and humidity; a central IoT gateway; cloud platform for real-time data intelligence; and AI-driven predictive maintenance with automated alerts/ticketing, enabling proactive fixes for 99.9% availability via universal retrofit on existing ventilators
A29: 28 | B29: E B Priyanka | C29: COMPLETED | E29: 8098927503 | I29: IPO-slh17e | J29: EdTech, FinTech, Enviro Tech | K29: https://docs.google.com/presentation/d/1MuQWS_G1HplPIFw5TjucIqjiErc1qDXv/edit?usp=sharing&ouid=104277249549708518105&rtpof=true&sd=true | L29: AquaMorph tackles global plastic pollution by automatically converting natural seaweed into biopolymer pellets, addressing the gap where polysaccharide-rich bioplastics remain underused despite seaweed's high biomass potential and China/Indonesia/Korea's massive existing seaweed production. The solution processes seaweed — pulverized, blended with PE/PLA, extruded, and coated with antibacterial ginkgo biloba extract — into durable, ~25% bio-based films for food packaging and antibacterial storage, replacing single-use plastics with biodegradable, CO₂-absorbing alternatives. Revenue spans core resin/film sales (55%), FMCG packaging contracts, by-products, licensing, and blue-carbon credits, targeting corporate ESG partners (Unilever, Nestlé) amid a market growing from $27B (TAM, 2025) to $68B by 2035.
A30: 29 | B30: Ezhilarasan M (2024-25) | C30: completed - prev startify | E30: 7904236600 | F30: {=_xlfn.XLOOKUP(I30,startify3.0!I:I,startify3.0!A:A)} -> #N/A | G30: preinc | I30: CEDAU1-05
A31: 30 | B31: Faheera Umu Salma | C31: COMPLETED | D31: 46000 | E31: 8681879364 | F31: {=_xlfn.XLOOKUP(I31,startify3.0!I:I,startify3.0!A:A)} -> 101 | H31: yes | I31: SC(BT)-fFRV5 | J31: Bio Tech, IoT / Hardware | K31: https://docs.google.com/presentation/d/18z-76Mx5ICtmDs3BWvgoQi21dn9ekcDy/edit?usp=sharing&ouid=104277249549708518105&rtpof=true&sd=true | L31: Silent heart attacks go unnoticed in 45% of cases worldwide, with high risk in diabetics, elderly, and women, while current diagnostic tests (ECG, troponin) miss early signs and detect damage only after occurrence, leading to disabilities and high healthcare costs. DiagnoBee's CardioSense patch addresses this with a painless microneedle-based device that detects early cardiac microRNAs (miR-208a, miR-133a, miR-499-5p) released before troponins appear, using aptamer technology for specific binding and fluorescent UV-based detection—offering multiplex detection of three markers on a single strip in ~20 minutes without lab infrastructure or skilled staff, at ₹490 per unit cost with portable smartphone app readout for self-monitoring and clinical verification options, enabling scalable access for rural health programs, ambulances, and primary health centers.​
A32: 31 | B32: G Rathi | C32: COMPLETED | E32: 9952437272 | F32: {=_xlfn.XLOOKUP(I32,startify3.0!I:I,startify3.0!A:A)} -> #N/A | I32: CEDAU-28 | J32: SaaS, EV / Mobility, App Development / Software | K32: https://docs.google.com/presentation/d/1FXIGWLrifrRMQscDpQMdcN-VyYJj8lRY/edit?usp=sharing&ouid=104277249549708518105&rtpof=true&sd=true | L32: AmpTrail by Nexoris Solutions is India's first real-time EV charging slot booking platform, solving EV owners' 30-60 minute waits at busy stations due to no slot visibility, inefficient charger utilization, fragmented multi-app experiences with manual payments, grid overloads from poor scheduling, and adoption barriers slowing India's EV transition. The app enables live availability tracking, advance reservations, OTP-secured payments via Razorpay, operator dashboards for utilization management, and cloud analytics (Flutter/Node.js/Firebase stack), with AI-ready scalability for predictive load balancing—ensuring zero wait times and seamless ecosystem integration
A33: 32 | B33: Ganesh Kumar P | C33: COMPLETED | E33: 9791638370 | F33: {=_xlfn.XLOOKUP(I33,startify3.0!I:I,startify3.0!A:A)} -> 145 | H33: yes | I33: GP-zvvwzi | J33: SaaS, FinTech, E-Commerce | K33: https://docs.google.com/presentation/d/1RaSKcvZtyuFxCyemLEnoqYmV2Y58scdO/edit?usp=sharing&ouid=104277249549708518105&rtpof=true&sd=true | L33: India's 60M+ freelancers, 94M self-employed (NSSO), and 40M+ merchants using static QR codes lack professional no-KYC UPI tools for branded links/QR (Bharat QR 2.0), auto-receipts, tracking/analytics, relying on personal apps like GPay without formal invoicing in ₹18L Cr/month UPI ecosystem. UPI.Direct solves this via serverless (Supabase/Vercel) no-app platform with Aadhaar login, instant customizable payment links/QR/receipts (GST-ready PDFs), credit packs, white-label APIs targeting ₹500Cr TAM (₹10Cr SOM in 18 months)
A34: 33 | B34: Gokkul M | C34: COMPLETED | E34: 9043405357 | I34: cedau-05 | J34: IoT / Hardware, Robotics / Automation | K34: https://drive.google.com/file/d/1p4i1zajYvfSaNqnNbQ1cEiLOuEYvjDSJ/view?usp=sharing | L34: AeroRover-X is a hybrid morphing robot that transitions seamlessly between aerial and ground modes in one continuous operation, addressing patrol operations where every human patrol risks 6–9 lives, takes 6–8 hours, and drones alone can't investigate close-up (671 casualties in last-mile patrol operations, 2020–26). Unlike aerial drones (can't investigate close-up), ground robots (can't reach terrain), or human patrols (slow, risky), it combines a unified autonomy stack with terrain-continuous navigation — GPS-denied operation via Visual-Inertial + LiDAR-SLAM fusion, maintaining the same reference frame across air-to-ground transitions with no reinitialization. Modular swappable payloads support ISR, supply delivery, medical kits, and communication relay. Claims 40–60% lower operational cost and 6–8 hrs → 1–2 hrs mission time reduction. Applications span defense/patrol, disaster relief, medicine delivery, and emergency logistics, with a roadmap toward fleet coordination and auto-charging hubs.
A35: 34 | B35: gopikakanagaraj | C35: COMPLETED | E35: 8610004262 | F35: {=_xlfn.XLOOKUP(I35,startify3.0!I:I,startify3.0!A:A)} -> 167 | H35: yes | I35: SC-nx45i | J35: AI / ML, EdTech, Bio Tech | K35: https://docs.google.com/presentation/d/100spzmnKXgcVCDW56dtZMhsgCfTyMSe0/edit?slide=id.p8#slide=id.p8 | L35: In dental education where over 318 colleges and 27,000 students in India mostly train on phantom head models that lack real tactile feedback, leading to low confidence, higher faculty supervision needs, and potential patient discomfort during the transition to clinical practice. This problem is widespread and contributes to significant stress and difficulty for a large proportion of dental students. The solution is Haptic Verse, a 3D haptic-based dental simulator for OHI-S that combines realistic tactile feedback, AI-based scoring, dual teacher–student modes, and analytics to deliver affordable, scalable, and objective skill training aligned to Indian dental curricula.
A36: 35 | B36: Guru moothy Subburaj | C36: COMPLETED | E36: 9597312212 | H36: yes | I36: TNS-95 | J36: Automobiles , App Development / Software | K36: https://docs.google.com/presentation/d/1WQXGrjy_NqQZ3WFJry6WxrY7dAXz0xkb/edit?usp=sharing&ouid=104277249549708518105&rtpof=true&sd=true | L36: Cyclebees addresses the lack of organized, affordable doorstep bicycle and e-bike repair services, inconsistent pricing and quality, absence of on-road trials for premium cycles, and shortage of certified technicians in the local market, indicating a large, underserved and time-constrained urban customer base dependent on cycles for mobility and fitness. The solution is a standardized, engineering-driven doorstep service ecosystem using mobile service units, app-based booking, certified technicians, and associated offerings like accessories, leasing, and training, designed to scale through process standardization and technology
A37: 36 | B37: Hari Krishnan | C37: COMPLETED | E37: 8939797268 | H37: yes | I37: CEDAU-36 | J37: FinTech, E-Commerce | K37: https://drive.google.com/file/d/1Jpe5V4pSn5lJy2WIv8hH5IrXrD21Dcd2/view?usp=sharing | L37: Tynko Partner is a hyperlocal platform tackling the challenge of discovering India's 10+ crore street vendors and small roadside shops, where uncertain arrival times, unexpected closures, lack of product availability checks, and absence from apps like Zomato force time-wasting street searches and missed purchases. Its walk-and-collect model displays nearby vendors on a map with real-time open/closed status, daily stock, and live locations, letting users reserve items from home before picking up in person—no delivery needed.
A38: 38 | B38: Harini Premkumar | C38: COMPLETED | D38: 19/12/25 | E38: 6381337230 | F38: {=_xlfn.XLOOKUP(I38,startify3.0!I:I,startify3.0!A:A)} -> 146 | H38: yes | I38: SC-j51bjj | J38: Bio Tech, IoT / Hardware, Deep Tech | K38: https://docs.google.com/presentation/d/1V-32Gir5a5QIm0vNZVAbU7v4XnkamQTt/edit?usp=sharing&ouid=104277249549708518105&rtpof=true&sd=true | L38: India's overcrowded public hospitals see 15% of patients contracting hospital-acquired infections (HAIs)—with up to 10% fatal—across 860,000+ government beds serving 770M people (55% population) and 260M+ BPL citizens via Ayushman Bharat, driven by inconsistent manual cleaning/hygiene in general wards. SparShield+ solves this via a modular hybrid light barrier using safe 405nm indigo-blue LEDs (not harmful UV-C) positioned between beds for continuous chemical-free air/surface disinfection in occupied spaces, killing ESKAPE pathogens/SARS-CoV-2 via ROS production disrupting bacterial quorum sensing, featuring low-cost plug-and-play scalability, IoT-ready monitoring, eco-friendly operation, targeting tier 1-3 hospitals/government tenders in India's $1.88B infection control mark
A39: 37 | B39: Harini Kandaswamy (2021-22) | C39: completed - prev startify | E39: 7092028561 | F39: {=_xlfn.XLOOKUP(I39,startify3.0!I:I,startify3.0!A:A)} -> #N/A | I39: CEDAU1-03 | J39: 0
A40: 39 | B40: Harsh Chordia (2024-25) | C40: completed - prev startify | E40: 9841454141 | F40: {=_xlfn.XLOOKUP(I40,startify3.0!I:I,startify3.0!A:A)} -> 46 | G40: preinc | I40: PX-5lg1jf | J40: AgriTech, Enviro Tech | L40: More than 20 million tonnes of paddy stubble are burnt every year, particularly across northern Indian states after the harvest season. This widespread practice is driven by time constraints between cropping cycles and the high cost of mechanized residue management. The resulting smoke releases large amounts of particulate matter (PM2.5), carbon monoxide, and other toxic gases into the atmosphere. During peak burning months, these emissions are estimated to contribute up to 30% of Delhi’s air pollution, significantly worsening air quality. The impact is severe, leading to health emergencies, reduced visibility, flight disruptions, and long-term respiratory and cardiovascular problems for millions of residents.
A41: 40 | B41: HEMANTH.B | C41: COMPLETED | E41: 9150479903 | F41: {=_xlfn.XLOOKUP(I41,startify3.0!I:I,startify3.0!A:A)} -> 91 | H41: yes | I41: SC-e2mmc2 | J41: AI / ML, SaaS, E-Commerce | K41: https://drive.google.com/file/d/1qjD-GcXz1UuBFOMudOdluGNs9fC7t9JA/view?usp=sharing | L41: Canine Connect, India’s first verified pet matchmaking platform, addresses key gaps in the dog and pet ecosystem: no unified platform for adoption/health/lost & found services, lack of health verification enabling unethical breeding, sick puppies overwhelming shelters, inefficient fragmented lost pet recovery, and missed vaccination tracking, impacting 14-15M urban paw parents in India (35M+ pet dogs) with animal suffering, emotional distress, and safety risks. The app offers AI-driven smart matchmaking (breed/age/health/location), verified profiles/certifications, secure in-app chat/video calls, QR-based lost & found, health insights/vaccination schedules, and vet/NGO connections via freemium + subscription model targeting ₹700M SOM in Tamil Nadu.
A42: 41 | B42: Howard Nikhil | C42: COMPLETED | D42: 45968 | E42: 7094149367 | F42: {=_xlfn.XLOOKUP(I42,startify3.0!I:I,startify3.0!A:A)} -> 4 | H42: yes | I42: SC-ss0phb | J42: IoT / Hardware, App Development / Software, Deep Tech | K42: https://docs.google.com/presentation/d/1DrL3w6tkh8WgbEy3HjkfwRQ93uZiQ4Wz/edit?usp=sharing&ouid=104277249549708518105&rtpof=true&sd=true | L42: Small businesses, researchers, startups, environmental organizations, and academic institutions globally lack affordable access to satellite services due to high costs (millions) and complex infrastructure, with long lead times (1–3 years) making traditional satellite solutions inaccessible. The global satellite market is valued at ~$3 billion USD (2024), projected to grow to $9–18 billion by 2030 at 13–22% CAGR, driven by demand for earth observation, communication, IoT, and remote sensing in agriculture and research. AstroAccess offers a modular, pay-per-use CubeSat platform with customizable payloads, cloud-based data processing, and an intuitive online booking system—enabling on-demand satellite services 70% cheaper than traditional providers, rapidly deployable within 12 months, and scalable across imaging, IoT, and environmental monitoring applications, democratizing space access for underserved markets while reducing space debris through compact, eco-friendly design.
A43: 42 | B43: Jai Ganesh M | C43: COMPLETED | D43: 19/12/25 | E43: 7358299188 | F43: {=_xlfn.XLOOKUP(I43,startify3.0!I:I,startify3.0!A:A)} -> #N/A | I43: cedau-03 | J43: Bio Tech, Hardware , Deep Tech | K43: https://drive.google.com/file/d/1f0KPgYZmecnbvsrtUrlSgDz0N6apAXyJ/view?usp=drive_link | L43: The Electric Patient Bed Mover is a battery-powered device that allows a single staff member to tow hospital beds effortlessly using a unique single-wheel drive with electromagnetic clamps, reducing fatigue, delays, and safety risks from manual bed transport. Unlike existing two-wheel, highly customized and expensive systems, this BLDC-motor-based mover works across a wide variety of beds with minimal customization at roughly one‑third to one‑quarter of the cost, targeting Indian hospitals first and then scaling to other regions, with a clear ₹4 lakh prototyping and commercialization work plan over 4–6 months.​
A44: 43 | B44: Janani S | C44: COMPLETED | E44: 8870976210 | F44: {=_xlfn.XLOOKUP(I44,startify3.0!I:I,startify3.0!A:A)} -> #N/A | H44: yes | I44: sc-529ofg | J44: AgriTech, E-Commerce | K44: https://docs.google.com/presentation/d/1FXfUyGDlWBSVSWdlR8txzdfGM1uWDNfg/edit?usp=sharing&ouid=104277249549708518105&rtpof=true&sd=true | L44: Verdant Vision is a community-driven digital marketplace that connects urban home growers with nearby consumers to redistribute surplus terrace/balcony produce. It lets verified home cultivators list excess fruits and vegetables with basic pesticide-free assurance, aggregates small quantities across homes, and sells them hyperlocally, reducing the 30%+ wastage of home-grown produce while giving nearby households affordable organic options. The platform adds value through traceability, location-based matching, in-app communication, aggregation support, and awareness campaigns, delivering social impact by cutting food waste, strengthening local green economies, and encouraging chemical-free urban farming.
A45: 44 | B45: jayambu akash siva teja | C45: COMPLETED | E45: 8121564541 / 7981973211 | F45: {=_xlfn.XLOOKUP(I45,startify3.0!I:I,startify3.0!A:A)} -> 215 | I45: ipo-5av34m | J45: Bio Tech, IoT / Hardware | K45: https://docs.google.com/presentation/d/15MGrNRcJXUSMXUaCjctPr49PzbioluZx/edit?usp=sharing&ouid=104277249549708518105&rtpof=true&sd=true | L45: Smart Biometric Foot Patch & Spiritual Wristband by Vetri Enterprises addresses pilgrims' life-threatening risks during sacred journeys, including stampedes, heat exhaustion, getting lost, plus gaps like no foot-specific barefoot wearables, biometric-spiritual integration, real-time haptic alerts for fatigue/terrain/posture, hygienic UV/antibacterial layers for treks, auto-rest massage modes, NFC/BLE temple syncing, and GPS distance tracking. The dual-device system uses biometric sensors, vibration/haptic feedback, AI analytics, flexible skin-safe materials, and GPS in the foot patch for health/step monitoring, vow/prayer tracking, emergency response, location updates, voice/language assistance, ensuring safety, accountability, and enhanced spiritual focus
A46: 45 | B46: Jeremiah Japhet | C46: COMPLETED | D46: 15/10/25 | E46: 8148091100 | F46: {=_xlfn.XLOOKUP(I46,startify3.0!I:I,startify3.0!A:A)} -> #N/A | G46: preinc | I46: cedau-11 | J46: Hardware, Automobiles | K46: https://docs.google.com/presentation/d/1EV9T72VDcsImuuEu7YDiejbpGu0Mvy9q/edit?usp=drive_link&ouid=104277249549708518105&rtpof=true&sd=true | L46: CEG Motorsports develops licensable innovation modules for affordable all-terrain vehicles (ATVs) targeting rural/agricultural/defense needs in India's ₹45,380Cr ATV market (27,428Cr recreation-focused), addressing expensive, terrain-unoptimized, non-smart existing ATVs via: High Gradeability Drivetrain (torque-biased diffs/low gearing/traction control/lightweight chassis for steep climbs); Rollover Detection & Safe Shutdown (tilt/traction-loss auto-cutoff); Terrain-Based Adaptive Suspension (servo-adjusted FOX shocks via sensors); and Topology-Optimized Steering Knuckle (30% lighter AlSi10Mg 3D-printed via FEA for better handling/efficiency).
A47: 46 | B47: Jeziel Praise Son | C47: COMPLETED | D47: 46000 | E47: 9042871766 | F47: {=_xlfn.XLOOKUP(I47,startify3.0!I:I,startify3.0!A:A)} -> 44 | H47: yes | I47: SC-9a9rgd | J47: AI / ML, SaaS, App Development / Software | K47: https://docs.google.com/presentation/d/149HppxiF5fWSdC5NDButuJX_m6yEKHIP/edit?usp=sharing&ouid=104277249549708518105&rtpof=true&sd=true | L47: Device repair in India is fragmented and untrustworthy, with over 70% of users facing repair issues due to unreliable providers, inconsistent service quality, lack of standardization, and absence of transparent pricing and quality control, affecting students, professionals, and the elderly nationwide. The unorganized repair sector lacks a centralized, trustworthy solution. TrustIT's platform addresses this with AI-powered diagnostics using voice and image analysis for precise fault detection, verified and trained service centers, seamless logistics with pickup/drop and real-time tracking, transparent centralized dashboards showing pricing and repair status, and multilingual UI/UX built on TensorFlow.js, React, Node.js, and Firebase—promoting e-waste reduction and circular economy while creating local employment opportunities through standardized, accessible repair services across India.
A48: 47 | B48: kalyani patra | C48: COMPLETED | E48: 8608499779 | F48: {=_xlfn.XLOOKUP(I48,startify3.0!I:I,startify3.0!A:A)} -> 214 | I48: ipo-28zbru | J48: FinTech, Iot / Hardware , AI / ML | K48: https://docs.google.com/presentation/d/1YFjs7wBOE-FwqPCIpm92exmo75IKjAZU/edit?usp=sharing&ouid=104277249549708518105&rtpof=true&sd=true | L48: Smart Hundi addresses massive inefficiencies and vulnerabilities in the traditional manual management of temple hundi donations, where billions in annual offerings (coins, notes, jewelry) from major temples like Tirupati Balaji face rampant theft during counting, labor-intensive error-prone processing, and difficulties in jewelry valuation, causing substantial financial losses and eroding public trust in temples. Smart Hundi proposes an AI and ML-powered automated system combining real-time image capturing with hybrid multi-step classification to instantly segregate coins, notes, and jewelry using conveyor-roller mechanisms and high-end imaging, alongside encrypted centralized databases for real-time valuation, digital payment integration, secure storage, and transparent auditing to ensure integrity and accountability in managing sacred offerings
A49: 48 | B49: Kavyashri K | C49: COMPLETED | E49: 6380541322 | F49: {=_xlfn.XLOOKUP(I49,startify3.0!I:I,startify3.0!A:A)} -> 135 | H49: yes | I49: PX-jq5l4j | K49: nil
A50: 49 | B50: Keerthana | C50: COMPLETED | D50: 46000 | E50: 8122302503 | F50: {=_xlfn.XLOOKUP(I50,startify3.0!I:I,startify3.0!A:A)} -> 100 | H50: yes | I50: SC(BT)-36X8Y | J50: Bio Tech, Consumables | K50: https://docs.google.com/presentation/d/1fiE9q_IVrPmYQ3YaT2hKpCfJKvOUE2OG/edit?usp=sharing&ouid=104277249549708518105&rtpof=true&sd=true | L50: Conventional sunscreens rely on chemical filters (hormone-disrupting, marine-toxic like oxybenzone/octinoxate causing coral bleaching) or mineral nanoparticles (inhalation/environmental risks, toxic byproducts), polluting oceans with thousands of tonnes yearly while failing eco-conscious consumers. EcoShield SPF by Keerthana P et al. offers a novel mineral-free, plant-based broad-spectrum SPF 50 using Ophiorrhiza mungos herbal UV filter + lignin/chitosan biopolymers for reef-safe, biodegradable protection tailored to Indian skin, priced at ₹399/100g via D2C/e-commerce with B2B eco-tourism partnerships, projecting ₹35L revenue (9K units, 40-50% growth, break-even month 8),
A51: 50 | B51: Kochadaimuthaiya | C51: COMPLETED | D51: 13/2/2026 | E51: 7092922565 | F51: {=_xlfn.XLOOKUP(I51,startify3.0!I:I,startify3.0!A:A)} -> #N/A | H51: yes | I51: cedau-18 | J51: FinTech, E-Commerce | K51: https://docs.google.com/presentation/d/1K0_8ixw9xLF8lSGKb6GeRqHY8DvkBBNV/edit?usp=sharing&ouid=104277249549708518105&rtpof=true&sd=true | L51: GIGGERS is a B2B gig workforce platform connecting verified gig workers with verified employers across marketing, events, cine field, seasonal work, and survey categories. Addressing fragmented hiring through informal WhatsApp groups, payment delays, safety risks (especially for women), and lack of transparency, GIGGERS introduces KYC/GST-verified employers, KYC-verified workers, real-time work tracking, area-specific job allocation, SOS safety features, basic insurance, assured payments, and rating systems. With a 6–8% commission model, the platform is validated through 100-day gig economy data (₹1+ crore transactions) and LOIs from employers. GIGGERS aims to formalize gig employment, promote gender equality (SDG 5), and drive economic growth (SDG 8).
A52: 51 | B52: Kota Nageshwar | C52: COMPLETED | D52: 30/01/26 | E52: 9363300142 | F52: {=_xlfn.XLOOKUP(I52,startify3.0!I:I,startify3.0!A:A)} -> #N/A | H52: no | I52: CEDAU-07 | J52: Hardware / Consumables | K52: https://drive.google.com/file/d/1n3xy0kOxO2Yp2Z-7V4fJMq_x4C118BzN/view?usp=sharing | L52: Urban Indian households face post-treatment municipal water contamination (dust, rust, sediments, bacteria, iron/"yellow water" from pipelines/sumps/tanks) while current RO/packaged solutions waste water (>50% rejection), strip minerals, require costly AMC/recurring cartridges, and cost ₹10,950/year for 20L daily packaged water (₹54,750 over 5 years). Swatchh Water Filters by Kota Nageshwar offers smart point-of-use non-RO/RO filters (0.01-1 micron filtration retaining TDS ≤300 minerals, zero wastage, 4-5+ year life, DIY backwash every 20 days, no AMC) across drinking/kitchen/bath/shower/washing machine/descale/yellow water use cases, seeking PAN-India investors to scale affordable, sustainable home water ecosystems.
A53: 52 | B53: Kotha Vamsi | C53: COMPLETED | D53: 19/12/25 | E53: 6381784015 | F53: {=_xlfn.XLOOKUP(I53,startify3.0!I:I,startify3.0!A:A)} -> 17 | H53: no | I53: PX-cm2mr | J53: EV / Mobility, App Development / Software, Deep Tech | K53: https://drive.google.com/file/d/1_oyvkYV9seEqEx0ZpV2wRqZi6JqcpK3a/view?usp=sharing | L53: EV owners in India face fragmented EV charging experiences requiring multiple brand-specific apps (Tesla, Tata Power, Ionity, ChargePoint, BP Pulse), lack of cross-brand compatibility at stations, unreliable real-time availability/pricing/queue data, and range anxiety amid projected 50M EVs by 2030 needing 1.3M chargers. Charge One solves this via a unified React Native app aggregating all networks with a single secure wallet (UPI/cards/digital), AI-powered real-time navigation/scheduling/recommendations based on route/battery/station load, cross-brand support for AC/DC chargers, and sustainable scalability, targeting EV users/fleets/providers in a $250-300B TAM with commission/subscription/ad-based revenue—current functional prototype needs payment gateway/UI fixes within 3 months.
A54: 53 | B54: Lakshmi Priya | C54: COMPLETED | D54: 46357 | E54: 8092225251 | F54: {=_xlfn.XLOOKUP(I54,startify3.0!I:I,startify3.0!A:A)} -> #N/A | H54: yes | I54: IPO-ozm1k | J54: AI / ML, SaaS, App Development / Software, Sports Tech | K54: https://drive.google.com/file/d/18TKSjzu0XBMIfcvR-TzwQO4eOlv5TP4I/view?usp=sharing | L54: ScoutEdge is an AI-powered cricket talent scouting and performance analytics platform focused on uncovering hidden players from Tier 2, Tier 3, and rural India who currently lack access and verified performance data. It tackles subjective, slow, and biased traditional scouting by providing an AI rating system that combines match performance, video analytics, fitness and challenge metrics, along with player dashboards, scout dashboards, and academy/tournament integration, already tested with 500+ players, multiple scouts and academies, and supported by state associations like Bihar and Bengal. The platform uses an AI/ML, cloud-based, mobile-first SaaS stack with subscription and data-insights revenue, and seeks IVP funding of about ₹8.06 lakh (total project cost ~₹9.10 lakh) to scale design, fabrication, validation, and commercialization of this end-to-end ecosystem from player to franchise.
A55: 54 | B55: Liya Therese A J | C55: COMPLETED | E55: 9626316318 | F55: {=_xlfn.XLOOKUP(I55,startify3.0!I:I,startify3.0!A:A)} -> 207 | H55: yes | I55: SS-6h7rb | J55: AgriTech, Enviro Tech | K55: https://docs.google.com/presentation/d/1g4-TPeuc1Ma7P0pBfXTI7XqP7vHwDnP6/edit?usp=sharing&ouid=104277249549708518105&rtpof=true&sd=true | L55: Conventional phenol‑formaldehyde floral foam, used by about two‑thirds of florists, is a single‑use plastic that does not biodegrade, breaks into microplastics, leaches toxic chemicals, and poses carcinogenic and respiratory risks to users while polluting landfills and waterways. The problem is large within the fast‑growing floriculture and décor market, where floral foam is widely used. The solution, Green Blooms, develops eco‑friendly, biodegradable, water‑retaining, lightweight floral blocks made from agro and floral waste as sustainable, compostable, reusable alternatives to conventional chemical floral foams.​
A56: 55 | B56: Madhu Pragadeshwaran / Bharat MS | C56: COMPLETED | E56: 9080265174 | F56: {=_xlfn.XLOOKUP(I56,startify3.0!I:I,startify3.0!A:A)} -> 133 | I56: SC-nryy8h | J56: Deep Tech , Drones | K56: https://drive.google.com/file/d/1zvoBHLHzNkEc_Tko9TpmvngKFuliUMRn/view?usp=sharing | L56: The Aerial LED-Drone Advertising project offers short-duration octocopter flights carrying transparent, thin LED mesh displays that show scrolling promotional messages over crowded local areas like markets and events. It addresses the high cost, poor targeting, and audience fatigue of traditional advertising (billboards, TV ads), which typically show low ROI and are often ignored. The system uses Pixhawk/QGC-controlled drones with customizable mesh sizes for daylight-visible, flexible, DGCA-compliant campaigns, priced affordably to serve small and medium businesses rather than only large brands. It also positions the drone platform for logistics and aerial survey use cases beyond advertising. Grant funds will support prototype fabrication, DGCA certification, and pilot campaigns; a business survey confirmed strong demand across retail, fitness, and event sectors.
A57: 56 | B57: maharaja pandian G | C57: COMPLETED | E57: 8270345463 | F57: {=_xlfn.XLOOKUP(I57,startify3.0!I:I,startify3.0!A:A)} -> 111 | H57: yes | I57: sc-towsh | J57: AI / ML, Bio Tech, IoT / Hardware | K57: https://docs.google.com/presentation/d/1qNVBk6gBUF6C_R1PZ17tOFm6axKc1L5C/edit?usp=sharing&ouid=104277249549708518105&rtpof=true&sd=true | L57: This is a global biomedical security gap highlighted during the coronavirus pandemic, where ordinary people using public transport are highly exposed and early cardiac risks often go undetected. The problem is widespread and affects general populations with limited bioscience awareness and access to timely primary diagnostics. The solution is Cardiosense, an AI-powered digital stethoscope that uses biosensors, piezoelectric sensing, and machine learning frameworks like TensorFlow and PyTorch to analyze cardiac data across age groups and enable early detection of cardiac-related diseases, supported by grant-funded R&D, prototyping, and IP protection.
A58: 57 | B58: MANI MOZHI VARMAN K | C58: COMPLETED | E58: 9361455523 | F58: {=_xlfn.XLOOKUP(I58,startify3.0!I:I,startify3.0!A:A)} -> 228 | H58: yes | I58: Sc-3343hr | J58: E-Commerce, Fashion / Lifestyle, App Development / Software | K58: https://drive.google.com/file/d/1JpesebGrTQRjlE59-oIm47tqykoWEbXQ/view?usp=sharing | L58: This fashion-tech marketplace targets Chennai’s Pondy Bazaar shoppers and local boutiques by building a mobile-first platform that curates inventory and partners with neighborhood vendors to bring their catalog online. The venture plans an MVP launch with a lean but structured 6‑month financial roadmap covering app store setup, cloud infrastructure, initial inventory, local delivery, and performance marketing, using a hybrid inventory-plus-commission model and phased logistics to reach profitability within an 8.5 lakh runway while scaling vendor participation
A59: 58 | B59: Mohamed Shameer M | C59: COMPLETED | E59: 6380652935 | F59: {=_xlfn.XLOOKUP(I59,startify3.0!I:I,startify3.0!A:A)} -> 162 | H59: yes | I59: SC-qaqe0p | J59: App Development / Software, | K59: https://docs.google.com/presentation/d/1LMmAzIeobpm2hgAhDJPW5aVOUNjQZPdS/edit?usp=sharing&ouid=104277249549708518105&rtpof=true&sd=true | L59: Tool use disabled per user request. Restaurant POS systems are rigid, lack workflow flexibility, and feature cluttered UIs that hinder staff efficiency as businesses scale, while neglecting customer retention through personalization like dietary preferences. This impacts mid-to-high-level restaurants, cafes, cloud kitchens, and chains needing scalable operations. SmartMenu offers a flexible Restaurant Operating System with customizable workflows, integrated ordering/staff/inventory/accounts/analytics, AI insights, and a customer app for preference storage, personalized recommendations, and multi-mode booking to enhance vendor operations and loyalty.
A60: 59 | B60: Mohammed Azgar | C60: COMPLETED | D60: 46000 | E60: 8148522265 | F60: {=_xlfn.XLOOKUP(I60,startify3.0!I:I,startify3.0!A:A)} -> 14 | H60: yes | I60: SC-oajf6r | J60: SaaS, EdTech, FinTech | K60: https://docs.google.com/presentation/d/1VWhrxq4im2ROTVEhW3mI93TDMyUbpKfn/edit?usp=sharing&ouid=104277249549708518105&rtpof=true&sd=true | L60: Early-stage entrepreneurs and students face three critical barriers: lack of focused business & finance education, limited access to startup-specific networks, and difficulty raising early-stage capital—causing 90% of startups to fail early, despite India having 159K+ startups and 43M+ students, with millions of aspiring founders from Tier 2 & 3 cities remaining underserved by fragmented, generic, job-focused platforms not built for startup founders. Sprezox is an all-in-one social media-based entrepreneurial platform addressing this gap by bringing together business creators, influencers, startups, and investors to Learn (reels and podcasts by niche experts), Network (connect with startups, incubators, accelerators, angel investors, VCs), Showcase & Fundraise (direct investor visibility), and Enable Equity Crowdfunding (micro/retail investors with micro-ticket sizes)—offering capital efficiency (single platform vs. fragmented services), lower barriers through inclusive crowdfunding, high revenue scalability via minimal-cost social content, reduced investor due diligence, and social impact through entrepreneurship access, job creation, financial inclusion, knowledge democratization, and reduced carbon footprint compared to physical events.​
A61: 60 | B61: Mohammed Hussain Basith | C61: COMPLETED | D61: 46357 | E61: 7200326094 | F61: {=_xlfn.XLOOKUP(I61,startify3.0!I:I,startify3.0!A:A)} -> 42 | H61: yes | I61: SC-83s9eo | J61: Enviro Tech | K61: https://docs.google.com/presentation/d/1XXOdoM72D_hhdWkD5i29TjW9-amrFpOE/edit?usp=sharing&ouid=104277249549708518105&rtpof=true&sd=true | L61: Over 600 million people globally rely on diesel for electricity, while solar and wind struggle to deliver consistent power in coastal communities. The Ocean Wave Energy Converter (OWEC) solves this through a buoyant HDPE drum with a direct mechanical power take-off system (gears, pulleys, shafts) converting wave motion directly into electricity via a DC generator, eliminating complex hydraulics, offering low-cost corrosion-resistant design, modular scalability from 1kW to 100kW+, high reliability in saltwater environments, silent eco-friendly operation with zero emissions, and 90% wave availability delivering predictable baseload power for off-grid coastal communities and islands.​
A62: 61 | B62: Ms. M.Nirmaladevi Senthilkumar | C62: COMPLETED | E62: 9688299333 | F62: {=_xlfn.XLOOKUP(I62,startify3.0!I:I,startify3.0!A:A)} -> #N/A | H62: yes | I62: CEDAU-29 | J62: Food Tech | K62: https://drive.google.com/file/d/1sFC4pPdrt2TlqHFgBbsQ0UUPSKQ--6He/view?usp=sharing | L62: Small Millet Chikki replaces refined-ingredient traditional snacks with a health-focused millet-based chikki that revives forgotten grains, offers naturally functional nutrition, and improves standardization, shelf life, and packaging for better consumer acceptance. It targets problems like low nutritional value, lack of protein–fiber balanced options, poor quality and shelf life in millet products, low awareness due to inconsistent packaging, and difficulty for micro-enterprises to turn healthy ideas into market-ready snacks, by developing a standardized, safe, scalable, millet chikki that boosts nutrition, supports rural entrepreneurs, and promotes sustainable millet consumption.
A63: 62 | B63: Mukesh Kumar | C63: COMPLETED | D63: 45969 | E63: 8122687750 | F63: {=_xlfn.XLOOKUP(I63,startify3.0!I:I,startify3.0!A:A)} -> 205 | H63: yes | I63: SC-fmdki | J63: Enviro Tech, , Deep Tech | K63: https://docs.google.com/presentation/d/10FTUyZ_zpXB2nndcBXQlWcBMXfMK0yVj/edit?usp=sharing&ouid=104277249549708518105&rtpof=true&sd=true | L63: India generates over 3 million tons of e-waste annually, with only 20% formally recycled while non-recyclable components like plastic casings, wire coatings, and PCB shells pollute landfills, contaminate land/water, and expose waste workers/communities to toxic materials especially in urban/semi-urban areas like Chennai, Delhi NCR, and Mumbai. RMK Aerospace's sustainable e-waste bricks solve this through a low-energy process shredding/mixing/pressing/curing non-recyclable e-waste with eco-binders into durable, thermally insulating, soundproof construction bricks/tiles featuring ≤90% less water consumption, no kiln firing/zero emissions, 30–50% cheaper cost, compressive strength up to 8–10 MPa, faster curing (3–7 days), modular decentralized manufacturing, and circular economy impact within India's ₹6.5 lakh crore brick market.​
A64: 63 | B64: Muni Chandrasekar Reddy K | C64: COMPLETED | E64: 9962764646 | F64: {=_xlfn.XLOOKUP(I64,startify3.0!I:I,startify3.0!A:A)} -> 200 | I64: SC-3gcyak | J64: EdTech, App Development / Software, Sports Tech | K64: https://docs.google.com/presentation/d/1uK1jvNK5uZzUPeWETKPYgSroJ5mXheZM/edit?usp=sharing&ouid=104277249549708518105&rtpof=true&sd=true | L64: APEX is a first-of-its-kind offline sports pairing mobile app using skill-based ratings (like Chess.com) for real-time proximity matching across badminton, football, table tennis, tennis, pickleball, and shuttle—solving solo players' struggles finding compatible partners when friends are busy, newcomers seek buddies, or introverts hesitate to socialize. It promotes daily sports for irregular players to improve skills/fitness while fostering social connections for students/professionals; Competitive edges include rating-driven fairness, geolocation speed, and multi-sport support vs generic find-a-friend apps.
A65: 64 | B65: MURUGANANTHAM | C65: COMPLETED | E65: 8973223615 | F65: {=_xlfn.XLOOKUP(I65,startify3.0!I:I,startify3.0!A:A)} -> #N/A | I65: CEDAU-30 | J65: Deep Tech | K65: https://drive.google.com/file/d/1X28ckk2B2gna7Ohu1co1xCtOLuMRGGAP/view?usp=sharing | L65: The document addresses the limitations of current lithium‑ion battery energy storage, including high cost, safety risks, performance degradation, limited energy density, slow charging, and poor performance in extreme climates. It frames this as a broad challenge for reliable, affordable, climate‑resilient energy storage. As a solution, it develops an eco‑friendly process to convert eucalyptus bark waste into nitrogen‑, sulfur‑, and phosphorus‑doped porous activated carbon, optimized for use as high‑performance supercapacitor electrode material that offers fast charging, long cycle life, and cost‑effective energy storage.
A66: 65 | B66: Nagendra Dasari | C66: COMPLETED | E66: 8555874504 | F66: {=_xlfn.XLOOKUP(I66,startify3.0!I:I,startify3.0!A:A)} -> #N/A | H66: yes | I66: CEDAU-32 | J66: AI / ML, FinTech, IoT / Hardware | K66: https://docs.google.com/presentation/d/1gXlydx6GGyjViK9BH2DExwsitvhYxcTC/edit?usp=sharing&ouid=104277249549708518105&rtpof=true&sd=true | L66: Modern shopping malls and supermarkets suffer from long checkout queues, customer frustration with heavy carts and expense tracking, plus retailer challenges like manpower shortages, inefficiencies, and missing real-time insights, creating widespread operational bottlenecks despite digital payment advances. No-Q solves this with an AI-powered autonomous smart shopping cart that uses computer vision for hands-free following, instantly detects and bills added products for queue-less checkout, tracks expenses live, and delivers retailer analytics, deployable as affordable retro-fits or custom units.
A67: 66 | B67: Naveen Kanna | C67: COMPLETED | E67: 6374990762 | F67: {=_xlfn.XLOOKUP(I67,startify3.0!I:I,startify3.0!A:A)} -> 34 | H67: yes | I67: SC-pcw53a | J67: AI / ML, Bio Tech , Deep Tech , Robotics / Automation | K67: https://docs.google.com/presentation/d/1j0u6rTzUBFBf7-jCFUsqyiQ-ftfNRYpJ/edit?usp=sharing&ouid=104277249549708518105&rtpof=true&sd=true | L67: Around 1.3 billion people (16% of the world) live with significant disabilities, many with severe mobility impairments for whom existing wheelchairs and assistive devices remain non-lifting, inefficient, and unable to provide versatile, high-performance, independence‑enhancing movement or performance augmentation. This technology gap leaves disabled users dependent on others and offers no unified solution that combines rehabilitation, mobility, and human performance enhancement. The proposed solution is an AI-powered exoskeleton that is 20–30% lighter, up to 40% cheaper via AI design and string‑tension actuation, adaptable, comfortable, irritation‑free, and temperature‑regulated for intuitive everyday use.
A68: 67 | B68: naveen kumar | C68: COMPLETED | E68: 8939724423 | F68: {=_xlfn.XLOOKUP(I68,startify3.0!I:I,startify3.0!A:A)} -> 112 | H68: yes | I68: sc-3yn3y | J68: AgriTech, Enviro Tech, IoT / Hardware, App Development / Software, Robotics / Automation | K68: https://drive.google.com/file/d/1TD6Zr_t4dP2amdmHB97iyp7MVXGAWrPM/view?usp=sharing | L68: AgriAi by Pentastech solves Indian farmers' crop losses from poor soil management and fertilizer overuse—India applies 166.9 kg/ha (4x global average) yet sees suboptimal yields due to nutrient imbalances, manual testing delays, and lack of actionable insights. Small farmers, advisors, and the environment suffer from imprecise applications causing soil degradation and runoff. The autonomous rover with smart probe uses IoT sensors (NPK, pH, moisture), Raspberry Pi, GPS/GIS for real-time nutrient mapping, and AI via React Native app for crop/fertilizer recommendations, outperforming costly static probes like Teralytic with full mobility, affordability, and B2B/B2C scalability
A69: 68 | B69: Naveen P | C69: COMPLETED | E69: 9566834018 | F69: {=_xlfn.XLOOKUP(I69,startify3.0!I:I,startify3.0!A:A)} -> 150 | H69: yes | I69: sc-zvs89 | J69: Bio Tech, Food Tech, Consumables | K69: https://drive.google.com/file/d/12jx3TEGH4NE1c_zk_vY7Hlkp-BXrhUBu/view?usp=sharing | L69: Sugarless Wonders is a line of truly sugar‑free, diabetic‑safe traditional sweets that use natural low‑GI sweeteners and innovative natural binders to preserve authentic mithai taste and texture while avoiding sugar spikes and artificial chemicals. It targets overconsumption of refined sugar and the resulting rise in diabetes, obesity, and heart disease by offering functional, protein- and gut‑friendly desserts that are safe for daily use and celebrations. The IVP grant is planned for R&D, formulation optimisation, pilot production, nutritional validation, certifications, and market entry with commercially ready products.
A70: 69 | B70: Navinkrishna K | C70: COMPLETED | E70: 8122980305 | F70: {=_xlfn.XLOOKUP(I70,startify3.0!I:I,startify3.0!A:A)} -> #N/A | H70: yes | I70: cedau-27 | J70: IoT / Hardware | K70: https://docs.google.com/presentation/d/1d8-jiX9yr-sMsCczAoqAxNddaCFgD9Lb/edit?usp=sharing&ouid=104277249549708518105&rtpof=true&sd=true | L70: GasGuardian by Gas Tech is a smart device solving the lack of real-time LPG monitoring in Indian homes and commercial kitchens, where manual checks fail to prevent undetected leaks causing fires, explosions, and major losses. It uses a load cell with HX711 ADC for precise cylinder weight tracking, MQ-2 sensor for leak detection, LCD display for status, buzzer for instant alarms, and optional GSM/Wi-Fi IoT for mobile alerts. Advantages include dual level-leak safety, high accuracy, affordability over imports, modular IoT scalability, and impacts like saving lives, cutting fire damage, reducing gas waste, and promoting safety awareness
A71: 70 | B71: Nelson | C71: COMPLETED | E71: 7358734289 | F71: {=_xlfn.XLOOKUP(I71,startify3.0!I:I,startify3.0!A:A)} -> #N/A | H71: yes | I71: cedau-25 | J71: AI / ML, EdTech, App development / Software | K71: https://docs.google.com/presentation/d/1svlsWidPE9Mo4IunAUtMRWoX6-3FELRG/edit?usp=sharing&ouid=104277249549708518105&rtpof=true&sd=true | L71: ResourceIndia.co addresses the costly and inefficient hiring of junior engineers in India, where companies spend heavily on recruitment and training, face high first-year attrition, and still lack verified performance data before hiring, leaving a large employability and trust gap between graduates and employers. ResourceIndia.co proposes an AI-powered, assessment-gated internship marketplace where startups and MSMEs post live projects, students complete supervised, real-world work, and performance is verified using AI and blockchain-based mechanisms, creating a scalable, ready-to-hire talent pool that reduces bad hires and onboarding time
A72: 71 | B72: Nikarika Ramesh | C72: COMPLETED | D72: 45968 | E72: 9790004554 | F72: {=_xlfn.XLOOKUP(I72,startify3.0!I:I,startify3.0!A:A)} -> 138 | G72: preinc | I72: SS-xiv9fo | J72: AI / ML, Food Tech, IoT / Hardware, Consumables | K72: https://docs.google.com/presentation/d/1UuvB8CG5hK21LYH5-VK1-ElnDGm_z_ck/edit?usp=drive_link&ouid=104277249549708518105&rtpof=true&sd=true | L72: VITASAFE MethScreen-Q is a portable, user-friendly device using dual spectral/RGB sensors + ML algorithms for real-time (15-min) on-site detection of residual methanol/ethanol (0.01-60% range) in alcohol, herbal beverages/cosmetics/sanitizers, far outperforming costly/non-portable GC-MS (₹3-5K/sample, lab-only) or inaccurate chemical kits. It targets FSSAI/CDSCO limits (e.g., 0.08% alcohol), slashing testing costs 50-95% for small producers/regulators while preventing poisoning risks (blindness/death), with PoC validated, published patent
B73: Parthsarathi | C73: COMPLETED | D73: 29/07/25 | E73: 8610254655 | F73: {=_xlfn.XLOOKUP(I73,startify3.0!I:I,startify3.0!A:A)} -> 28 | H73: yes | I73: SC-yd0hxd
A74: 72 | B74: P. Paneer Selvam | C74: COMPLETED | E74: 8675058253 | F74: {=_xlfn.XLOOKUP(I74,startify3.0!I:I,startify3.0!A:A)} -> 194 | H74: yes | I74: sc-s98rzx | J74: Enviro Tech, Renewable Energy | K74: https://docs.google.com/presentation/d/1R62ldDA80PBjNGZCWUlo8ednBrIS-Aq_/edit?usp=sharing&ouid=104277249549708518105&rtpof=true&sd=true | L74: This startup addresses India’s energy crisis, frequent summer power cuts, pollution, low renewable energy utilization, and reliability issues in the renewable sector. These challenges affect large segments of the population and demand more dependable, clean, and distributed power solutions. The proposed solution is a low‑wind-speed optimized vertical axis wind turbine using aluminum alloy sheets, drag-based aerodynamic blades, lightweight metallic I‑beams, and a PMSM generator to deliver cost‑effective, easy-to-transport, recyclable, and reliable renewable power
A75: 73 | B75: Prathib Vamsi P | C75: COMPLETED | D75: 28/11/25 | E75: 9003815145 | F75: #N/A | G75: preinc | I75: cedau-06 | J75: Enviro Tech, Automobiles , Consumables | K75: https://docs.google.com/presentation/d/1R3kivspd_3Lf6F3BjWMmF6CfZnH8UGnm/edit?usp=drive_link&ouid=104277249549708518105&rtpof=true&sd=true | L75: MotorX addresses the environmental and operational challenges of liquid radiator coolants. The problem: liquid coolants generate ~65,000 tons CO₂ annually due to shipping weight (~1.1 kg/L), produce ~12,000 tons plastic waste from PET bottles yearly, and create spill management issues for service centers. The market size is ₹2,350 crores across multiple segments (liquid coolant: ₹950 Cr, powdered: ₹285 Cr, exports: ₹300 Cr+). MotorX's solution: dry powder radiator coolant in compostable sachets offering 90% transport weight reduction, eliminates plastic, provides 2+ year shelf stability, and enables ₹230 crores revenue potential targeting 11% market share within 3 years.
A76: 74 | B76: Praveen B B | C76: COMPLETED | E76: 9600447671 | F76: {=_xlfn.XLOOKUP(I76,startify3.0!I:I,startify3.0!A:A)} -> 186 | H76: yes | I76: SC-8bhnkk | J76: Iot / Hardware , Consumables | K76: https://drive.google.com/file/d/1ZTekSFYEKDNZI7T30N0Kmx-9Wxd1xtYC/view?usp=sharing | L76: Senticlip addresses the widespread safety gap women face, where existing devices are often bulky, rely on phones, or only trigger loud alarms, leaving many without discreet, always-on protection in real-world situations like harassment after dark or emergencies needing immediate help. Senticlip proposes a stylish hair accessory with one-touch and voice-activated SOS, precise GPS tracking, automatic calls to guardians, and an encrypted 1080p camera for evidence recording, sold via customizable B2C on-demand manufacturing and B2B safety programs, to provide subtle, tech-enabled personal security at scale.
A77: 75 | B77: Praveen Kumar R | C77: COMPLETED | D77: 30/01/26 | E77: 8148402208 | F77: {=_xlfn.XLOOKUP(I77,startify3.0!I:I,startify3.0!A:A)} -> #N/A | I77: cedau-19 | J77: AI / ML, AgriTech, E-Commerce, IoT / Hardware | K77: https://docs.google.com/presentation/d/14q8HVWXmbsPywVvXUfo8vnvagpaozDFv/edit?usp=sharing&ouid=104277249549708518105&rtpof=true&sd=true | L77: Namma Vivasayi addresses widespread agricultural challenges such as labour shortages, limited access to machinery, water mismanagement, market price instability, climate impacts, financial stress, soil mismanagement, and lack of farmer training. The problem spans over 120 million farmers nationally and about 40 million in South India, with an initial focus on 5 lakh farmers in Tamil Nadu. The solution is an end-to-end farming platform that combines labour and machinery booking, an AI-powered AgriBot, IoT-based smart irrigation, a direct farmer marketplace, and smart canteen services, delivered through a phased roadmap from prototype to large-scale rollout.
A78: 76 | B78: Prempradeep S | C78: COMPLETED | D78: 14/11/25 | E78: 7708365986 | F78: {=_xlfn.XLOOKUP(I78,startify3.0!I:I,startify3.0!A:A)} -> 39 | G78: preinc | H78: yes | I78: SC-b4jkfxa | J78: AI / ML , IoT / Hardware, Deep Tech, Robotics / Automation | K78: https://drive.google.com/file/d/1VorSWnUlyM-hZbEwKD3-ydU3amct_rNZ/view?usp=sharing | L78: Aquaholics Autonomous Water Surface Cleaning Robot addresses plastic pollution crisis in water ecosystems threatening marine life and water quality, where India relies primarily on slow, expensive, risky manual labor that misses debris in hard-to-reach areas, while semi-automated/robotic systems fail at waste handling, obstacle navigation, and bad weather performance—making consistent cleaning difficult for municipalities/NGOs. The 25kg-capacity robot features autonomous navigation via LiDAR/GPS/IMU+SLAM+ROS for real-time mapping, computer vision/polarized cameras for waste detection (plastics/debris/oil spills), screw conveyor+robotic arm for collection, 360° ballast tanks for stability, hybrid solar/battery power, pH/DO/water level sensors, acoustic deterrence for aquatic safety, UV disinfection, and LoRa communication—reducing manual labor costs while preserving biodiversity.​
A79: 77 | B79: Priya Roshni A | C79: COMPLETED | E79: 9363197584 | F79: {=_xlfn.XLOOKUP(I79,startify3.0!I:I,startify3.0!A:A)} -> 147 | I79: SC-vnqnnm | J79: AI / ML, EdTech | K79: priya_ORIONix.pptx | L79: The problem is the lack of a safe, direct way for students to talk to professionals they aspire to become, as existing platforms limit messaging without premium access, have low response rates, and expose students to scams, fake mentors, and shallow web-only knowledge. With over 25 million college students in India and rising demand for localized, personalized mentorship, this gap is large. The solution is ORIONIX, an AI-powered mentorship social network where verified students connect with verified mentors through secure calls/chats and 3D AI-driven VR/AR avatars, offering multilingual, experience-based guidance.
A80: 78 | B80: Purushothaman J | C80: COMPLETED | D80: 19/12/25 | E80: 9176435615 | F80: {=_xlfn.XLOOKUP(I80,startify3.0!I:I,startify3.0!A:A)} -> 119 | H80: yes | I80: SC-aodnso | J80: EdTech, IoT / Hardware, App Development / Software | K80: https://docs.google.com/presentation/d/1Jqm6_fP9FgL0YIqrGdUb-tYgGnQ5StAv/edit?usp=sharing&ouid=104277249549708518105&rtpof=true&sd=true | L80: Traditional FDM 3D printers suffer from inefficiency and limited industrial applicability due to complex support structure requirements increasing material waste, long curing times slowing production, time-consuming post-processing, and limited scalability where existing affordable machines are polymer-only lacking strength for heavy-duty applications. GrainForge solves this with a resin + ceramic/metal powder composite printing system featuring instant UV curing at the nozzle tip for support-free printing, eliminating waste and accelerating production, faster curing enabling quicker print times, enhanced material strength and durability for industrial applications, cost-effective scalability for SMEs/R&D labs/educational use, and customizable 3–6 DOF modular design adaptable to multiple materials including recycled glass fiber from wind turbine blades.​
A81: 79 | B81: R V Aswiga | C81: COMPLETED | E81: 9790341644 | F81: {=_xlfn.XLOOKUP(I81,startify3.0!I:I,startify3.0!A:A)} -> 219 | H81: yes | I81: IPO-mf6d59 | J81: EdTech, Bio Tech, Enviro Tech | K81: https://docs.google.com/presentation/d/1d_QPiSCNKK8qPBBvYe2cLPeJl46ZqELP/edit?usp=sharing&ouid=104277249549708518105&rtpof=true&sd=true | L81: A shift from 18th-century cotton- and gauze-based sanitary napkins to plastic-dominated manufacturing, creating health hazards, environmental damage, and no hygienic on-demand pad production options. This widespread issue impacts menstruating women globally, particularly students facing absenteeism from irregular periods and lack of access. The solution is a GUI-based smart machine using biodegradable materials like bamboo cotton and aloe vera to instantly produce customizable, three-layered organic napkins via touchscreen input, with auto-material loading and an integrated incinerator for stigma-free disposal.​
A82: 80 | B82: rahul g | C82: COMPLETED | E82: 7305714848 | I82: SC-6y3eg | J82: SaaS, Bio Tech, Robotics / Automation | K82: https://drive.google.com/file/d/18ecch_ekv7-0S81KDJHkIjivGZFfbeRh/view?usp=sharing | L82: SterilySense is a dual-mode robot combining vacuum cleaning with UV-C disinfection and TiO₂ photocatalysis, tackling healthcare-associated infections that affect 1 in 25 patients daily and cause ~90,000 preventable U.S. deaths yearly, especially in low-resource clinics reliant on manual cleaning. It disinfects both horizontal and vertical surfaces via a 360° rotating arm, using AI anomaly detection (UV-A scan, microscopic confirmation, UV-C kill) instead of timer-based cleaning, with a live dashboard tracking hotspots and bacteria levels. Lab tests showed bacterial colonies dropping to zero post-treatment. Claims up to 70–90% HAI reduction and ~40% lower cleaning costs versus chemical methods.
A83: 82 | B83: Renjith Kumar R (2023-24) | C83: completed - prev startify | E83: 6398101110 | F83: {=_xlfn.XLOOKUP(I83,startify3.0!I:I,startify3.0!A:A)} -> #N/A | G83: preinc | I83: CEDAU1-04
A84: 81 | B84: Ranjith. K | C84: COMPLETED | D84: 17/04/25 | E84: 8883035691 | F84: {=_xlfn.XLOOKUP(I84,startify3.0!I:I,startify3.0!A:A)} -> 1 | G84: preinc | I84: SC-591xv | J84: SaaS, Consumables, Enviro Tech | K84: https://docs.google.com/presentation/d/1if-EUnplBW5VbKgR7L12TzrIzz_2XseW/edit?usp=sharing&ouid=104277249549708518105&rtpof=true&sd=true | L84: Rats damage car engine wiring, causing breakdowns, safety hazards, and costly repairs, affecting millions of vehicles worldwide in high-infestation areas like India. The car cover market, valued at ₹7,565 crores in 2024, is projected to reach ₹9,761 crores by 2032, highlighting the problem's scale for car owners, showrooms, service centers, and fleet operators. The RATFREE solution is a non-toxic, biodegradable protective coating applied to car covers made from polypropylene and nylon fabric, offering 100% rat-proofing, long-lasting reusability (up to 3 years), waterproofing, and airflow preservation without chemicals or toxins, outperforming sprays, meshes, and ultrasonic devices.
A85: 83 | B85: Reshma Ch | C85: COMPLETED | D85: 46357 | E85: 9940432697 | F85: {=_xlfn.XLOOKUP(I85,startify3.0!I:I,startify3.0!A:A)} -> #N/A | H85: yes | I85: CEDAU-04 | J85: Bio Tech, Enviro Tech | K85: https://docs.google.com/presentation/d/1Ntxw63M7DcsoxOIi704XmNM8A5r7ezz0/edit?usp=sharing&ouid=104277249549708518105&rtpof=true&sd=true | L85: SanBio360 tackles the massive problem of sanitary pad waste in India, where about 12.3 billion pads (~113,000 tonnes) are dumped yearly, taking 300–500 years to degrade and currently managed mainly by polluting incineration or landfilling. It proposes a decentralized hybrid system that biologically treats biodegradable components via anaerobic digestion and fermentation to produce biogas, bioethanol, and compost, while non-biodegradable fractions undergo pyrolysis to yield fuel oil and biochar, creating a zero-waste, circular, revenue-generating sanitary waste solution
A86: 84 | B86: rithuparan p s | C86: COMPLETED | E86: 9150624440 | F86: {=_xlfn.XLOOKUP(I86,startify3.0!I:I,startify3.0!A:A)} -> 62 | H86: yes | I86: SC-slpbfe | J86: Bio Tech, App Development / Software | K86: https://docs.google.com/presentation/d/1k_R53bveQiXpAf_kiNbuGUvDcY5O-ZEo/edit?usp=sharing&ouid=104277249549708518105&rtpof=true&sd=true | L86: AlertCare addresses a large and growing crisis in geriatric care in India, where over 150 million elderly people, many living alone or far from their children, face undetected health emergencies and families suffer continuous caregiver anxiety due to poor fit of current smartwatches and reactive panic buttons. The solution is AlertCare, a low-cost, proactive care ecosystem built around a simple wrist wearable that continuously tracks key vitals and uses an offline, regional-language intelligent voice engine to give real-time spoken guidance to elders without needing smartphones or internet, supported by an AI caregiver app and a grant-backed plan to build and test pilot units for commercialization.
A87: 85 | B87: Roshan | C87: COMPLETED | E87: 8754864334 | F87: {=_xlfn.XLOOKUP(I87,startify3.0!I:I,startify3.0!A:A)} -> 41 | H87: yes | I87: SC-y4ea0v | J87: Enviro Tech, IoT / Hardware, Robotics / Automation | K87: https://drive.google.com/file/d/14vFE5wfabqJc8fVR0TmOnN5rBoOLq0F9/view?usp=sharing | L87: WaterWise by hyrowah Technologies tackles severe inland water pollution in India, where contaminated surface waters seep into groundwater causing health crises like cancer, compounded by inefficient manual cleaning and delayed traditional monitoring that fails to catch anomalies in real-time. Local lakes accumulate plastics, debris, oil, and sewage, with municipal responses too slow and reports arriving too late to prevent spread. The solution deploys autonomous surface bots for multi-point real-time monitoring (24+ parameters from 6 inputs via DNN), debris/oil collection, 3D lakebed modeling, and adaptive treatments using nanobubble tech plus eco-friendly biotech like Moringa and Guar Gum.
A88: 86 | B88: S Jeevesh | C88: COMPLETED | D88: 45968 | E88: 9025314278 | F88: {=_xlfn.XLOOKUP(I88,startify3.0!I:I,startify3.0!A:A)} -> 50 | H88: yes | I88: SC-dyjltj | J88: AI / ML, SaaS, FinTech, E-Commerce, IoT / Hardware , Robotics / Automation | K88: https://docs.google.com/presentation/d/1xilADa_we21eyupqg43BdOhiGZY8F1wV/edit?usp=sharing&ouid=104277249549708518105&rtpof=true&sd=true | L88: Manual labor dominates over 75% of Indian warehouses, slowing fulfillment, increasing safety risks, and elevating costs, while grid-based automation requires fixed layouts, high upfront investment (₹60–90L/zone), and complex infrastructure changes, making it inaccessible for small and mid-sized warehouses. The Indian warehouse automation market addresses 3PL, cold storage, FMCG, and e-commerce sectors with diverse, dynamic layouts. Navogenix Porter is an AI-powered, non-grid autonomous robot using sensor fusion (LiDAR, stereo vision, UWB, IMU) that carries payloads (50–200kg) across any warehouse floor without infrastructure changes, deployable in 1–2 days at ₹3.5–5L/unit—60–70% lower cost than traditional grid systems—with real-time obstacle avoidance, cloud-based monitoring, and modular scalability designed specifically for Indian warehousing realities.
A89: 87 | B89: S PRITHIV RAJ | C89: COMPLETED | E89: 8220316694 | F89: {=_xlfn.XLOOKUP(I89,startify3.0!I:I,startify3.0!A:A)} -> #N/A | H89: yes | I89: PX-iryrmq | J89: Bio Tech, IoT / Hardware | K89: https://docs.google.com/presentation/d/16iZHJVd8g9Vuf773Dx3vQinjIncBZeZc/edit?usp=sharing&ouid=104277249549708518105&rtpof=true&sd=true | L89: Deaf and hard-of-hearing individuals face critical risks from sound-based alerts like doorbells, fire alarms, gas leaks, and emergency warnings, which they cannot hear, leading to missed notifications, delayed responses, dependency on others, and potential danger in daily life and crises. The Calling Bell and Emergency Alert System Band solves this widespread accessibility gap with a wearable wristband receiver paired to a wireless transmitter that converts doorbell presses and emergency sensor triggers into instant, distinguishable vibrations and OLED visual displays (e.g., "CALLING BELL" or "EMERGENCY"), ensuring reliable, location-independent awareness through customizable patterns
A90: 88 | B90: S Thangavel | C90: COMPLETED | E90: 9750366570 | I90: IPO-mf2rwi | J90: SaaS, Bio Tech, IoT / Hardware | K90: https://docs.google.com/presentation/d/1O-4Y-K-HaEKILeDFo5VeCQkQP8ahl1TS/edit?usp=sharing&ouid=104277249549708518105&rtpof=true&sd=true | L90: Cortivue ("Cortisol + view — see your stress") is a wearable spectacles-based stress-sensing device, positioned against biosensor competitors like MUSE, Oura, Bella Beat, and Apple Watch — most of which offer only data visibility or single-metric feedback rather than integrated, actionable stress insight. Cortivue delivers personalized insight and action plans through smart glasses, with 66.1% of 2,217 surveyed consumers open to wearing sensor-equipped spectacles. Revenue model spans hardware sales, freemium/Pro/Enterprise subscriptions, B2B wellness dashboards, and API/SaaS licensing, targeting frame manufacturers, health-tech apps, insurers, and wellness brands as partners. Market sizing: TAM ~550M glasses-wearers globally, SAM ~44M in urban India, SOM ~66,000 users in 3 years (16.35% CAGR).
A91: 89 | B91: S Varshaa | C91: COMPLETED | D91: #N/A | E91: 9952048318 | F91: {=_xlfn.XLOOKUP(I91,startify3.0!I:I,startify3.0!A:A)} -> 30 | H91: yes | I91: SC-ywojqq | J91: AI / ML, EdTech, Deep Tech | K91: https://docs.google.com/presentation/d/1r_uJDDSgeSqdewnxUdc17ddlmhNFHjj7/edit?usp=sharing&ouid=104277249549708518105&rtpof=true&sd=true | L91: LearnSphere transforms overwhelming note-taking into an adaptive, gamified, AI-powered learning system for students, professionals, and researchers, addressing a gap where 90%+ of Indian learners lack effective self-study tools and existing apps (Notion, OneNote) are cluttered and unpersonalized. It combines a physical pen-and-paper writing experience (via a Digital Sleeve) with offline-first AI processing — multi-format capture, quiz/summary generation, spaced repetition, semantic search, flashcards, and peer hypothesis-discussion threads. Positioned against Neo Smartpen, XNote AI, Remarkable, GoodNotes, and Supernote, its differentiation is combining real pen feel + comprehensive AI learning + gamification, none of which competitors offer together, at more affordable pricing.
A92: 90 | B92: S. John Paul | C92: COMPLETED | E92: 9176775477 | F92: {=_xlfn.XLOOKUP(I92,startify3.0!I:I,startify3.0!A:A)} -> 58 | I92: SC-lvrbhd | J92: AgriTech, IoT / Hardware, App Development / Software, Deep Tech | K92: https://drive.google.com/file/d/1HRf_OMTsFfLIgp75MqT6IfnQd187-lg3/view?usp=sharing | L92: Flovepal Greenspace develops IoT-enabled smart plant pots designed to help urban residents easily grow and maintain indoor plants despite limited time, space, and knowledge. Targeting working professionals aged 25–45 in metro cities, the smart pot uses soil moisture sensors, automated irrigation, and a companion mobile app (Flutter + Firebase) to monitor plant health, send alerts, and provide personalized care tips. With eco-friendly 3D-printed casing and optional subscription-based app features, Flovepal follows a razor-and-blades revenue model (₹2000 per unit + ₹99/month). The solution promotes healthier indoor air, reduced stress, and sustainable urban living through effortless smart gardening
A93: 91 | B93: SA siva sooryaa | C93: COMPLETED | E93: 9488505516 | I93: IPO-7i7nb | J93: AgriTech, Enviro Tech, IoT / Hardware | K93: https://drive.google.com/file/d/1P71FvYpItc1HA5flnMDZjHqgEnahKtvC/view?usp=sharing | L93: Soil Steps is a multi-purpose solar-powered agri device targeting India's 82–86% marginal farmers (≤1 acre) who still depend on bullock carts and manual labor because affordable machinery for small plots is missing and large tractors are inaccessible. It's a compact, lightweight, all-terrain machine built for narrow, water-filled paddy fields, controlled remotely via an ESP32–BTS7960 system for easy use by elderly and marginal farmers. Its modular design supports eight detachable implements (leveller, bed former, bund shaper, ploughers, mud block remover) on a single chassis, replacing multiple separate tools. Running solely on solar power, it cuts fuel and maintenance costs, with expansion potential into Bangladesh, Nepal, and Africa's comparable marginal-farming markets.
A94: 92 | B94: Sadhana | C94: COMPLETED | D94: 45968 | E94: 6385256271 | F94: {=_xlfn.XLOOKUP(I94,startify3.0!I:I,startify3.0!A:A)} -> 29 | H94: yes | I94: SC-oyp2ts | J94: Bio Tech, AgriTech, Enviro Tech | K94: https://docs.google.com/presentation/d/12RsdTu1tH7jx2uQYyNA2C3v1dFMkZU0H/edit?usp=sharing&ouid=104277249549708518105&rtpof=true&sd=true | L94: Plant viruses cause $60 billion+ in annual global agricultural losses (FAO), threatening food security and farmer livelihoods, with smallholder farmers lacking affordable diagnostic tools because current methods (PCR/ELISA) are expensive, time-consuming, inaccessible, and detect infections too late to prevent damage. GenéGlow's "Fluorza" solution uses genetically engineered Pseudomonas fluorescens bacteria integrated with CRISPR-Cas9 technology to detect crop viral infections on-site within 24–48 hours through visible UV fluorescence, offering an affordable (₹100/unit) spray requiring no laboratory expertise or infrastructure, with built-in environmental "kill switch" biosafety and scalability across multiple crops and viral pathogens, empowering resource-limited farmers while reducing chemical pesticide dependency and promoting sustainable farming practices.
A95: 93 | B95: Saigovind V / Sadhana | C95: COMPLETED | E95: 9789095971 | F95: {=_xlfn.XLOOKUP(I95,startify3.0!I:I,startify3.0!A:A)} -> 151 | H95: yes | I95: SC-bgbq2f | J95: AI / ML, SaaS | K95: https://docs.google.com/presentation/d/1ENBbWjMrus_c-pGMptggJFsm1nLYauzS/edit?usp=sharing&ouid=104277249549708518105&rtpof=true&sd=true | L95: SyncField addresses the problem of fragmented IT and service delivery caused by small firms using multiple disconnected ERP and project management tools, leading to data silos, delayed updates, invisible risks, and compliance gaps that erode client trust and project success. SyncField proposes an AI-powered intelligence meta-layer that unifies existing ERP and PM tools without replacing them, introducing Aegis—an escalation prediction and prevention engine—alongside Trust Ledger for accountability, Client Visualiser for transparency, Smart Nudge Engine for proactive alerts, and SyncField Green for ESG regulatory compliance, enabling IT SMBs to orchestrate delivery, control risks, and meet sustainability goals in real time.
A96: 94 | B96: Sakthivel S | C96: COMPLETED | E96: 9944085762 | I96: CEDAU-09 | J96: AI / ML, SaaS | K96: https://docs.google.com/presentation/d/1PSNb4KAfoToZb3vJ3ZDzvwtjMzaZ7y4H/edit?usp=sharing&ouid=104277249549708518105&rtpof=true&sd=true | L96: EventBoost is an AI-powered "smart support system" plugging into existing event-management platforms rather than replacing them, tackling a gap where organizers (college fests, weddings, expos, corporate events) lack intelligent vendor/sponsor matching and dynamic pricing tools. It layers rule-based and ML-driven vendor, speaker, and sponsor-matching engines, plus reinforcement-learning pricing suggestions, on top of ticketing platforms like BookMyShow or Townscript via REST APIs, embeddable widgets, or white-label SaaS. Revenue combines freemium/Pro subscriptions (₹1,999/month), 3–5% commission on bookings, and white-label deals — targeting India's 20,000+ college fests and 50,000+ wedding/event planners, projecting 12,000 organizers and ₹5.1 Cr revenue by 2029. Early pilot metrics show 95% of users reporting time savings.
B97: Sandiep Lakshman | C97: COMPLETED | D97: 14/11/25 | E97: 9944039984 | F97: {=_xlfn.XLOOKUP(I97,startify3.0!I:I,startify3.0!A:A)} -> 169 | H97: yes | I97: SC-vm5wp7
A98: 95 | B98: Salonica D | C98: COMPLETED | E98: 8825987128 | F98: {=_xlfn.XLOOKUP(I98,startify3.0!I:I,startify3.0!A:A)} -> 71 | H98: yes | I98: SC-ox0pjd | J98: Bio Tech, AgriTech, Enviro Tech, Consumables | K98: https://docs.google.com/presentation/d/1nHZJs4i8lSAPFeGmnNbmIfUuscVuCEPM/edit?usp=sharing&ouid=104277249549708518105&rtpof=true&sd=true | L98: PlumeXB valorizes poultry feather keratin waste—millions of tons annually landfilled/incinerated, polluting water/soil/communities—via novel thermo-microbial enzymatic process using dual-pulse steaming pretreatment + underexplored microbes (Arthrobacter arilaitensis & Aeribacillus pallidus) for solid-state fermentation, yielding dual high-value products: antimicrobial peptides (AMPs) tackling antibiotic resistance for healthcare/cosmetics + eco-friendly biofertilizers, enabling zero-discharge circular bioeconomy vs single-output competitors (harsh chemical/Bacillus fertilizer-only, high-energy synthetic AMPs like IFFCO/Cipla). Superior sustainability/product value positions it ahead in competitive matrix
A99: 96 | B99: Sanjeev Misd | C99: COMPLETED | E99: 9080861148 | I99: SC-n4aonf | J99: AI / ML, AgriTech, IoT / Hardware, Deep Tech , Robotics / Automation | K99: https://docs.google.com/presentation/d/11pbQZHDGUguVuSuwEOLjm3MfecqFhYTM/edit?usp=sharing&ouid=104277249549708518105&rtpof=true&sd=true | L99: MISD Automation makes Autonomous Precision Agriculture Drone represents the cutting edge of agricultural technology, combining advanced AI-driven swarm coordination with precision farming capabilities. Our system enables farmers to monitor vast agricultural areas with unprecedented accuracy and efficiency.Featuring coordinated drone swarms that work in perfect harmony, this solution provides real-time crop monitoring, soil analysis, and targeted spraying operations. The drones are equipped with multispectral cameras, advanced sensors, and AI-powered analytics to deliver actionable insights for optimal crop management.Designed for large-scale agricultural operations, the system can cover thousands of acres in a single flight, collecting data on crop health, soil moisture levels, pest detection, and irrigation needs. The autonomous operation reduces labor costs while increasing precision and yield optimization.
A100: 97 | B100: Santhoshjeferson | C100: COMPLETED | D100: 13/2/2026 | E100: 8903672237 | F100: {=_xlfn.XLOOKUP(I100,startify3.0!I:I,startify3.0!A:A)} -> 172 | H100: yes | I100: SS-gxk3kp | J100: Consumables , Hardware | K100: https://docs.google.com/presentation/d/1Tj9hcJg78Kfgp5-s1rqG-Ao1ByvAKk-C/edit?usp=sharing&ouid=104277249549708518105&rtpof=true&sd=true | L100: Jefey Composites develops lignin-activated wood dust granules for Wood Plastic Composites (WPC) via mechanical press briquetting, enabling higher wood loading, superior tensile/flexural strength, lower water absorption, better dimensional/UV/thermal stability vs standard wood flour+PE/PP/PVC (moisture-sensitive, brittle, UV-unstable). It reduces petroleum dependency (30-40% renewable content), CO₂ footprint, and costs using low-cost lignin waste from paper/pulp/bio-refineries (Composites Part A/Bioresource Tech review cited).
...
